Workbook

Sheet Dashboard
B1: PORTFOLIO FIDELITY 2024
B2: OVERVIEW | F2: PERFORMANCE | J2: DIVIDEND STATS | N2: DIVIDEND INCOME EXPECTED | S2: Total Holdings: | W2: Notes
B3: Cost Basis | D3: Market Value | F3: Market Return ($) | H3: Market Return (%) | J3: Dividend Yield | L3: Yield On Cost | N3: Annual | P3: Monthly | S3: =Positions!A32 -> 17 | W3: Investment Strategy:
B4: =Positions!AA32 -> 34841.691 | D4: =Positions!AB32 -> 40306.351 | F4: =Positions!O32 -> 5464.6604 | H4: =Positions!Q32 -> 0.20328763 | J4: =Positions!X32 -> 0.021898336 | L4: =Positions!Y32 -> 0.025332927 | N4: =Positions!AC32 -> 882.64201 | P4: =(N4/12) -> 73.553501 | W4: - Focus on using capital for dividend growth companies and potential capital gains. - Increase allocation in ETFs/index funds. - Keep cash position between 10% and 15%. - Max allocation: 10% per stock and 20% per ETF. - No more than 30 holdings.
B5: Day Gain ($) | D5: Day Gain (%) | F5: Total Return ($) | H5: Total Return (%) | J5: Div. Growth Rate | L5: Div. Received | N5: Weekly | P5: Daily
B6: =Positions!K32 -> -149.30738 | D6: =Positions!J32 -> -0.0037180869 | F6: =Positions!P32 -> 6471.6504 | H6: =Positions!R32 -> 0.24074808 | J6: =Positions!Z32 -> 0.045599895 | L6: =Positions!AE32 -> 1006.99 | N6: =(N4/52) -> 16.973885 | P6: =(N4/365) -> 2.4181973 | W6: Advice to keep in mind:
B7: CASH | F7: SOLD POSITIONS | J7: ESTIMATED TAXES (2024) | N7: DIVIDEND INCOME CUMULATED | W7: - Take some profits from all positions that don't align with long-term goals by trimming or selling if: * growth type: when they fully recover or are overvalued. * value type: when they cut the dividend. - Rebalance the portfolio to align with the allocation target by adding money in specific categories and cutting some positions if they are too overexposed. - Find a sweet spot between not selling at all, no matter what, and selling if the company is overvalued, no matter what. * If the position is highly overvalued and rebalancing others cannot reduce its allocation, trimming it and taking profits could make sense. Otherwise, adding to other positions reduces the allocation of the one that is overexposed. - Don't overthink whether the business is good by waiting for the right price. Don't let stock price inform valuation opinion. Just go for it; don't miss the opportunity to enter right away or to keep increasing your position. - Don't skip your portfolio contributions; try to deposit at least a small amount every month.
B8: Available to trade | F8: Market Return ($) | J8: Dividend | L8: Sold Positions | N8: Annual | P8: Monthly
B9: =Positions!C34 -> 7960.27 | F9: ='Sold Positions'!I16 -> -95.078 | J9: ='Dividend Log'!AG4 -> 9.0456 | L9: ='Sold Positions'!M16 -> 0 | N9: ='Dividend Log'!N1 -> 886.2 | P9: =(N9/12) -> 73.85
B10: Weighting (Market Value) | F10: Total Return ($) | J10: Total | N10: Weekly | P10: Daily
B11: =Positions!C35 -> 0.19749419 | F11: ='Sold Positions'!J16 -> -88.378 | J11: =J9+L9 -> 9.0456 | N11: =(N9/52) -> 17.042308 | P11: =(N9/365) -> 2.4279452
W25: Opportunities Screening
W27: Watchlist | Y27: Portfolio
W29: =Watchlist!A2 -> AAPL | X29: =Watchlist!W2 -> Overrated | Y29: =Positions!A2 -> GOOGL | Z29: =Positions!AJ2 -> Hold
W30: =Watchlist!A3 -> V | X30: =Watchlist!W3 -> Overrated | Y30: =Positions!A3 -> MSFT | Z30: =Positions!AJ3 -> Avg. Cost
W31: =Watchlist!A4 -> PEP | X31: =Watchlist!W4 -> Overrated | Y31: =Positions!A4 -> DIS | Z31: =Positions!AJ4 -> Overcost
W32: =Watchlist!A5 -> MO | X32: =Watchlist!W5 -> Strong Buy | Y32: =Positions!A5 -> TGT | Z32: =Positions!AJ5 -> Avg. Cost
W33: =Watchlist!A6 -> ABBV | X33: =Watchlist!W6 -> Overrated | Y33: =Positions!A6 -> SBUX | Z33: =Positions!AJ6 -> Hold
W34: =Watchlist!A7 -> JNJ | X34: =Watchlist!W7 -> Overrated | Y34: =Positions!A7 -> JPM | Z34: =Positions!AJ7 -> Hold
W35: =Watchlist!A8 -> COST | X35: =Watchlist!W8 -> Overrated | Y35: =Positions!A8 -> KO | Z35: =Positions!AJ8 -> Hold
W36: =Watchlist!A9 -> TXRH | X36: =Watchlist!W9 -> Overrated | Y36: =Positions!A9 -> O | Z36: =Positions!AJ9 -> Hold
W37: =Watchlist!A10 -> CMG | X37: =Watchlist!W10 -> Overrated | Y37: =Positions!A10 -> VICI | Z37: =Positions!AJ10 -> Avg. Cost
W38: =Watchlist!A11 -> STZ | X38: =Watchlist!W11 -> Expensive | Y38: =Positions!A11 -> UNH | Z38: =Positions!AJ11 -> Overcost
W39: =Watchlist!A12 -> CMCSA | X39: =Watchlist!W12 -> Strong Buy | Y39: =Positions!A12 -> VGT | Z39: =Positions!AJ12 -> Hold
W40: =Watchlist!A13 -> CVX | X40: =Watchlist!W13 -> Buy | Y40: =Positions!A13 -> VOO | Z40: =Positions!AJ13 -> Hold
... W49: =Watchlist!A22 | X49: =Watchlist!W22 | Y49: =Positions!A22 | Z49: =Positions!AJ22
W50: =Watchlist!A23 | X50: =Watchlist!W23 | Z50: =Positions!AJ23
B52: Dividend Dashboard | S52: Performance
S55: YTD Annual Return | W55: Portfolio Projection
S56: Portfolio | V56: ='Annual Data'!F3 -> 0 | W56: Years | Y56: ='Portfolio Projections'!N3 -> 20
S58: S&P 500 | V58: ='Annual Data'!G3 -> 0.1788 | W58: Projected Value | Y58: ='Portfolio Projections'!L15 -> 1628754.8
S60: Difference | V60: =V56-V58 -> -0.1788 | W60: Monthly Contrib. | Y60: ='Portfolio Projections'!B6 -> 1500
B98: Foward Income Expected Goals | S98: All times Portfolio Income Rank
B100: $1 a day | D100: $50 a month | F100: $100 a month | H100: $5 a day | J100: $200 a month | L100: $500 a month | N100: $1000 a month | P100: $2000 a month | S100: ✅ Top Dividend Payers | W100: ❌ Bottom Dividend Payers
S101: 1st | T101: {=INDEX('Dividend Log'!$B$2:$AF$2, MATCH(LARGE('Dividend Log'!$B$3:$AF$3, 1), 'Dividend Log'!$B$3:$AF$3, 0))} -> SCHD | V101: =LARGE('Dividend Log'!$B$3:$AF$3, 1) -> 197.34 | W101: 1st | X101: =IFERROR(__xludf.DUMMYFUNCTION("INDEX('Dividend Log'!$B$2:$AF$2, MATCH(SMALL(FILTER('Dividend Log'!$B$3:$AF$3,'Dividend Log'!$B$3:$AF$3>0), 1), 'Dividend Log'!$B$3:$AF$3, 0))"),"GOOGL") -> GOOGL | Z101: =IFERROR(__xludf.DUMMYFUNCTION("SMALL(FILTER('Dividend Log'!$B$3:$AF$3,'Dividend Log'!$B$3:$AF$3>0), 1)"),5.67) -> 5.67
B102: =IF($P$6/1>1, "✅ Achieved", "⏳ In Progress: " & TEXT($P$6/1, "0%")) -> ✅ Achieved | D102: =IF($P$4/50>1, "✅ Achieved", "⏳ In Progress: " & TEXT($P$4/50, "0%")) -> ✅ Achieved | F102: =IF($P$4/100>1, "✅ Achieved", "⏳ In Progress: " & TEXT($P$4/100, "0%")) -> ⏳ In Progress: 74% | H102: =IF($P$6/5>1, "✅ Achieved", "⏳ In Progress: " & TEXT($P$6/5, "0%")) -> ⏳ In Progress: 48% | J102: =IF($P$4/200>1, "✅ Achieved", "⏳ In Progress: " & TEXT($P$4/200, "0%")) -> ⏳ In Progress: 37% | L102: =IF($P$4/500>1, "✅ Achieved", "⏳ In Progress: " & TEXT($P$4/500, "0%")) -> ⏳ In Progress: 15% | N102: =IF($P$4/1000>1, "✅ Achieved", "⏳ In Progress: " & TEXT($P$4/1000, "0%")) -> ⏳ In Progress: 7% | P102: =IF($P$4/2000>1, "✅ Achieved", "⏳ In Progress: " & TEXT($P$4/2000, "0%")) -> ⏳ In Progress: 4%
S103: 2nd | T103: {=INDEX('Dividend Log'!$B$2:$AF$2, MATCH(LARGE('Dividend Log'!$B$3:$AF$3, 2), 'Dividend Log'!$B$3:$AF$3, 0))} -> SPAXX | V103: =LARGE('Dividend Log'!$B$3:$AF$3, 2) -> 180.66 | W103: 2nd | X103: =IFERROR(__xludf.DUMMYFUNCTION("INDEX('Dividend Log'!$B$2:$AF$2, MATCH(SMALL(FILTER('Dividend Log'!$B$3:$AF$3,'Dividend Log'!$B$3:$AF$3>0), 2), 'Dividend Log'!$B$3:$AF$3, 0))"),"VIG") -> VIG | Z103: =IFERROR(__xludf.DUMMYFUNCTION("SMALL(FILTER('Dividend Log'!$B$3:$AF$3,'Dividend Log'!$B$3:$AF$3>0), 2)"),6.25) -> 6.25
S105: 3rd | T105: {=INDEX('Dividend Log'!$B$2:$AF$2, MATCH(LARGE('Dividend Log'!$B$3:$AF$3, 3), 'Dividend Log'!$B$3:$AF$3, 0))} -> TGT | V105: =LARGE('Dividend Log'!$B$3:$AF$3, 3) -> 172.39 | W105: 3rd | X105: =IFERROR(__xludf.DUMMYFUNCTION("INDEX('Dividend Log'!$B$2:$AF$2, MATCH(SMALL(FILTER('Dividend Log'!$B$3:$AF$3,'Dividend Log'!$B$3:$AF$3>0), 3), 'Dividend Log'!$B$3:$AF$3, 0))"),"BND") -> BND | Z105: =IFERROR(__xludf.DUMMYFUNCTION("SMALL(FILTER('Dividend Log'!$B$3:$AF$3,'Dividend Log'!$B$3:$AF$3>0), 3)"),8.45) -> 8.45
S107: 4th | T107: {=INDEX('Dividend Log'!$B$2:$AF$2, MATCH(LARGE('Dividend Log'!$B$3:$AF$3, 4), 'Dividend Log'!$B$3:$AF$3, 0))} -> O | V107: =LARGE('Dividend Log'!$B$3:$AF$3, 4) -> 124 | W107: 4th | X107: =IFERROR(__xludf.DUMMYFUNCTION("INDEX('Dividend Log'!$B$2:$AF$2, MATCH(SMALL(FILTER('Dividend Log'!$B$3:$AF$3,'Dividend Log'!$B$3:$AF$3>0), 4), 'Dividend Log'!$B$3:$AF$3, 0))"),"VGT") -> VGT | Z107: =IFERROR(__xludf.DUMMYFUNCTION("SMALL(FILTER('Dividend Log'!$B$3:$AF$3,'Dividend Log'!$B$3:$AF$3>0), 4)"),10.16) -> 10.16
S109: 5th | T109: {=INDEX('Dividend Log'!$B$2:$AF$2, MATCH(LARGE('Dividend Log'!$B$3:$AF$3, 5), 'Dividend Log'!$B$3:$AF$3, 0))} -> VXUS | V109: =LARGE('Dividend Log'!$B$3:$AF$3, 5) -> 51.61 | W109: 5th | X109: =IFERROR(__xludf.DUMMYFUNCTION("INDEX('Dividend Log'!$B$2:$AF$2, MATCH(SMALL(FILTER('Dividend Log'!$B$3:$AF$3,'Dividend Log'!$B$3:$AF$3>0), 5), 'Dividend Log'!$B$3:$AF$3, 0))"),"SBUX") -> SBUX | Z109: =IFERROR(__xludf.DUMMYFUNCTION("SMALL(FILTER('Dividend Log'!$B$3:$AF$3,'Dividend Log'!$B$3:$AF$3>0), 5)"),12.43) -> 12.43
S111: Percent of Total Income | V111: =SUM(V101:V110)/$N$9 -> 0.81922817 | W111: Percent of Total Income | Z111: =SUM(Z101:Z110)/$N$9 -> 0.048476642

Sheet Claude Cache
A1: ⚠️ SHEET RESERVED FOR =CLAUDE... FUNCTIONS. DO NOT EDIT! ⚠️
A2: Key | B2: Value | C2: Expiration

Sheet Positions
A1: Ticker | B1: Company Name | C1: View On Seeking Alpha | D1: # of Shares | E1: Avg. Cost Per Share | F1: Share Price | G1: Intrinsic Value | H1: InvT Score | I1: Day Change / Share ($) | J1: Day Change / Share (%) | K1: Overall Day Change ($) | L1: 52 Week Low | M1: 52 Week Range | N1: 52 Week High | O1: Market Return ($) | P1: Total Return ($) | Q1: Market Return (%) | R1: Total Return (%) | S1: Security Type | T1: Sector | U1: Category | V1: Portfolio Allocation | W1: Annual Dividend | X1: Dividend Yield | Y1: Yield On Cost | Z1: 5 Year Dividend Growth Rate | AA1: Cost Basis | AB1: Market Value | AC1: Annual Dividend Income | AD1: Percentage of Total Income | AE1: Total Dividends Received | AF1: Annual Shares Purch. w/ Div. | AG1: Distance From Intrinsic Value | AH1: Intrinsic Value Signal | AI1: Distance From Avg. Cost | AJ1: Avg. Cost Signal | AK1: DO NOT DELETE THIS COLUMN
A2: GOOGL | B2: =IFERROR(__xludf.DUMMYFUNCTION("IF(ISBLANK(A2),"""", googlefinance(A2, ""name""))"),"Alphabet Inc Class A") -> Alphabet Inc Class A | C2: =IF(ISBLANK(A2),"", HYPERLINK("https://seekingalpha.com/symbol/" & A2,"View")) -> View | D2: 9.025 | E2: 154.48 | F2: =IFERROR(__xludf.DUMMYFUNCTION("IF(ISBLANK(A2),"""", googlefinance(A2, ""price""))"),300.88) -> 300.88 | G2: =IF(ISBLANK(A2),"",IFERROR(VLOOKUP(A2, 'Intrinsic Values List'!$A$2:$D$70, 4, FALSE), "Not Found" )) -> 187.26 | H2: =IF(ISBLANK(A2),"",IFERROR(VLOOKUP(A2, 'Intrinsic Values List'!$A$2:$G$70, 7, FALSE), "Not Found" )) -> 8.58 | I2: =IFERROR(__xludf.DUMMYFUNCTION("IFERROR(googlefinance(A2,""change""),"""")"),-2.25) -> -2.25 | J2: =IFERROR(__xludf.DUMMYFUNCTION("iferror(GOOGLEFINANCE(A2,""changepct"")/100,"""")"),-0.0074) -> -0.0074 | K2: =if(isblank(A2),"",(D2*I2)) -> -20.30625 | L2: =IFERROR(__xludf.DUMMYFUNCTION("IF(ISBLANK(A2),"""", googlefinance(A2, ""low52""))"),140.53) -> 140.53 | M2: =IFERROR(__xludf.DUMMYFUNCTION("IF(ISBLANK(A2),"""",IFERROR(SPARKLINE((F2-L2)/(N2-L2),{""charttype"",""bar"";""max"",1;""min"",0;""color1"",""2c79b5""}),""n/a""))"),"") | N2: =IFERROR(__xludf.DUMMYFUNCTION("IF(ISBLANK(A2),"""", googlefinance(A2, ""high52""))"),349.0) -> 349 | O2: =if(isblank(A2),"",(F2-E2)*D2) -> 1321.26 | P2: =if(isblank(A2),"",O2+AE2) -> 1326.93 | Q2: =iferror(if(D2<0,0,O2/(E2*D2)),"") -> 0.94769549 | R2: =if(isblank(A2),"",P2/(E2*D2)) -> 0.9517624 | S2: Stocks | T2: Information Technology | U2: Growth | V2: =if(isblank(A2),"",AB2/$AB$32) -> 0.067370077 | W2: =IFERROR(__xludf.DUMMYFUNCTION("IfError(IF(isblank(A2),"""",split(AK2, ""()"")))"),0.83) -> 0.83 | X2: =IFERROR(__xludf.DUMMYFUNCTION("""COMPUTED_VALUE"""),0.0028) -> 0.0028 | Y2: =IFERROR(W2/E2,"") -> 0.0053728638 | Z2: 0 | AA2: =iferror(if(isblank(A2),"",D2*E2),0) -> 1394.182 | AB2: =IF(ISBLANK(A2),"",D2*F2) -> 2715.442 | AC2: =IFERROR(IF(ISBLANK(A2),"",D2*W2),"") -> 7.49075 | AD2: =if(isblank(A2),"",AC2/$AC$32) -> 0.0084867363 | AE2: =IF(ISBLANK($A2),"",SUM(OFFSET('Dividend Log'!$B$17, 0, ROW($A2)-2), OFFSET('Dividend Log'!$B$31, 0, ROW($A2)-2), OFFSET('Dividend Log'!$B$45, 0, ROW($A2)-2), OFFSET('Dividend Log'!$B$59, 0, ROW($A2)-2), OFFSET('Dividend Log'!$B$73, 0, ROW($A2)-2))) -> 5.67 | AF2: =IFERROR(AC2/F2,"") -> 0.024896138 | AG2: =iferror(IF(ISBLANK(G2),"",(F2-G2)/G2),"") -> 0.60674997 | AH2: =IF(AG2="", "", IF(AG2<=-15%, "Strong Buy", IF(AG2<0%, "Buy", IF(AG2<=15%, "Expensive", "Overrated")))) -> Overrated | AI2: =IF(ISBLANK(A2),"",(F2-E2)/E2) -> 0.94769549 | AJ2: =IF(A2="", "", IF(AI2<-15%, "Strong Buy", IF(AI2<-5%, "Buy", IF(AI2<5%, "Avg. Cost", IF(AI2<=15%, "Overcost", "Hold"))))) -> Hold | AK2: =IFERROR(__xludf.DUMMYFUNCTION("LET(t, A2, IF(t="""","""", IFERROR( SUBSTITUTE( INDEX( IMPORTXML( ""https://finviz.com/quote.ashx?t=""&t&""&ty=dv"", ""(//td[normalize-space()='Dividend TTM' or contains(.,'Dividend TTM')]/following-si"&"bling::td[1])[1]"" ),1,1), ""*"",""""), IFERROR( SUBSTITUTE( INDEX( IMPORTXML( ""https://finviz.com/quote.ashx?t=""&t, ""(//td[normalize-space()='Dividend']/following-sibling:"&":td[1])[1]"" ),1,1), ""*"",""""), """") ) ) ) "),"0.83 (0.28%)") -> 0.83 (0.28%)
A3: MSFT | B3: =IFERROR(__xludf.DUMMYFUNCTION("IF(ISBLANK(A3),"""", googlefinance(A3, ""name""))"),"Microsoft Corp") -> Microsoft Corp | C3: =IF(ISBLANK(A3),"", HYPERLINK("https://seekingalpha.com/symbol/" & A3,"View")) -> View | D3: 9.552 | E3: 393.4 | F3: =IFERROR(__xludf.DUMMYFUNCTION("IF(ISBLANK(A3),"""", googlefinance(A3, ""price""))"),410.68) -> 410.68 | G3: =IF(ISBLANK(A3),"",IFERROR(VLOOKUP(A3, 'Intrinsic Values List'!$A$2:$D$70, 4, FALSE), "Not Found" )) -> 334 | H3: =IF(ISBLANK(A3),"",IFERROR(VLOOKUP(A3, 'Intrinsic Values List'!$A$2:$G$70, 7, FALSE), "Not Found" )) -> 8.74 | I3: =IFERROR(__xludf.DUMMYFUNCTION("IFERROR(googlefinance(A3,""change""),"""")"),5.48) -> 5.48 | J3: =IFERROR(__xludf.DUMMYFUNCTION("iferror(GOOGLEFINANCE(A3,""changepct"")/100,"""")"),0.013500000000000002) -> 0.0135 | K3: =if(isblank(A3),"",(D3*I3)) -> 52.34496 | L3: =IFERROR(__xludf.DUMMYFUNCTION("IF(ISBLANK(A3),"""", googlefinance(A3, ""low52""))"),344.79) -> 344.79 | M3: =IFERROR(__xludf.DUMMYFUNCTION("IF(ISBLANK(A3),"""",IFERROR(SPARKLINE((F3-L3)/(N3-L3),{""charttype"",""bar"";""max"",1;""min"",0;""color1"",""2c79b5""}),""n/a""))"),"") | N3: =IFERROR(__xludf.DUMMYFUNCTION("IF(ISBLANK(A3),"""", googlefinance(A3, ""high52""))"),555.45) -> 555.45 | O3: =if(isblank(A3),"",(F3-E3)*D3) -> 165.05856 | P3: =if(isblank(A3),"",O3+AE3) -> 198.08856 | Q3: =iferror(if(D3<0,0,O3/(E3*D3)),"") -> 0.043924759 | R3: =if(isblank(A3),"",P3/(E3*D3)) -> 0.052714577 | S3: Stocks | T3: Information Technology | U3: Growth | V3: =if(isblank(A3),"",AB3/$AB$32) -> 0.097324993 | W3: =IFERROR(__xludf.DUMMYFUNCTION("IfError(IF(isblank(A3),"""",split(AK3, ""()"")))"),"") | Y3: =IFERROR(W3/E3,"") -> 0 | Z3: 0.102 | AA3: =iferror(if(isblank(A3),"",D3*E3),0) -> 3757.7568 | AB3: =IF(ISBLANK(A3),"",D3*F3) -> 3922.8154 | AC3: =IFERROR(IF(ISBLANK(A3),"",D3*W3),"") -> 0 | AD3: =if(isblank(A3),"",AC3/$AC$32) -> 0 | AE3: =IF(ISBLANK($A3),"",SUM(OFFSET('Dividend Log'!$B$17, 0, ROW($A3)-2), OFFSET('Dividend Log'!$B$31, 0, ROW($A3)-2), OFFSET('Dividend Log'!$B$45, 0, ROW($A3)-2), OFFSET('Dividend Log'!$B$59, 0, ROW($A3)-2), OFFSET('Dividend Log'!$B$73, 0, ROW($A3)-2))) -> 33.03 | AF3: =IFERROR(AC3/F3,"") -> 0 | AG3: =iferror(IF(ISBLANK(G3),"",(F3-G3)/G3),"") -> 0.22958084 | AH3: =IF(AG3="", "", IF(AG3<=-15%, "Strong Buy", IF(AG3<0%, "Buy", IF(AG3<=15%, "Expensive", "Overrated")))) -> Overrated | AI3: =IF(ISBLANK(A3),"",(F3-E3)/E3) -> 0.043924759 | AJ3: =IF(A3="", "", IF(AI3<-15%, "Strong Buy", IF(AI3<-5%, "Buy", IF(AI3<5%, "Avg. Cost", IF(AI3<=15%, "Overcost", "Hold"))))) -> Avg. Cost | AK3: =IFERROR(__xludf.DUMMYFUNCTION("LET(t, A3, IF(t="""","""", IFERROR( SUBSTITUTE( INDEX( IMPORTXML( ""https://finviz.com/quote.ashx?t=""&t&""&ty=dv"", ""(//td[normalize-space()='Dividend TTM' or contains(.,'Dividend TTM')]/following-si"&"bling::td[1])[1]"" ),1,1), ""*"",""""), IFERROR( SUBSTITUTE( INDEX( IMPORTXML( ""https://finviz.com/quote.ashx?t=""&t, ""(//td[normalize-space()='Dividend']/following-sibling:"&":td[1])[1]"" ),1,1), ""*"",""""), """") ) ) ) "),"")
A4: DIS | B4: =IFERROR(__xludf.DUMMYFUNCTION("IF(ISBLANK(A4),"""", googlefinance(A4, ""name""))"),"Walt Disney Co") -> Walt Disney Co | C4: =IF(ISBLANK(A4),"", HYPERLINK("https://seekingalpha.com/symbol/" & A4,"View")) -> View | D4: 17.264 | E4: 93.48 | F4: =IFERROR(__xludf.DUMMYFUNCTION("IF(ISBLANK(A4),"""", googlefinance(A4, ""price""))"),102.41) -> 102.41 | G4: =IF(ISBLANK(A4),"",IFERROR(VLOOKUP(A4, 'Intrinsic Values List'!$A$2:$D$70, 4, FALSE), "Not Found" )) -> 89.15 | H4: =IF(ISBLANK(A4),"",IFERROR(VLOOKUP(A4, 'Intrinsic Values List'!$A$2:$G$70, 7, FALSE), "Not Found" )) -> 3.29 | I4: =IFERROR(__xludf.DUMMYFUNCTION("IFERROR(googlefinance(A4,""change""),"""")"),-0.63) -> -0.63 | J4: =IFERROR(__xludf.DUMMYFUNCTION("iferror(GOOGLEFINANCE(A4,""changepct"")/100,"""")"),-0.0060999999999999995) -> -0.0061 | K4: =if(isblank(A4),"",(D4*I4)) -> -10.87632 | L4: =IFERROR(__xludf.DUMMYFUNCTION("IF(ISBLANK(A4),"""", googlefinance(A4, ""low52""))"),80.1) -> 80.1 | M4: =IFERROR(__xludf.DUMMYFUNCTION("IF(ISBLANK(A4),"""",IFERROR(SPARKLINE((F4-L4)/(N4-L4),{""charttype"",""bar"";""max"",1;""min"",0;""color1"",""2c79b5""}),""n/a""))"),"") | N4: =IFERROR(__xludf.DUMMYFUNCTION("IF(ISBLANK(A4),"""", googlefinance(A4, ""high52""))"),124.69) -> 124.69 | O4: =if(isblank(A4),"",(F4-E4)*D4) -> 154.16752 | P4: =if(isblank(A4),"",O4+AE4) -> 183.87752 | Q4: =iferror(if(D4<0,0,O4/(E4*D4)),"") -> 0.095528455 | R4: =if(isblank(A4),"",P4/(E4*D4)) -> 0.11393798 | S4: Stocks | T4: Communication Services | U4: Growth | V4: =if(isblank(A4),"",AB4/$AB$32) -> 0.04386421 | W4: =IFERROR(__xludf.DUMMYFUNCTION("IfError(IF(isblank(A4),"""",split(AK4, ""()"")))"),1.25) -> 1.25 | X4: =IFERROR(__xludf.DUMMYFUNCTION("""COMPUTED_VALUE"""),0.0122) -> 0.0122 | Y4: =IFERROR(W4/E4,"") -> 0.013371844 | Z4: -0.2948 | AA4: =iferror(if(isblank(A4),"",D4*E4),0) -> 1613.8387 | AB4: =IF(ISBLANK(A4),"",D4*F4) -> 1768.0062 | AC4: =IFERROR(IF(ISBLANK(A4),"",D4*W4),"") -> 21.58 | AD4: =if(isblank(A4),"",AC4/$AC$32) -> 0.024449323 | AE4: =IF(ISBLANK($A4),"",SUM(OFFSET('Dividend Log'!$B$17, 0, ROW($A4)-2), OFFSET('Dividend Log'!$B$31, 0, ROW($A4)-2), OFFSET('Dividend Log'!$B$45, 0, ROW($A4)-2), OFFSET('Dividend Log'!$B$59, 0, ROW($A4)-2), OFFSET('Dividend Log'!$B$73, 0, ROW($A4)-2))) -> 29.71 | AF4: =IFERROR(AC4/F4,"") -> 0.21072161 | AG4: =iferror(IF(ISBLANK(G4),"",(F4-G4)/G4),"") -> 0.14873808 | AH4: =IF(AG4="", "", IF(AG4<=-15%, "Strong Buy", IF(AG4<0%, "Buy", IF(AG4<=15%, "Expensive", "Overrated")))) -> Expensive | AI4: =IF(ISBLANK(A4),"",(F4-E4)/E4) -> 0.095528455 | AJ4: =IF(A4="", "", IF(AI4<-15%, "Strong Buy", IF(AI4<-5%, "Buy", IF(AI4<5%, "Avg. Cost", IF(AI4<=15%, "Overcost", "Hold"))))) -> Overcost | AK4: =IFERROR(__xludf.DUMMYFUNCTION("LET(t, A4, IF(t="""","""", IFERROR( SUBSTITUTE( INDEX( IMPORTXML( ""https://finviz.com/quote.ashx?t=""&t&""&ty=dv"", ""(//td[normalize-space()='Dividend TTM' or contains(.,'Dividend TTM')]/following-si"&"bling::td[1])[1]"" ),1,1), ""*"",""""), IFERROR( SUBSTITUTE( INDEX( IMPORTXML( ""https://finviz.com/quote.ashx?t=""&t, ""(//td[normalize-space()='Dividend']/following-sibling:"&":td[1])[1]"" ),1,1), ""*"",""""), """") ) ) ) "),"1.25 (1.22%)") -> 1.25 (1.22%)
A5: TGT | B5: =IFERROR(__xludf.DUMMYFUNCTION("IF(ISBLANK(A5),"""", googlefinance(A5, ""name""))"),"Target Corp") -> Target Corp | C5: =IF(ISBLANK(A5),"", HYPERLINK("https://seekingalpha.com/symbol/" & A5,"View")) -> View | D5: 31.358 | E5: 117.78 | F5: =IFERROR(__xludf.DUMMYFUNCTION("IF(ISBLANK(A5),"""", googlefinance(A5, ""price""))"),120.36) -> 120.36 | G5: =IF(ISBLANK(A5),"",IFERROR(VLOOKUP(A5, 'Intrinsic Values List'!$A$2:$D$70, 4, FALSE), "Not Found" )) -> 226.6 | H5: =IF(ISBLANK(A5),"",IFERROR(VLOOKUP(A5, 'Intrinsic Values List'!$A$2:$G$70, 7, FALSE), "Not Found" )) -> 6.59 | I5: =IFERROR(__xludf.DUMMYFUNCTION("IFERROR(googlefinance(A5,""change""),"""")"),0.28) -> 0.28 | J5: =IFERROR(__xludf.DUMMYFUNCTION("iferror(GOOGLEFINANCE(A5,""changepct"")/100,"""")"),0.0023) -> 0.0023 | K5: =if(isblank(A5),"",(D5*I5)) -> 8.78024 | L5: =IFERROR(__xludf.DUMMYFUNCTION("IF(ISBLANK(A5),"""", googlefinance(A5, ""low52""))"),83.44) -> 83.44 | M5: =IFERROR(__xludf.DUMMYFUNCTION("IF(ISBLANK(A5),"""",IFERROR(SPARKLINE((F5-L5)/(N5-L5),{""charttype"",""bar"";""max"",1;""min"",0;""color1"",""2c79b5""}),""n/a""))"),"") | N5: =IFERROR(__xludf.DUMMYFUNCTION("IF(ISBLANK(A5),"""", googlefinance(A5, ""high52""))"),126.0) -> 126 | O5: =if(isblank(A5),"",(F5-E5)*D5) -> 80.90364 | P5: =if(isblank(A5),"",O5+AE5) -> 253.29364 | Q5: =iferror(if(D5<0,0,O5/(E5*D5)),"") -> 0.021905247 | R5: =if(isblank(A5),"",P5/(E5*D5)) -> 0.068581089 | S5: Stocks | T5: Consumer Staples | U5: Growth | V5: =if(isblank(A5),"",AB5/$AB$32) -> 0.093639061 | W5: =IFERROR(__xludf.DUMMYFUNCTION("IfError(IF(isblank(A5),"""",split(AK5, ""()"")))"),4.54) -> 4.54 | X5: =IFERROR(__xludf.DUMMYFUNCTION("""COMPUTED_VALUE"""),0.0377) -> 0.0377 | Y5: =IFERROR(W5/E5,"") -> 0.038546443 | Z5: 0.1151 | AA5: =iferror(if(isblank(A5),"",D5*E5),0) -> 3693.3452 | AB5: =IF(ISBLANK(A5),"",D5*F5) -> 3774.2489 | AC5: =IFERROR(IF(ISBLANK(A5),"",D5*W5),"") -> 142.36532 | AD5: =if(isblank(A5),"",AC5/$AC$32) -> 0.16129452 | AE5: =IF(ISBLANK($A5),"",SUM(OFFSET('Dividend Log'!$B$17, 0, ROW($A5)-2), OFFSET('Dividend Log'!$B$31, 0, ROW($A5)-2), OFFSET('Dividend Log'!$B$45, 0, ROW($A5)-2), OFFSET('Dividend Log'!$B$59, 0, ROW($A5)-2), OFFSET('Dividend Log'!$B$73, 0, ROW($A5)-2))) -> 172.39 | AF5: =IFERROR(AC5/F5,"") -> 1.1828292 | AG5: =iferror(IF(ISBLANK(G5),"",(F5-G5)/G5),"") -> -0.46884378 | AH5: =IF(AG5="", "", IF(AG5<=-15%, "Strong Buy", IF(AG5<0%, "Buy", IF(AG5<=15%, "Expensive", "Overrated")))) -> Strong Buy | AI5: =IF(ISBLANK(A5),"",(F5-E5)/E5) -> 0.021905247 | AJ5: =IF(A5="", "", IF(AI5<-15%, "Strong Buy", IF(AI5<-5%, "Buy", IF(AI5<5%, "Avg. Cost", IF(AI5<=15%, "Overcost", "Hold"))))) -> Avg. Cost | AK5: =IFERROR(__xludf.DUMMYFUNCTION("LET(t, A5, IF(t="""","""", IFERROR( SUBSTITUTE( INDEX( IMPORTXML( ""https://finviz.com/quote.ashx?t=""&t&""&ty=dv"", ""(//td[normalize-space()='Dividend TTM' or contains(.,'Dividend TTM')]/following-si"&"bling::td[1])[1]"" ),1,1), ""*"",""""), IFERROR( SUBSTITUTE( INDEX( IMPORTXML( ""https://finviz.com/quote.ashx?t=""&t, ""(//td[normalize-space()='Dividend']/following-sibling:"&":td[1])[1]"" ),1,1), ""*"",""""), """") ) ) ) "),"4.54 (3.77%)") -> 4.54 (3.77%)
A6: SBUX | B6: =IFERROR(__xludf.DUMMYFUNCTION("IF(ISBLANK(A6),"""", googlefinance(A6, ""name""))"),"Starbucks Corp") -> Starbucks Corp | C6: =IF(ISBLANK(A6),"", HYPERLINK("https://seekingalpha.com/symbol/" & A6,"View")) -> View | D6: 5.071 | E6: 81.62 | F6: =IFERROR(__xludf.DUMMYFUNCTION("IF(ISBLANK(A6),"""", googlefinance(A6, ""price""))"),98.69) -> 98.69 | G6: =IF(ISBLANK(A6),"",IFERROR(VLOOKUP(A6, 'Intrinsic Values List'!$A$2:$D$70, 4, FALSE), "Not Found" )) -> 89.57 | H6: =IF(ISBLANK(A6),"",IFERROR(VLOOKUP(A6, 'Intrinsic Values List'!$A$2:$G$70, 7, FALSE), "Not Found" )) -> 5.17 | I6: =IFERROR(__xludf.DUMMYFUNCTION("IFERROR(googlefinance(A6,""change""),"""")"),1.54) -> 1.54 | J6: =IFERROR(__xludf.DUMMYFUNCTION("iferror(GOOGLEFINANCE(A6,""changepct"")/100,"""")"),0.0159) -> 0.0159 | K6: =if(isblank(A6),"",(D6*I6)) -> 7.80934 | L6: =IFERROR(__xludf.DUMMYFUNCTION("IF(ISBLANK(A6),"""", googlefinance(A6, ""low52""))"),75.5) -> 75.5 | M6: =IFERROR(__xludf.DUMMYFUNCTION("IF(ISBLANK(A6),"""",IFERROR(SPARKLINE((F6-L6)/(N6-L6),{""charttype"",""bar"";""max"",1;""min"",0;""color1"",""2c79b5""}),""n/a""))"),"") | N6: =IFERROR(__xludf.DUMMYFUNCTION("IF(ISBLANK(A6),"""", googlefinance(A6, ""high52""))"),110.43) -> 110.43 | O6: =if(isblank(A6),"",(F6-E6)*D6) -> 86.56197 | P6: =if(isblank(A6),"",O6+AE6) -> 98.99197 | Q6: =iferror(if(D6<0,0,O6/(E6*D6)),"") -> 0.20913992 | R6: =if(isblank(A6),"",P6/(E6*D6)) -> 0.23917169 | S6: Stocks | T6: Consumer Discretionary | U6: Growth | V6: =if(isblank(A6),"",AB6/$AB$32) -> 0.012416331 | W6: =IFERROR(__xludf.DUMMYFUNCTION("IfError(IF(isblank(A6),"""",split(AK6, ""()"")))"),2.46) -> 2.46 | X6: =IFERROR(__xludf.DUMMYFUNCTION("""COMPUTED_VALUE"""),0.0249) -> 0.0249 | Y6: =IFERROR(W6/E6,"") -> 0.030139672 | Z6: 0.075 | AA6: =iferror(if(isblank(A6),"",D6*E6),0) -> 413.89502 | AB6: =IF(ISBLANK(A6),"",D6*F6) -> 500.45699 | AC6: =IFERROR(IF(ISBLANK(A6),"",D6*W6),"") -> 12.47466 | AD6: =if(isblank(A6),"",AC6/$AC$32) -> 0.014133318 | AE6: =IF(ISBLANK($A6),"",SUM(OFFSET('Dividend Log'!$B$17, 0, ROW($A6)-2), OFFSET('Dividend Log'!$B$31, 0, ROW($A6)-2), OFFSET('Dividend Log'!$B$45, 0, ROW($A6)-2), OFFSET('Dividend Log'!$B$59, 0, ROW($A6)-2), OFFSET('Dividend Log'!$B$73, 0, ROW($A6)-2))) -> 12.43 | AF6: =IFERROR(AC6/F6,"") -> 0.12640247 | AG6: =iferror(IF(ISBLANK(G6),"",(F6-G6)/G6),"") -> 0.10181981 | AH6: =IF(AG6="", "", IF(AG6<=-15%, "Strong Buy", IF(AG6<0%, "Buy", IF(AG6<=15%, "Expensive", "Overrated")))) -> Expensive | AI6: =IF(ISBLANK(A6),"",(F6-E6)/E6) -> 0.20913992 | AJ6: =IF(A6="", "", IF(AI6<-15%, "Strong Buy", IF(AI6<-5%, "Buy", IF(AI6<5%, "Avg. Cost", IF(AI6<=15%, "Overcost", "Hold"))))) -> Hold | AK6: =IFERROR(__xludf.DUMMYFUNCTION("LET(t, A6, IF(t="""","""", IFERROR( SUBSTITUTE( INDEX( IMPORTXML( ""https://finviz.com/quote.ashx?t=""&t&""&ty=dv"", ""(//td[normalize-space()='Dividend TTM' or contains(.,'Dividend TTM')]/following-si"&"bling::td[1])[1]"" ),1,1), ""*"",""""), IFERROR( SUBSTITUTE( INDEX( IMPORTXML( ""https://finviz.com/quote.ashx?t=""&t, ""(//td[normalize-space()='Dividend']/following-sibling:"&":td[1])[1]"" ),1,1), ""*"",""""), """") ) ) ) "),"2.46 (2.49%)") -> 2.46 (2.49%)
A7: JPM | B7: =IFERROR(__xludf.DUMMYFUNCTION("IF(ISBLANK(A7),"""", googlefinance(A7, ""name""))"),"JPMorgan Chase & Co") -> JPMorgan Chase & Co | C7: =IF(ISBLANK(A7),"", HYPERLINK("https://seekingalpha.com/symbol/" & A7,"View")) -> View | D7: 2.057 | E7: 199.07 | F7: =IFERROR(__xludf.DUMMYFUNCTION("IF(ISBLANK(A7),"""", googlefinance(A7, ""price""))"),293.55) -> 293.55 | G7: =IF(ISBLANK(A7),"",IFERROR(VLOOKUP(A7, 'Intrinsic Values List'!$A$2:$D$70, 4, FALSE), "Not Found" )) -> 287.74 | H7: =IF(ISBLANK(A7),"",IFERROR(VLOOKUP(A7, 'Intrinsic Values List'!$A$2:$G$70, 7, FALSE), "Not Found" )) -> 6.82 | I7: =IFERROR(__xludf.DUMMYFUNCTION("IFERROR(googlefinance(A7,""change""),"""")"),-5.84) -> -5.84 | J7: =IFERROR(__xludf.DUMMYFUNCTION("iferror(GOOGLEFINANCE(A7,""changepct"")/100,"""")"),-0.0195) -> -0.0195 | K7: =if(isblank(A7),"",(D7*I7)) -> -12.01288 | L7: =IFERROR(__xludf.DUMMYFUNCTION("IF(ISBLANK(A7),"""", googlefinance(A7, ""low52""))"),202.16) -> 202.16 | M7: =IFERROR(__xludf.DUMMYFUNCTION("IF(ISBLANK(A7),"""",IFERROR(SPARKLINE((F7-L7)/(N7-L7),{""charttype"",""bar"";""max"",1;""min"",0;""color1"",""2c79b5""}),""n/a""))"),"") | N7: =IFERROR(__xludf.DUMMYFUNCTION("IF(ISBLANK(A7),"""", googlefinance(A7, ""high52""))"),337.25) -> 337.25 | O7: =if(isblank(A7),"",(F7-E7)*D7) -> 194.34536 | P7: =if(isblank(A7),"",O7+AE7) -> 212.37536 | Q7: =iferror(if(D7<0,0,O7/(E7*D7)),"") -> 0.47460692 | R7: =if(isblank(A7),"",P7/(E7*D7)) -> 0.51863763 | S7: Stocks | T7: Financials | U7: Value Stocks | V7: =if(isblank(A7),"",AB7/$AB$32) -> 0.014981072 | W7: =IFERROR(__xludf.DUMMYFUNCTION("IfError(IF(isblank(A7),"""",split(AK7, ""()"")))"),5.8) -> 5.8 | X7: =IFERROR(__xludf.DUMMYFUNCTION("""COMPUTED_VALUE"""),0.0198) -> 0.0198 | Y7: =IFERROR(W7/E7,"") -> 0.02913548 | Z7: 0.075 | AA7: =iferror(if(isblank(A7),"",D7*E7),0) -> 409.48699 | AB7: =IF(ISBLANK(A7),"",D7*F7) -> 603.83235 | AC7: =IFERROR(IF(ISBLANK(A7),"",D7*W7),"") -> 11.9306 | AD7: =if(isblank(A7),"",AC7/$AC$32) -> 0.013516918 | AE7: =IF(ISBLANK($A7),"",SUM(OFFSET('Dividend Log'!$B$17, 0, ROW($A7)-2), OFFSET('Dividend Log'!$B$31, 0, ROW($A7)-2), OFFSET('Dividend Log'!$B$45, 0, ROW($A7)-2), OFFSET('Dividend Log'!$B$59, 0, ROW($A7)-2), OFFSET('Dividend Log'!$B$73, 0, ROW($A7)-2))) -> 18.03 | AF7: =IFERROR(AC7/F7,"") -> 0.04064248 | AG7: =iferror(IF(ISBLANK(G7),"",(F7-G7)/G7),"") -> 0.02019184 | AH7: =IF(AG7="", "", IF(AG7<=-15%, "Strong Buy", IF(AG7<0%, "Buy", IF(AG7<=15%, "Expensive", "Overrated")))) -> Expensive | AI7: =IF(ISBLANK(A7),"",(F7-E7)/E7) -> 0.47460692 | AJ7: =IF(A7="", "", IF(AI7<-15%, "Strong Buy", IF(AI7<-5%, "Buy", IF(AI7<5%, "Avg. Cost", IF(AI7<=15%, "Overcost", "Hold"))))) -> Hold | AK7: =IFERROR(__xludf.DUMMYFUNCTION("LET(t, A7, IF(t="""","""", IFERROR( SUBSTITUTE( INDEX( IMPORTXML( ""https://finviz.com/quote.ashx?t=""&t&""&ty=dv"", ""(//td[normalize-space()='Dividend TTM' or contains(.,'Dividend TTM')]/following-si"&"bling::td[1])[1]"" ),1,1), ""*"",""""), IFERROR( SUBSTITUTE( INDEX( IMPORTXML( ""https://finviz.com/quote.ashx?t=""&t, ""(//td[normalize-space()='Dividend']/following-sibling:"&":td[1])[1]"" ),1,1), ""*"",""""), """") ) ) ) "),"5.80 (1.98%)") -> 5.80 (1.98%)
A8: KO | B8: =IFERROR(__xludf.DUMMYFUNCTION("IF(ISBLANK(A8),"""", googlefinance(A8, ""name""))"),"Coca-Cola Co") -> Coca-Cola Co | C8: =IF(ISBLANK(A8),"", HYPERLINK("https://seekingalpha.com/symbol/" & A8,"View")) -> View | D8: 11.418 | E8: 63.85 | F8: =IFERROR(__xludf.DUMMYFUNCTION("IF(ISBLANK(A8),"""", googlefinance(A8, ""price""))"),77.03) -> 77.03 | G8: =IF(ISBLANK(A8),"",IFERROR(VLOOKUP(A8, 'Intrinsic Values List'!$A$2:$D$70, 4, FALSE), "Not Found" )) -> 40.7 | H8: =IF(ISBLANK(A8),"",IFERROR(VLOOKUP(A8, 'Intrinsic Values List'!$A$2:$G$70, 7, FALSE), "Not Found" )) -> 6 | I8: =IFERROR(__xludf.DUMMYFUNCTION("IFERROR(googlefinance(A8,""change""),"""")"),-1.07) -> -1.07 | J8: =IFERROR(__xludf.DUMMYFUNCTION("iferror(GOOGLEFINANCE(A8,""changepct"")/100,"""")"),-0.0137) -> -0.0137 | K8: =if(isblank(A8),"",(D8*I8)) -> -12.21726 | L8: =IFERROR(__xludf.DUMMYFUNCTION("IF(ISBLANK(A8),"""", googlefinance(A8, ""low52""))"),65.35) -> 65.35 | M8: =IFERROR(__xludf.DUMMYFUNCTION("IF(ISBLANK(A8),"""",IFERROR(SPARKLINE((F8-L8)/(N8-L8),{""charttype"",""bar"";""max"",1;""min"",0;""color1"",""2c79b5""}),""n/a""))"),"") | N8: =IFERROR(__xludf.DUMMYFUNCTION("IF(ISBLANK(A8),"""", googlefinance(A8, ""high52""))"),82.0) -> 82 | O8: =if(isblank(A8),"",(F8-E8)*D8) -> 150.48924 | P8: =if(isblank(A8),"",O8+AE8) -> 179.22924 | Q8: =iferror(if(D8<0,0,O8/(E8*D8)),"") -> 0.2064213 | R8: =if(isblank(A8),"",P8/(E8*D8)) -> 0.24584304 | S8: Stocks | T8: Consumer Staples | U8: Value Stocks | V8: =if(isblank(A8),"",AB8/$AB$32) -> 0.021821091 | W8: =IFERROR(__xludf.DUMMYFUNCTION("IfError(IF(isblank(A8),"""",split(AK8, ""()"")))"),2.04) -> 2.04 | X8: =IFERROR(__xludf.DUMMYFUNCTION("""COMPUTED_VALUE"""),0.0265) -> 0.0265 | Y8: =IFERROR(W8/E8,"") -> 0.031949883 | Z8: 0.035 | AA8: =iferror(if(isblank(A8),"",D8*E8),0) -> 729.0393 | AB8: =IF(ISBLANK(A8),"",D8*F8) -> 879.52854 | AC8: =IFERROR(IF(ISBLANK(A8),"",D8*W8),"") -> 23.29272 | AD8: =if(isblank(A8),"",AC8/$AC$32) -> 0.02638977 | AE8: =IF(ISBLANK($A8),"",SUM(OFFSET('Dividend Log'!$B$17, 0, ROW($A8)-2), OFFSET('Dividend Log'!$B$31, 0, ROW($A8)-2), OFFSET('Dividend Log'!$B$45, 0, ROW($A8)-2), OFFSET('Dividend Log'!$B$59, 0, ROW($A8)-2), OFFSET('Dividend Log'!$B$73, 0, ROW($A8)-2))) -> 28.74 | AF8: =IFERROR(AC8/F8,"") -> 0.30238504 | AG8: =iferror(IF(ISBLANK(G8),"",(F8-G8)/G8),"") -> 0.89262899 | AH8: =IF(AG8="", "", IF(AG8<=-15%, "Strong Buy", IF(AG8<0%, "Buy", IF(AG8<=15%, "Expensive", "Overrated")))) -> Overrated | AI8: =IF(ISBLANK(A8),"",(F8-E8)/E8) -> 0.2064213 | AJ8: =IF(A8="", "", IF(AI8<-15%, "Strong Buy", IF(AI8<-5%, "Buy", IF(AI8<5%, "Avg. Cost", IF(AI8<=15%, "Overcost", "Hold"))))) -> Hold | AK8: =IFERROR(__xludf.DUMMYFUNCTION("LET(t, A8, IF(t="""","""", IFERROR( SUBSTITUTE( INDEX( IMPORTXML( ""https://finviz.com/quote.ashx?t=""&t&""&ty=dv"", ""(//td[normalize-space()='Dividend TTM' or contains(.,'Dividend TTM')]/following-si"&"bling::td[1])[1]"" ),1,1), ""*"",""""), IFERROR( SUBSTITUTE( INDEX( IMPORTXML( ""https://finviz.com/quote.ashx?t=""&t, ""(//td[normalize-space()='Dividend']/following-sibling:"&":td[1])[1]"" ),1,1), ""*"",""""), """") ) ) ) "),"2.04 (2.65%)") -> 2.04 (2.65%)
A9: O | B9: =IFERROR(__xludf.DUMMYFUNCTION("IF(ISBLANK(A9),"""", googlefinance(A9, ""name""))"),"Realty Income Corp") -> Realty Income Corp | C9: =IF(ISBLANK(A9),"", HYPERLINK("https://seekingalpha.com/symbol/" & A9,"View")) -> View | D9: 31.001 | E9: 54.62 | F9: =IFERROR(__xludf.DUMMYFUNCTION("IF(ISBLANK(A9),"""", googlefinance(A9, ""price""))"),64.8) -> 64.8 | G9: =IF(ISBLANK(A9),"",IFERROR(VLOOKUP(A9, 'Intrinsic Values List'!$A$2:$D$70, 4, FALSE), "Not Found" )) -> 33.62 | H9: =IF(ISBLANK(A9),"",IFERROR(VLOOKUP(A9, 'Intrinsic Values List'!$A$2:$G$70, 7, FALSE), "Not Found" )) -> 3.92 | I9: =IFERROR(__xludf.DUMMYFUNCTION("IFERROR(googlefinance(A9,""change""),"""")"),-1.2) -> -1.2 | J9: =IFERROR(__xludf.DUMMYFUNCTION("iferror(GOOGLEFINANCE(A9,""changepct"")/100,"""")"),-0.0182) -> -0.0182 | K9: =if(isblank(A9),"",(D9*I9)) -> -37.2012 | L9: =IFERROR(__xludf.DUMMYFUNCTION("IF(ISBLANK(A9),"""", googlefinance(A9, ""low52""))"),50.71) -> 50.71 | M9: =IFERROR(__xludf.DUMMYFUNCTION("IF(ISBLANK(A9),"""",IFERROR(SPARKLINE((F9-L9)/(N9-L9),{""charttype"",""bar"";""max"",1;""min"",0;""color1"",""2c79b5""}),""n/a""))"),"") | N9: =IFERROR(__xludf.DUMMYFUNCTION("IF(ISBLANK(A9),"""", googlefinance(A9, ""high52""))"),67.94) -> 67.94 | O9: =if(isblank(A9),"",(F9-E9)*D9) -> 315.59018 | P9: =if(isblank(A9),"",O9+AE9) -> 439.59018 | Q9: =iferror(if(D9<0,0,O9/(E9*D9)),"") -> 0.18637862 | R9: =if(isblank(A9),"",P9/(E9*D9)) -> 0.2596095 | S9: Stocks | T9: Real Estate | U9: Value Stocks | V9: =if(isblank(A9),"",AB9/$AB$32) -> 0.049839907 | W9: =IFERROR(__xludf.DUMMYFUNCTION("IfError(IF(isblank(A9),"""",split(AK9, ""()"")))"),3.5) -> 3.5 | X9: =IFERROR(__xludf.DUMMYFUNCTION("""COMPUTED_VALUE"""),0.054) -> 0.054 | Y9: =IFERROR(W9/E9,"") -> 0.064079092 | Z9: 0.0355 | AA9: =iferror(if(isblank(A9),"",D9*E9),0) -> 1693.2746 | AB9: =IF(ISBLANK(A9),"",D9*F9) -> 2008.8648 | AC9: =IFERROR(IF(ISBLANK(A9),"",D9*W9),"") -> 108.5035 | AD9: =if(isblank(A9),"",AC9/$AC$32) -> 0.12293036 | AE9: =IF(ISBLANK($A9),"",SUM(OFFSET('Dividend Log'!$B$17, 0, ROW($A9)-2), OFFSET('Dividend Log'!$B$31, 0, ROW($A9)-2), OFFSET('Dividend Log'!$B$45, 0, ROW($A9)-2), OFFSET('Dividend Log'!$B$59, 0, ROW($A9)-2), OFFSET('Dividend Log'!$B$73, 0, ROW($A9)-2))) -> 124 | AF9: =IFERROR(AC9/F9,"") -> 1.6744367 | AG9: =iferror(IF(ISBLANK(G9),"",(F9-G9)/G9),"") -> 0.92742415 | AH9: =IF(AG9="", "", IF(AG9<=-15%, "Strong Buy", IF(AG9<0%, "Buy", IF(AG9<=15%, "Expensive", "Overrated")))) -> Overrated | AI9: =IF(ISBLANK(A9),"",(F9-E9)/E9) -> 0.18637862 | AJ9: =IF(A9="", "", IF(AI9<-15%, "Strong Buy", IF(AI9<-5%, "Buy", IF(AI9<5%, "Avg. Cost", IF(AI9<=15%, "Overcost", "Hold"))))) -> Hold | AK9: =IFERROR(__xludf.DUMMYFUNCTION("LET(t, A9, IF(t="""","""", IFERROR( SUBSTITUTE( INDEX( IMPORTXML( ""https://finviz.com/quote.ashx?t=""&t&""&ty=dv"", ""(//td[normalize-space()='Dividend TTM' or contains(.,'Dividend TTM')]/following-si"&"bling::td[1])[1]"" ),1,1), ""*"",""""), IFERROR( SUBSTITUTE( INDEX( IMPORTXML( ""https://finviz.com/quote.ashx?t=""&t, ""(//td[normalize-space()='Dividend']/following-sibling:"&":td[1])[1]"" ),1,1), ""*"",""""), """") ) ) ) "),"3.50 (5.40%)") -> 3.50 (5.40%)
A10: VICI | B10: =IFERROR(__xludf.DUMMYFUNCTION("IF(ISBLANK(A10),"""", googlefinance(A10, ""name""))"),"VICI Properties Inc") -> VICI Properties Inc | C10: =IF(ISBLANK(A10),"", HYPERLINK("https://seekingalpha.com/symbol/" & A10,"View")) -> View | D10: 15.874 | E10: 29.95 | F10: =IFERROR(__xludf.DUMMYFUNCTION("IF(ISBLANK(A10),"""", googlefinance(A10, ""price""))"),29.69) -> 29.69 | G10: =IF(ISBLANK(A10),"",IFERROR(VLOOKUP(A10, 'Intrinsic Values List'!$A$2:$D$70, 4, FALSE), "Not Found" )) -> 86.13 | H10: =IF(ISBLANK(A10),"",IFERROR(VLOOKUP(A10, 'Intrinsic Values List'!$A$2:$G$70, 7, FALSE), "Not Found" )) -> 5.78 | I10: =IFERROR(__xludf.DUMMYFUNCTION("IFERROR(googlefinance(A10,""change""),"""")"),-0.2) -> -0.2 | J10: =IFERROR(__xludf.DUMMYFUNCTION("iferror(GOOGLEFINANCE(A10,""changepct"")/100,"""")"),-0.0067) -> -0.0067 | K10: =if(isblank(A10),"",(D10*I10)) -> -3.1748 | L10: =IFERROR(__xludf.DUMMYFUNCTION("IF(ISBLANK(A10),"""", googlefinance(A10, ""low52""))"),27.48) -> 27.48 | M10: =IFERROR(__xludf.DUMMYFUNCTION("IF(ISBLANK(A10),"""",IFERROR(SPARKLINE((F10-L10)/(N10-L10),{""charttype"",""bar"";""max"",1;""min"",0;""color1"",""2c79b5""}),""n/a""))"),"") | N10: =IFERROR(__xludf.DUMMYFUNCTION("IF(ISBLANK(A10),"""", googlefinance(A10, ""high52""))"),34.03) -> 34.03 | O10: =if(isblank(A10),"",(F10-E10)*D10) -> -4.12724 | P10: =if(isblank(A10),"",O10+AE10) -> 22.89276 | Q10: =iferror(if(D10<0,0,O10/(E10*D10)),"") -> -0.0086811352 | R10: =if(isblank(A10),"",P10/(E10*D10)) -> 0.048152069 | S10: Stocks | T10: Real Estate | U10: Value Stocks | V10: =if(isblank(A10),"",AB10/$AB$32) -> 0.011692923 | W10: =IFERROR(__xludf.DUMMYFUNCTION("IfError(IF(isblank(A10),"""",split(AK10, ""()"")))"),1.76) -> 1.76 | X10: =IFERROR(__xludf.DUMMYFUNCTION("""COMPUTED_VALUE"""),0.0594) -> 0.0594 | Y10: =IFERROR(W10/E10,"") -> 0.058764608 | Z10: 0.0664 | AA10: =iferror(if(isblank(A10),"",D10*E10),0) -> 475.4263 | AB10: =IF(ISBLANK(A10),"",D10*F10) -> 471.29906 | AC10: =IFERROR(IF(ISBLANK(A10),"",D10*W10),"") -> 27.93824 | AD10: =if(isblank(A10),"",AC10/$AC$32) -> 0.031652969 | AE10: =IF(ISBLANK($A10),"",SUM(OFFSET('Dividend Log'!$B$17, 0, ROW($A10)-2), OFFSET('Dividend Log'!$B$31, 0, ROW($A10)-2), OFFSET('Dividend Log'!$B$45, 0, ROW($A10)-2), OFFSET('Dividend Log'!$B$59, 0, ROW($A10)-2), OFFSET('Dividend Log'!$B$73, 0, ROW($A10)-2))) -> 27.02 | AF10: =IFERROR(AC10/F10,"") -> 0.94099832 | AG10: =iferror(IF(ISBLANK(G10),"",(F10-G10)/G10),"") -> -0.65528852 | AH10: =IF(AG10="", "", IF(AG10<=-15%, "Strong Buy", IF(AG10<0%, "Buy", IF(AG10<=15%, "Expensive", "Overrated")))) -> Strong Buy | AI10: =IF(ISBLANK(A10),"",(F10-E10)/E10) -> -0.0086811352 | AJ10: =IF(A10="", "", IF(AI10<-15%, "Strong Buy", IF(AI10<-5%, "Buy", IF(AI10<5%, "Avg. Cost", IF(AI10<=15%, "Overcost", "Hold"))))) -> Avg. Cost | AK10: =IFERROR(__xludf.DUMMYFUNCTION("LET(t, A10, IF(t="""","""", IFERROR( SUBSTITUTE( INDEX( IMPORTXML( ""https://finviz.com/quote.ashx?t=""&t&""&ty=dv"", ""(//td[normalize-space()='Dividend TTM' or contains(.,'Dividend TTM')]/following-s"&"ibling::td[1])[1]"" ),1,1), ""*"",""""), IFERROR( SUBSTITUTE( INDEX( IMPORTXML( ""https://finviz.com/quote.ashx?t=""&t, ""(//td[normalize-space()='Dividend']/following-sibling"&"::td[1])[1]"" ),1,1), ""*"",""""), """") ) ) ) "),"1.76 (5.94%)") -> 1.76 (5.94%)
A11: UNH | B11: =IFERROR(__xludf.DUMMYFUNCTION("IF(ISBLANK(A11),"""", googlefinance(A11, ""name""))"),"UnitedHealth Group Inc") -> UnitedHealth Group Inc | C11: =IF(ISBLANK(A11),"", HYPERLINK("https://seekingalpha.com/symbol/" & A11,"View")) -> View | D11: 5.066 | E11: 261.98 | F11: =IFERROR(__xludf.DUMMYFUNCTION("IF(ISBLANK(A11),"""", googlefinance(A11, ""price""))"),288.77) -> 288.77 | G11: =IF(ISBLANK(A11),"",IFERROR(VLOOKUP(A11, 'Intrinsic Values List'!$A$2:$D$70, 4, FALSE), "Not Found" )) -> 362.68 | H11: =IF(ISBLANK(A11),"",IFERROR(VLOOKUP(A11, 'Intrinsic Values List'!$A$2:$G$70, 7, FALSE), "Not Found" )) -> 5 | I11: =IFERROR(__xludf.DUMMYFUNCTION("IFERROR(googlefinance(A11,""change""),"""")"),-3.19) -> -3.19 | J11: =IFERROR(__xludf.DUMMYFUNCTION("iferror(GOOGLEFINANCE(A11,""changepct"")/100,"""")"),-0.0109) -> -0.0109 | K11: =if(isblank(A11),"",(D11*I11)) -> -16.16054 | L11: =IFERROR(__xludf.DUMMYFUNCTION("IF(ISBLANK(A11),"""", googlefinance(A11, ""low52""))"),234.6) -> 234.6 | M11: =IFERROR(__xludf.DUMMYFUNCTION("IF(ISBLANK(A11),"""",IFERROR(SPARKLINE((F11-L11)/(N11-L11),{""charttype"",""bar"";""max"",1;""min"",0;""color1"",""2c79b5""}),""n/a""))"),"") | N11: =IFERROR(__xludf.DUMMYFUNCTION("IF(ISBLANK(A11),"""", googlefinance(A11, ""high52""))"),606.36) -> 606.36 | O11: =if(isblank(A11),"",(F11-E11)*D11) -> 135.71814 | P11: =if(isblank(A11),"",O11+AE11) -> 157.88814 | Q11: =iferror(if(D11<0,0,O11/(E11*D11)),"") -> 0.10225971 | R11: =if(isblank(A11),"",P11/(E11*D11)) -> 0.11896417 | S11: Stocks | T11: Health Care | U11: Value Stocks | V11: =if(isblank(A11),"",AB11/$AB$32) -> 0.036294747 | W11: =IFERROR(__xludf.DUMMYFUNCTION("IfError(IF(isblank(A11),"""",split(AK11, ""()"")))"),8.73) -> 8.73 | X11: =IFERROR(__xludf.DUMMYFUNCTION("""COMPUTED_VALUE"""),0.0302) -> 0.0302 | Y11: =IFERROR(W11/E11,"") -> 0.033323154 | Z11: 0.0875 | AA11: =iferror(if(isblank(A11),"",D11*E11),0) -> 1327.1907 | AB11: =IF(ISBLANK(A11),"",D11*F11) -> 1462.9088 | AC11: =IFERROR(IF(ISBLANK(A11),"",D11*W11),"") -> 44.22618 | AD11: =if(isblank(A11),"",AC11/$AC$32) -> 0.050106589 | AE11: =IF(ISBLANK($A11),"",SUM(OFFSET('Dividend Log'!$B$17, 0, ROW($A11)-2), OFFSET('Dividend Log'!$B$31, 0, ROW($A11)-2), OFFSET('Dividend Log'!$B$45, 0, ROW($A11)-2), OFFSET('Dividend Log'!$B$59, 0, ROW($A11)-2), OFFSET('Dividend Log'!$B$73, 0, ROW($A11)-2))) -> 22.17 | AF11: =IFERROR(AC11/F11,"") -> 0.15315365 | AG11: =iferror(IF(ISBLANK(G11),"",(F11-G11)/G11),"") -> -0.20378846 | AH11: =IF(AG11="", "", IF(AG11<=-15%, "Strong Buy", IF(AG11<0%, "Buy", IF(AG11<=15%, "Expensive", "Overrated")))) -> Strong Buy | AI11: =IF(ISBLANK(A11),"",(F11-E11)/E11) -> 0.10225971 | AJ11: =IF(A11="", "", IF(AI11<-15%, "Strong Buy", IF(AI11<-5%, "Buy", IF(AI11<5%, "Avg. Cost", IF(AI11<=15%, "Overcost", "Hold"))))) -> Overcost | AK11: =IFERROR(__xludf.DUMMYFUNCTION("LET(t, A11, IF(t="""","""", IFERROR( SUBSTITUTE( INDEX( IMPORTXML( ""https://finviz.com/quote.ashx?t=""&t&""&ty=dv"", ""(//td[normalize-space()='Dividend TTM' or contains(.,'Dividend TTM')]/following-s"&"ibling::td[1])[1]"" ),1,1), ""*"",""""), IFERROR( SUBSTITUTE( INDEX( IMPORTXML( ""https://finviz.com/quote.ashx?t=""&t, ""(//td[normalize-space()='Dividend']/following-sibling"&"::td[1])[1]"" ),1,1), ""*"",""""), """") ) ) ) "),"8.73 (3.02%)") -> 8.73 (3.02%)
A12: VGT | B12: =IFERROR(__xludf.DUMMYFUNCTION("IF(ISBLANK(A12),"""", googlefinance(A12, ""name""))"),"Vanguard Information Technology Index Fund ETF") -> Vanguard Information Technology Index Fund ETF | C12: =IF(ISBLANK(A12),"", HYPERLINK("https://seekingalpha.com/symbol/" & A12,"View")) -> View | D12: 3.015 | E12: 507.59 | F12: =IFERROR(__xludf.DUMMYFUNCTION("IF(ISBLANK(A12),"""", googlefinance(A12, ""price""))"),733.27) -> 733.27 | G12: =IF(ISBLANK(A12),"",IFERROR(VLOOKUP(A12, 'Intrinsic Values List'!$A$2:$D$70, 4, FALSE), "Not Found" )) -> Not Found | H12: =IF(ISBLANK(A12),"",IFERROR(VLOOKUP(A12, 'Intrinsic Values List'!$A$2:$G$70, 7, FALSE), "Not Found" )) -> Not Found | I12: =IFERROR(__xludf.DUMMYFUNCTION("IFERROR(googlefinance(A12,""change""),"""")"),0.14) -> 0.14 | J12: =IFERROR(__xludf.DUMMYFUNCTION("iferror(GOOGLEFINANCE(A12,""changepct"")/100,"""")"),2.0E-4) -> 0.0002 | K12: =if(isblank(A12),"",(D12*I12)) -> 0.4221 | L12: =IFERROR(__xludf.DUMMYFUNCTION("IF(ISBLANK(A12),"""", googlefinance(A12, ""low52""))"),451.0) -> 451 | M12: =IFERROR(__xludf.DUMMYFUNCTION("IF(ISBLANK(A12),"""",IFERROR(SPARKLINE((F12-L12)/(N12-L12),{""charttype"",""bar"";""max"",1;""min"",0;""color1"",""2c79b5""}),""n/a""))"),"") | N12: =IFERROR(__xludf.DUMMYFUNCTION("IF(ISBLANK(A12),"""", googlefinance(A12, ""high52""))"),806.99) -> 806.99 | O12: =if(isblank(A12),"",(F12-E12)*D12) -> 680.4252 | P12: =if(isblank(A12),"",O12+AE12) -> 690.5852 | Q12: =iferror(if(D12<0,0,O12/(E12*D12)),"") -> 0.44461081 | R12: =if(isblank(A12),"",P12/(E12*D12)) -> 0.45124967 | S12: ETFs | T12: ETF | U12: Growth | V12: =if(isblank(A12),"",AB12/$AB$32) -> 0.054850141 | W12: =IFERROR(__xludf.DUMMYFUNCTION("IfError(IF(isblank(A12),"""",split(AK12, ""()"")))"),3.05) -> 3.05 | X12: =IFERROR(__xludf.DUMMYFUNCTION("""COMPUTED_VALUE"""),0.0042) -> 0.0042 | Y12: =IFERROR(W12/E12,"") -> 0.0060087866 | Z12: 0.0875 | AA12: =iferror(if(isblank(A12),"",D12*E12),0) -> 1530.3838 | AB12: =IF(ISBLANK(A12),"",D12*F12) -> 2210.809 | AC12: =IFERROR(IF(ISBLANK(A12),"",D12*W12),"") -> 9.19575 | AD12: =if(isblank(A12),"",AC12/$AC$32) -> 0.010418437 | AE12: =IF(ISBLANK($A12),"",SUM(OFFSET('Dividend Log'!$B$17, 0, ROW($A12)-2), OFFSET('Dividend Log'!$B$31, 0, ROW($A12)-2), OFFSET('Dividend Log'!$B$45, 0, ROW($A12)-2), OFFSET('Dividend Log'!$B$59, 0, ROW($A12)-2), OFFSET('Dividend Log'!$B$73, 0, ROW($A12)-2))) -> 10.16 | AF12: =IFERROR(AC12/F12,"") -> 0.012540742 | AG12: =iferror(IF(ISBLANK(G12),"",(F12-G12)/G12),"") | AH12: =IF(AG12="", "", IF(AG12<=-15%, "Strong Buy", IF(AG12<0%, "Buy", IF(AG12<=15%, "Expensive", "Overrated")))) | AI12: =IF(ISBLANK(A12),"",(F12-E12)/E12) -> 0.44461081 | AJ12: =IF(A12="", "", IF(AI12<-15%, "Strong Buy", IF(AI12<-5%, "Buy", IF(AI12<5%, "Avg. Cost", IF(AI12<=15%, "Overcost", "Hold"))))) -> Hold | AK12: =IFERROR(__xludf.DUMMYFUNCTION("LET(t, A12, IF(t="""","""", IFERROR( SUBSTITUTE( INDEX( IMPORTXML( ""https://finviz.com/quote.ashx?t=""&t&""&ty=dv"", ""(//td[normalize-space()='Dividend TTM' or contains(.,'Dividend TTM')]/following-s"&"ibling::td[1])[1]"" ),1,1), ""*"",""""), IFERROR( SUBSTITUTE( INDEX( IMPORTXML( ""https://finviz.com/quote.ashx?t=""&t, ""(//td[normalize-space()='Dividend']/following-sibling"&"::td[1])[1]"" ),1,1), ""*"",""""), """") ) ) ) "),"3.05 (0.42%)") -> 3.05 (0.42%)
A13: VOO | B13: =IFERROR(__xludf.DUMMYFUNCTION("IF(ISBLANK(A13),"""", googlefinance(A13, ""name""))"),"Vanguard S&P 500 ETF") -> Vanguard S&P 500 ETF | C13: =IF(ISBLANK(A13),"", HYPERLINK("https://seekingalpha.com/symbol/" & A13,"View")) -> View | D13: 3.064 | E13: 480.16 | F13: =IFERROR(__xludf.DUMMYFUNCTION("IF(ISBLANK(A13),"""", googlefinance(A13, ""price""))"),626.81) -> 626.81 | G13: =IF(ISBLANK(A13),"",IFERROR(VLOOKUP(A13, 'Intrinsic Values List'!$A$2:$D$70, 4, FALSE), "Not Found" )) -> Not Found | H13: =IF(ISBLANK(A13),"",IFERROR(VLOOKUP(A13, 'Intrinsic Values List'!$A$2:$G$70, 7, FALSE), "Not Found" )) -> Not Found | I13: =IFERROR(__xludf.DUMMYFUNCTION("IFERROR(googlefinance(A13,""change""),"""")"),-3.37) -> -3.37 | J13: =IFERROR(__xludf.DUMMYFUNCTION("iferror(GOOGLEFINANCE(A13,""changepct"")/100,"""")"),-0.0053) -> -0.0053 | K13: =if(isblank(A13),"",(D13*I13)) -> -10.32568 | L13: =IFERROR(__xludf.DUMMYFUNCTION("IF(ISBLANK(A13),"""", googlefinance(A13, ""low52""))"),442.8) -> 442.8 | M13: =IFERROR(__xludf.DUMMYFUNCTION("IF(ISBLANK(A13),"""",IFERROR(SPARKLINE((F13-L13)/(N13-L13),{""charttype"",""bar"";""max"",1;""min"",0;""color1"",""2c79b5""}),""n/a""))"),"") | N13: =IFERROR(__xludf.DUMMYFUNCTION("IF(ISBLANK(A13),"""", googlefinance(A13, ""high52""))"),641.8) -> 641.8 | O13: =if(isblank(A13),"",(F13-E13)*D13) -> 449.3356 | P13: =if(isblank(A13),"",O13+AE13) -> 484.5656 | Q13: =iferror(if(D13<0,0,O13/(E13*D13)),"") -> 0.30541903 | R13: =if(isblank(A13),"",P13/(E13*D13)) -> 0.3293653 | S13: ETFs | T13: ETF | U13: Foundational | V13: =if(isblank(A13),"",AB13/$AB$32) -> 0.047648715 | W13: =IFERROR(__xludf.DUMMYFUNCTION("IfError(IF(isblank(A13),"""",split(AK13, ""()"")))"),7.07) -> 7.07 | X13: =IFERROR(__xludf.DUMMYFUNCTION("""COMPUTED_VALUE"""),0.0113) -> 0.0113 | Y13: =IFERROR(W13/E13,"") -> 0.014724259 | Z13: 0.0465 | AA13: =iferror(if(isblank(A13),"",D13*E13),0) -> 1471.2102 | AB13: =IF(ISBLANK(A13),"",D13*F13) -> 1920.5458 | AC13: =IFERROR(IF(ISBLANK(A13),"",D13*W13),"") -> 21.66248 | AD13: =if(isblank(A13),"",AC13/$AC$32) -> 0.02454277 | AE13: =IF(ISBLANK($A13),"",SUM(OFFSET('Dividend Log'!$B$17, 0, ROW($A13)-2), OFFSET('Dividend Log'!$B$31, 0, ROW($A13)-2), OFFSET('Dividend Log'!$B$45, 0, ROW($A13)-2), OFFSET('Dividend Log'!$B$59, 0, ROW($A13)-2), OFFSET('Dividend Log'!$B$73, 0, ROW($A13)-2))) -> 35.23 | AF13: =IFERROR(AC13/F13,"") -> 0.034559883 | AG13: =iferror(IF(ISBLANK(G13),"",(F13-G13)/G13),"") | AH13: =IF(AG13="", "", IF(AG13<=-15%, "Strong Buy", IF(AG13<0%, "Buy", IF(AG13<=15%, "Expensive", "Overrated")))) | AI13: =IF(ISBLANK(A13),"",(F13-E13)/E13) -> 0.30541903 | AJ13: =IF(A13="", "", IF(AI13<-15%, "Strong Buy", IF(AI13<-5%, "Buy", IF(AI13<5%, "Avg. Cost", IF(AI13<=15%, "Overcost", "Hold"))))) -> Hold | AK13: =IFERROR(__xludf.DUMMYFUNCTION("LET(t, A13, IF(t="""","""", IFERROR( SUBSTITUTE( INDEX( IMPORTXML( ""https://finviz.com/quote.ashx?t=""&t&""&ty=dv"", ""(//td[normalize-space()='Dividend TTM' or contains(.,'Dividend TTM')]/following-s"&"ibling::td[1])[1]"" ),1,1), ""*"",""""), IFERROR( SUBSTITUTE( INDEX( IMPORTXML( ""https://finviz.com/quote.ashx?t=""&t, ""(//td[normalize-space()='Dividend']/following-sibling"&"::td[1])[1]"" ),1,1), ""*"",""""), """") ) ) ) "),"7.07 (1.13%)") -> 7.07 (1.13%)
A14: VTI | B14: =IFERROR(__xludf.DUMMYFUNCTION("IF(ISBLANK(A14),"""", googlefinance(A14, ""name""))"),"Vanguard Total Stock Market Index Fund ETF") -> Vanguard Total Stock Market Index Fund ETF | C14: =IF(ISBLANK(A14),"", HYPERLINK("https://seekingalpha.com/symbol/" & A14,"View")) -> View | D14: 8.147 | E14: 260.86 | F14: =IFERROR(__xludf.DUMMYFUNCTION("IF(ISBLANK(A14),"""", googlefinance(A14, ""price""))"),336.0) -> 336 | G14: =IF(ISBLANK(A14),"",IFERROR(VLOOKUP(A14, 'Intrinsic Values List'!$A$2:$D$70, 4, FALSE), "Not Found" )) -> Not Found | H14: =IF(ISBLANK(A14),"",IFERROR(VLOOKUP(A14, 'Intrinsic Values List'!$A$2:$G$70, 7, FALSE), "Not Found" )) -> Not Found | I14: =IFERROR(__xludf.DUMMYFUNCTION("IFERROR(googlefinance(A14,""change""),"""")"),-2.19) -> -2.19 | J14: =IFERROR(__xludf.DUMMYFUNCTION("iferror(GOOGLEFINANCE(A14,""changepct"")/100,"""")"),-0.006500000000000001) -> -0.0065 | K14: =if(isblank(A14),"",(D14*I14)) -> -17.84193 | L14: =IFERROR(__xludf.DUMMYFUNCTION("IF(ISBLANK(A14),"""", googlefinance(A14, ""low52""))"),236.5) -> 236.5 | M14: =IFERROR(__xludf.DUMMYFUNCTION("IF(ISBLANK(A14),"""",IFERROR(SPARKLINE((F14-L14)/(N14-L14),{""charttype"",""bar"";""max"",1;""min"",0;""color1"",""2c79b5""}),""n/a""))"),"") | N14: =IFERROR(__xludf.DUMMYFUNCTION("IF(ISBLANK(A14),"""", googlefinance(A14, ""high52""))"),344.4) -> 344.4 | O14: =if(isblank(A14),"",(F14-E14)*D14) -> 612.16558 | P14: =if(isblank(A14),"",O14+AE14) -> 656.26558 | Q14: =iferror(if(D14<0,0,O14/(E14*D14)),"") -> 0.28804723 | R14: =if(isblank(A14),"",P14/(E14*D14)) -> 0.30879796 | S14: ETFs | T14: ETF | U14: Foundational | V14: =if(isblank(A14),"",AB14/$AB$32) -> 0.067914657 | W14: =IFERROR(__xludf.DUMMYFUNCTION("IfError(IF(isblank(A14),"""",split(AK14, ""()"")))"),3.76) -> 3.76 | X14: =IFERROR(__xludf.DUMMYFUNCTION("""COMPUTED_VALUE"""),0.0112) -> 0.0112 | Y14: =IFERROR(W14/E14,"") -> 0.014413862 | Z14: 0.0471 | AA14: =iferror(if(isblank(A14),"",D14*E14),0) -> 2125.2264 | AB14: =IF(ISBLANK(A14),"",D14*F14) -> 2737.392 | AC14: =IFERROR(IF(ISBLANK(A14),"",D14*W14),"") -> 30.63272 | AD14: =if(isblank(A14),"",AC14/$AC$32) -> 0.034705713 | AE14: =IF(ISBLANK($A14),"",SUM(OFFSET('Dividend Log'!$B$17, 0, ROW($A14)-2), OFFSET('Dividend Log'!$B$31, 0, ROW($A14)-2), OFFSET('Dividend Log'!$B$45, 0, ROW($A14)-2), OFFSET('Dividend Log'!$B$59, 0, ROW($A14)-2), OFFSET('Dividend Log'!$B$73, 0, ROW($A14)-2))) -> 44.1 | AF14: =IFERROR(AC14/F14,"") -> 0.09116881 | AG14: =iferror(IF(ISBLANK(G14),"",(F14-G14)/G14),"") | AH14: =IF(AG14="", "", IF(AG14<=-15%, "Strong Buy", IF(AG14<0%, "Buy", IF(AG14<=15%, "Expensive", "Overrated")))) | AI14: =IF(ISBLANK(A14),"",(F14-E14)/E14) -> 0.28804723 | AJ14: =IF(A14="", "", IF(AI14<-15%, "Strong Buy", IF(AI14<-5%, "Buy", IF(AI14<5%, "Avg. Cost", IF(AI14<=15%, "Overcost", "Hold"))))) -> Hold | AK14: =IFERROR(__xludf.DUMMYFUNCTION("LET(t, A14, IF(t="""","""", IFERROR( SUBSTITUTE( INDEX( IMPORTXML( ""https://finviz.com/quote.ashx?t=""&t&""&ty=dv"", ""(//td[normalize-space()='Dividend TTM' or contains(.,'Dividend TTM')]/following-s"&"ibling::td[1])[1]"" ),1,1), ""*"",""""), IFERROR( SUBSTITUTE( INDEX( IMPORTXML( ""https://finviz.com/quote.ashx?t=""&t, ""(//td[normalize-space()='Dividend']/following-sibling"&"::td[1])[1]"" ),1,1), ""*"",""""), """") ) ) ) "),"3.76 (1.12%)") -> 3.76 (1.12%)
A15: SCHD | B15: =IFERROR(__xludf.DUMMYFUNCTION("IF(ISBLANK(A15),"""", googlefinance(A15, ""name""))"),"Schwab US Dividend Equity ETF") -> Schwab US Dividend Equity ETF | C15: =IF(ISBLANK(A15),"", HYPERLINK("https://seekingalpha.com/symbol/" & A15,"View")) -> View | D15: 186.205 | E15: 26.98 | F15: =IFERROR(__xludf.DUMMYFUNCTION("IF(ISBLANK(A15),"""", googlefinance(A15, ""price""))"),31.26) -> 31.26 | G15: =IF(ISBLANK(A15),"",IFERROR(VLOOKUP(A15, 'Intrinsic Values List'!$A$2:$D$70, 4, FALSE), "Not Found" )) -> Not Found | H15: =IF(ISBLANK(A15),"",IFERROR(VLOOKUP(A15, 'Intrinsic Values List'!$A$2:$G$70, 7, FALSE), "Not Found" )) -> Not Found | I15: =IFERROR(__xludf.DUMMYFUNCTION("IFERROR(googlefinance(A15,""change""),"""")"),-0.28) -> -0.28 | J15: =IFERROR(__xludf.DUMMYFUNCTION("iferror(GOOGLEFINANCE(A15,""changepct"")/100,"""")"),-0.0089) -> -0.0089 | K15: =if(isblank(A15),"",(D15*I15)) -> -52.1374 | L15: =IFERROR(__xludf.DUMMYFUNCTION("IF(ISBLANK(A15),"""", googlefinance(A15, ""low52""))"),23.88) -> 23.88 | M15: =IFERROR(__xludf.DUMMYFUNCTION("IF(ISBLANK(A15),"""",IFERROR(SPARKLINE((F15-L15)/(N15-L15),{""charttype"",""bar"";""max"",1;""min"",0;""color1"",""2c79b5""}),""n/a""))"),"") | N15: =IFERROR(__xludf.DUMMYFUNCTION("IF(ISBLANK(A15),"""", googlefinance(A15, ""high52""))"),31.95) -> 31.95 | O15: =if(isblank(A15),"",(F15-E15)*D15) -> 796.9574 | P15: =if(isblank(A15),"",O15+AE15) -> 994.2974 | Q15: =iferror(if(D15<0,0,O15/(E15*D15)),"") -> 0.15863603 | R15: =if(isblank(A15),"",P15/(E15*D15)) -> 0.19791696 | S15: ETFs | T15: ETF | U15: Value Stocks | V15: =if(isblank(A15),"",AB15/$AB$32) -> 0.14441318 | W15: =IFERROR(__xludf.DUMMYFUNCTION("IfError(IF(isblank(A15),"""",split(AK15, ""()"")))"),1.05) -> 1.05 | X15: =IFERROR(__xludf.DUMMYFUNCTION("""COMPUTED_VALUE"""),0.0335) -> 0.0335 | Y15: =IFERROR(W15/E15,"") -> 0.038917717 | Z15: 0.118 | AA15: =iferror(if(isblank(A15),"",D15*E15),0) -> 5023.8109 | AB15: =IF(ISBLANK(A15),"",D15*F15) -> 5820.7683 | AC15: =IFERROR(IF(ISBLANK(A15),"",D15*W15),"") -> 195.51525 | AD15: =if(isblank(A15),"",AC15/$AC$32) -> 0.22151138 | AE15: =IF(ISBLANK($A15),"",SUM(OFFSET('Dividend Log'!$B$17, 0, ROW($A15)-2), OFFSET('Dividend Log'!$B$31, 0, ROW($A15)-2), OFFSET('Dividend Log'!$B$45, 0, ROW($A15)-2), OFFSET('Dividend Log'!$B$59, 0, ROW($A15)-2), OFFSET('Dividend Log'!$B$73, 0, ROW($A15)-2))) -> 197.34 | AF15: =IFERROR(AC15/F15,"") -> 6.2544866 | AG15: =iferror(IF(ISBLANK(G15),"",(F15-G15)/G15),"") | AH15: =IF(AG15="", "", IF(AG15<=-15%, "Strong Buy", IF(AG15<0%, "Buy", IF(AG15<=15%, "Expensive", "Overrated")))) | AI15: =IF(ISBLANK(A15),"",(F15-E15)/E15) -> 0.15863603 | AJ15: =IF(A15="", "", IF(AI15<-15%, "Strong Buy", IF(AI15<-5%, "Buy", IF(AI15<5%, "Avg. Cost", IF(AI15<=15%, "Overcost", "Hold"))))) -> Hold | AK15: =IFERROR(__xludf.DUMMYFUNCTION("LET(t, A15, IF(t="""","""", IFERROR( SUBSTITUTE( INDEX( IMPORTXML( ""https://finviz.com/quote.ashx?t=""&t&""&ty=dv"", ""(//td[normalize-space()='Dividend TTM' or contains(.,'Dividend TTM')]/following-s"&"ibling::td[1])[1]"" ),1,1), ""*"",""""), IFERROR( SUBSTITUTE( INDEX( IMPORTXML( ""https://finviz.com/quote.ashx?t=""&t, ""(//td[normalize-space()='Dividend']/following-sibling"&"::td[1])[1]"" ),1,1), ""*"",""""), """") ) ) ) "),"1.05 (3.35%)") -> 1.05 (3.35%)
A16: VIG | B16: =IFERROR(__xludf.DUMMYFUNCTION("IF(ISBLANK(A16),"""", googlefinance(A16, ""name""))"),"Vanguard Dividend Appreciation Index Fund ETF") -> Vanguard Dividend Appreciation Index Fund ETF | C16: =IF(ISBLANK(A16),"", HYPERLINK("https://seekingalpha.com/symbol/" & A16,"View")) -> View | D16: 1.03 | E16: 179.84 | F16: =IFERROR(__xludf.DUMMYFUNCTION("IF(ISBLANK(A16),"""", googlefinance(A16, ""price""))"),223.45) -> 223.45 | G16: =IF(ISBLANK(A16),"",IFERROR(VLOOKUP(A16, 'Intrinsic Values List'!$A$2:$D$70, 4, FALSE), "Not Found" )) -> Not Found | H16: =IF(ISBLANK(A16),"",IFERROR(VLOOKUP(A16, 'Intrinsic Values List'!$A$2:$G$70, 7, FALSE), "Not Found" )) -> Not Found | I16: =IFERROR(__xludf.DUMMYFUNCTION("IFERROR(googlefinance(A16,""change""),"""")"),-2.07) -> -2.07 | J16: =IFERROR(__xludf.DUMMYFUNCTION("iferror(GOOGLEFINANCE(A16,""changepct"")/100,"""")"),-0.0092) -> -0.0092 | K16: =if(isblank(A16),"",(D16*I16)) -> -2.1321 | L16: =IFERROR(__xludf.DUMMYFUNCTION("IF(ISBLANK(A16),"""", googlefinance(A16, ""low52""))"),169.32) -> 169.32 | M16: =IFERROR(__xludf.DUMMYFUNCTION("IF(ISBLANK(A16),"""",IFERROR(SPARKLINE((F16-L16)/(N16-L16),{""charttype"",""bar"";""max"",1;""min"",0;""color1"",""2c79b5""}),""n/a""))"),"") | N16: =IFERROR(__xludf.DUMMYFUNCTION("IF(ISBLANK(A16),"""", googlefinance(A16, ""high52""))"),230.5) -> 230.5 | O16: =if(isblank(A16),"",(F16-E16)*D16) -> 44.9183 | P16: =if(isblank(A16),"",O16+AE16) -> 51.1683 | Q16: =iferror(if(D16<0,0,O16/(E16*D16)),"") -> 0.24249333 | R16: =if(isblank(A16),"",P16/(E16*D16)) -> 0.27623421 | S16: ETFs | T16: ETF | U16: Value Stocks | V16: =if(isblank(A16),"",AB16/$AB$32) -> 0.0057101051 | W16: =IFERROR(__xludf.DUMMYFUNCTION("IfError(IF(isblank(A16),"""",split(AK16, ""()"")))"),3.56) -> 3.56 | X16: =IFERROR(__xludf.DUMMYFUNCTION("""COMPUTED_VALUE"""),0.0159) -> 0.0159 | Y16: =IFERROR(W16/E16,"") -> 0.019795374 | Z16: 0.0846 | AA16: =iferror(if(isblank(A16),"",D16*E16),0) -> 185.2352 | AB16: =IF(ISBLANK(A16),"",D16*F16) -> 230.1535 | AC16: =IFERROR(IF(ISBLANK(A16),"",D16*W16),"") -> 3.6668 | AD16: =if(isblank(A16),"",AC16/$AC$32) -> 0.0041543457 | AE16: =IF(ISBLANK($A16),"",SUM(OFFSET('Dividend Log'!$B$17, 0, ROW($A16)-2), OFFSET('Dividend Log'!$B$31, 0, ROW($A16)-2), OFFSET('Dividend Log'!$B$45, 0, ROW($A16)-2), OFFSET('Dividend Log'!$B$59, 0, ROW($A16)-2), OFFSET('Dividend Log'!$B$73, 0, ROW($A16)-2))) -> 6.25 | AF16: =IFERROR(AC16/F16,"") -> 0.016409935 | AG16: =iferror(IF(ISBLANK(G16),"",(F16-G16)/G16),"") | AH16: =IF(AG16="", "", IF(AG16<=-15%, "Strong Buy", IF(AG16<0%, "Buy", IF(AG16<=15%, "Expensive", "Overrated")))) | AI16: =IF(ISBLANK(A16),"",(F16-E16)/E16) -> 0.24249333 | AJ16: =IF(A16="", "", IF(AI16<-15%, "Strong Buy", IF(AI16<-5%, "Buy", IF(AI16<5%, "Avg. Cost", IF(AI16<=15%, "Overcost", "Hold"))))) -> Hold | AK16: =IFERROR(__xludf.DUMMYFUNCTION("LET(t, A16, IF(t="""","""", IFERROR( SUBSTITUTE( INDEX( IMPORTXML( ""https://finviz.com/quote.ashx?t=""&t&""&ty=dv"", ""(//td[normalize-space()='Dividend TTM' or contains(.,'Dividend TTM')]/following-s"&"ibling::td[1])[1]"" ),1,1), ""*"",""""), IFERROR( SUBSTITUTE( INDEX( IMPORTXML( ""https://finviz.com/quote.ashx?t=""&t, ""(//td[normalize-space()='Dividend']/following-sibling"&"::td[1])[1]"" ),1,1), ""*"",""""), """") ) ) ) "),"3.56 (1.59%)") -> 3.56 (1.59%)
A17: VXUS | B17: =IFERROR(__xludf.DUMMYFUNCTION("IF(ISBLANK(A17),"""", googlefinance(A17, ""name""))"),"Vanguard Total International Stock Index Fund ETF") -> Vanguard Total International Stock Index Fund ETF | C17: =IF(ISBLANK(A17),"", HYPERLINK("https://seekingalpha.com/symbol/" & A17,"View")) -> View | D17: 14.765 | E17: 59.99 | F17: =IFERROR(__xludf.DUMMYFUNCTION("IF(ISBLANK(A17),"""", googlefinance(A17, ""price""))"),78.72) -> 78.72 | G17: =IF(ISBLANK(A17),"",IFERROR(VLOOKUP(A17, 'Intrinsic Values List'!$A$2:$D$70, 4, FALSE), "Not Found" )) -> Not Found | H17: =IF(ISBLANK(A17),"",IFERROR(VLOOKUP(A17, 'Intrinsic Values List'!$A$2:$G$70, 7, FALSE), "Not Found" )) -> Not Found | I17: =IFERROR(__xludf.DUMMYFUNCTION("IFERROR(googlefinance(A17,""change""),"""")"),-1.62) -> -1.62 | J17: =IFERROR(__xludf.DUMMYFUNCTION("iferror(GOOGLEFINANCE(A17,""changepct"")/100,"""")"),-0.0202) -> -0.0202 | K17: =if(isblank(A17),"",(D17*I17)) -> -23.9193 | L17: =IFERROR(__xludf.DUMMYFUNCTION("IF(ISBLANK(A17),"""", googlefinance(A17, ""low52""))"),54.98) -> 54.98 | M17: =IFERROR(__xludf.DUMMYFUNCTION("IF(ISBLANK(A17),"""",IFERROR(SPARKLINE((F17-L17)/(N17-L17),{""charttype"",""bar"";""max"",1;""min"",0;""color1"",""2c79b5""}),""n/a""))"),"") | N17: =IFERROR(__xludf.DUMMYFUNCTION("IF(ISBLANK(A17),"""", googlefinance(A17, ""high52""))"),84.28) -> 84.28 | O17: =if(isblank(A17),"",(F17-E17)*D17) -> 276.54845 | P17: =if(isblank(A17),"",O17+AE17) -> 328.15845 | Q17: =iferror(if(D17<0,0,O17/(E17*D17)),"") -> 0.3122187 | R17: =if(isblank(A17),"",P17/(E17*D17)) -> 0.37048555 | S17: ETFs | T17: ETF | U17: International Market | V17: =if(isblank(A17),"",AB17/$AB$32) -> 0.028836666 | W17: =IFERROR(__xludf.DUMMYFUNCTION("IfError(IF(isblank(A17),"""",split(AK17, ""()"")))"),2.4) -> 2.4 | X17: =IFERROR(__xludf.DUMMYFUNCTION("""COMPUTED_VALUE"""),0.0305) -> 0.0305 | Y17: =IFERROR(W17/E17,"") -> 0.040006668 | Z17: 0.0543 | AA17: =iferror(if(isblank(A17),"",D17*E17),0) -> 885.75235 | AB17: =IF(ISBLANK(A17),"",D17*F17) -> 1162.3008 | AC17: =IFERROR(IF(ISBLANK(A17),"",D17*W17),"") -> 35.436 | AD17: =if(isblank(A17),"",AC17/$AC$32) -> 0.040147647 | AE17: =IF(ISBLANK($A17),"",SUM(OFFSET('Dividend Log'!$B$17, 0, ROW($A17)-2), OFFSET('Dividend Log'!$B$31, 0, ROW($A17)-2), OFFSET('Dividend Log'!$B$45, 0, ROW($A17)-2), OFFSET('Dividend Log'!$B$59, 0, ROW($A17)-2), OFFSET('Dividend Log'!$B$73, 0, ROW($A17)-2))) -> 51.61 | AF17: =IFERROR(AC17/F17,"") -> 0.45015244 | AG17: =iferror(IF(ISBLANK(G17),"",(F17-G17)/G17),"") | AH17: =IF(AG17="", "", IF(AG17<=-15%, "Strong Buy", IF(AG17<0%, "Buy", IF(AG17<=15%, "Expensive", "Overrated")))) | AI17: =IF(ISBLANK(A17),"",(F17-E17)/E17) -> 0.3122187 | AJ17: =IF(A17="", "", IF(AI17<-15%, "Strong Buy", IF(AI17<-5%, "Buy", IF(AI17<5%, "Avg. Cost", IF(AI17<=15%, "Overcost", "Hold"))))) -> Hold | AK17: =IFERROR(__xludf.DUMMYFUNCTION("LET(t, A17, IF(t="""","""", IFERROR( SUBSTITUTE( INDEX( IMPORTXML( ""https://finviz.com/quote.ashx?t=""&t&""&ty=dv"", ""(//td[normalize-space()='Dividend TTM' or contains(.,'Dividend TTM')]/following-s"&"ibling::td[1])[1]"" ),1,1), ""*"",""""), IFERROR( SUBSTITUTE( INDEX( IMPORTXML( ""https://finviz.com/quote.ashx?t=""&t, ""(//td[normalize-space()='Dividend']/following-sibling"&"::td[1])[1]"" ),1,1), ""*"",""""), """") ) ) ) "),"2.40 (3.05%)") -> 2.40 (3.05%)
A18: BND | B18: =IFERROR(__xludf.DUMMYFUNCTION("IF(ISBLANK(A18),"""", googlefinance(A18, ""name""))"),"Vanguard Total Bond Market Index Fund ETF") -> Vanguard Total Bond Market Index Fund ETF | C18: =IF(ISBLANK(A18),"", HYPERLINK("https://seekingalpha.com/symbol/" & A18,"View")) -> View | D18: 2.108 | E18: 72.28 | F18: =IFERROR(__xludf.DUMMYFUNCTION("IF(ISBLANK(A18),"""", googlefinance(A18, ""price""))"),74.34) -> 74.34 | G18: =IF(ISBLANK(A18),"",IFERROR(VLOOKUP(A18, 'Intrinsic Values List'!$A$2:$D$70, 4, FALSE), "Not Found" )) -> Not Found | H18: =IF(ISBLANK(A18),"",IFERROR(VLOOKUP(A18, 'Intrinsic Values List'!$A$2:$G$70, 7, FALSE), "Not Found" )) -> Not Found | I18: =IFERROR(__xludf.DUMMYFUNCTION("IFERROR(googlefinance(A18,""change""),"""")"),-0.17) -> -0.17 | J18: =IFERROR(__xludf.DUMMYFUNCTION("iferror(GOOGLEFINANCE(A18,""changepct"")/100,"""")"),-0.0023) -> -0.0023 | K18: =if(isblank(A18),"",(D18*I18)) -> -0.35836 | L18: =IFERROR(__xludf.DUMMYFUNCTION("IF(ISBLANK(A18),"""", googlefinance(A18, ""low52""))"),71.41) -> 71.41 | M18: =IFERROR(__xludf.DUMMYFUNCTION("IF(ISBLANK(A18),"""",IFERROR(SPARKLINE((F18-L18)/(N18-L18),{""charttype"",""bar"";""max"",1;""min"",0;""color1"",""2c79b5""}),""n/a""))"),"") | N18: =IFERROR(__xludf.DUMMYFUNCTION("IF(ISBLANK(A18),"""", googlefinance(A18, ""high52""))"),75.23) -> 75.23 | O18: =if(isblank(A18),"",(F18-E18)*D18) -> 4.34248 | P18: =if(isblank(A18),"",O18+AE18) -> 12.79248 | Q18: =iferror(if(D18<0,0,O18/(E18*D18)),"") -> 0.028500277 | R18: =if(isblank(A18),"",P18/(E18*D18)) -> 0.083958756 | S18: ETFs | T18: Bonds | U18: US Bonds | V18: =if(isblank(A18),"",AB18/$AB$32) -> 0.0038879411 | W18: =IFERROR(__xludf.DUMMYFUNCTION("IfError(IF(isblank(A18),"""",split(AK18, ""()"")))"),2.88) -> 2.88 | X18: =IFERROR(__xludf.DUMMYFUNCTION("""COMPUTED_VALUE"""),0.0387) -> 0.0387 | Y18: =IFERROR(W18/E18,"") -> 0.039845047 | Z18: -0.0045 | AA18: =iferror(if(isblank(A18),"",D18*E18),0) -> 152.36624 | AB18: =IF(ISBLANK(A18),"",D18*F18) -> 156.70872 | AC18: =IFERROR(IF(ISBLANK(A18),"",D18*W18),"") -> 6.07104 | AD18: =if(isblank(A18),"",AC18/$AC$32) -> 0.0068782586 | AE18: =IF(ISBLANK($A18),"",SUM(OFFSET('Dividend Log'!$B$17, 0, ROW($A18)-2), OFFSET('Dividend Log'!$B$31, 0, ROW($A18)-2), OFFSET('Dividend Log'!$B$45, 0, ROW($A18)-2), OFFSET('Dividend Log'!$B$59, 0, ROW($A18)-2), OFFSET('Dividend Log'!$B$73, 0, ROW($A18)-2))) -> 8.45 | AF18: =IFERROR(AC18/F18,"") -> 0.08166586 | AG18: =iferror(IF(ISBLANK(G18),"",(F18-G18)/G18),"") | AH18: =IF(AG18="", "", IF(AG18<=-15%, "Strong Buy", IF(AG18<0%, "Buy", IF(AG18<=15%, "Expensive", "Overrated")))) | AI18: =IF(ISBLANK(A18),"",(F18-E18)/E18) -> 0.028500277 | AJ18: =IF(A18="", "", IF(AI18<-15%, "Strong Buy", IF(AI18<-5%, "Buy", IF(AI18<5%, "Avg. Cost", IF(AI18<=15%, "Overcost", "Hold"))))) -> Avg. Cost | AK18: =IFERROR(__xludf.DUMMYFUNCTION("LET(t, A18, IF(t="""","""", IFERROR( SUBSTITUTE( INDEX( IMPORTXML( ""https://finviz.com/quote.ashx?t=""&t&""&ty=dv"", ""(//td[normalize-space()='Dividend TTM' or contains(.,'Dividend TTM')]/following-s"&"ibling::td[1])[1]"" ),1,1), ""*"",""""), IFERROR( SUBSTITUTE( INDEX( IMPORTXML( ""https://finviz.com/quote.ashx?t=""&t, ""(//td[normalize-space()='Dividend']/following-sibling"&"::td[1])[1]"" ),1,1), ""*"",""""), """") ) ) ) "),"2.88 (3.87%)") -> 2.88 (3.87%)
B19: =IFERROR(__xludf.DUMMYFUNCTION("IF(ISBLANK(A19),"""", googlefinance(A19, ""name""))"),"") | C19: =IF(ISBLANK(A19),"", HYPERLINK("https://seekingalpha.com/symbol/" & A19,"View")) | F19: =IFERROR(__xludf.DUMMYFUNCTION("IF(ISBLANK(A19),"""", googlefinance(A19, ""price""))"),"") | H19: =IF(ISBLANK(A19),"",IFERROR(VLOOKUP(A19, 'Intrinsic Values List'!$A$2:$G$45, 7, FALSE), "Not found" )) | I19: =IFERROR(__xludf.DUMMYFUNCTION("IFERROR(googlefinance(A19,""change""),"""")"),"") | J19: =IFERROR(__xludf.DUMMYFUNCTION("iferror(GOOGLEFINANCE(A19,""changepct"")/100,"""")"),"") | K19: =if(isblank(A19),"",(D19*I19)) | L19: =IFERROR(__xludf.DUMMYFUNCTION("IF(ISBLANK(A19),"""", googlefinance(A19, ""low52""))"),"") | M19: =IFERROR(__xludf.DUMMYFUNCTION("IF(ISBLANK(A19),"""",IFERROR(SPARKLINE((F19-L19)/(N19-L19),{""charttype"",""bar"";""max"",1;""min"",0;""color1"",""2c79b5""}),""n/a""))"),"") | N19: =IFERROR(__xludf.DUMMYFUNCTION("IF(ISBLANK(A19),"""", googlefinance(A19, ""high52""))"),"") | O19: =if(isblank(A19),"",(F19-E19)*D19) | P19: =if(isblank(A19),"",O19+AE19) | Q19: =iferror(if(D19<0,0,O19/(E19*D19)),"") | R19: =if(isblank(A19),"",P19/(E19*D19)) | S19: (Select Security) | T19: (Select) | U19: (Select) | V19: =if(isblank(A19),"",AB19/$AB$32) | W19: =IFERROR(__xludf.DUMMYFUNCTION("IfError(IF(isblank(A19),"""",split(AK19, ""()"")))"),"") | Y19: =IFERROR(W19/E19,"") | AA19: =iferror(if(isblank(A19),"",D19*E19),0) | AB19: =IF(ISBLANK(A19),"",D19*F19) | AC19: =IFERROR(IF(ISBLANK(A19),"",D19*W19),"") | AD19: =if(isblank(A19),"",AC19/$AC$32) | AE19: =if(isblank(A19),"",SUM('Dividend Log'!S17,'Dividend Log'!S31,'Dividend Log'!S45,'Dividend Log'!S59,'Dividend Log'!S73)) | AF19: =IFERROR(AC19/F19,"") | AG19: =IF(ISBLANK(G19),"",(F19-G19)/G19) | AH19: =IF(G19="", "", IF(AG19<=-15%, "Strong Buy", IF(AG19<0%, "Buy", IF(AG19<=15%, "Expensive", "Overrated")))) | AI19: =IF(ISBLANK(A19),"",(F19-E19)/E19) | AJ19: =IF(A19="", "", IF(AI19<-15%, "Strong Buy", IF(AI19<-5%, "Buy", IF(AI19<5%, "Avg. Cost", IF(AI19<=15%, "Overcost", "Hold"))))) | AK19: =IFERROR(__xludf.DUMMYFUNCTION("IF(S19=""Stocks"", IfError(IF(isblank(A19),"""", substitute(index(IMPORTHTML(""http://finviz.com/quote.ashx?t=""&A19,""table"", 10),8,2),""*"","""")), 0), IfError(IF(isblank(A19),"""", substitute(index(IMPORTHTML(""http://finviz.com/quote.ashx?t"&"=""&A19,""table"", 10),7,2),""*"","""")), 0) )"),"")
B20: =IFERROR(__xludf.DUMMYFUNCTION("IF(ISBLANK(A20),"""", googlefinance(A20, ""name""))"),"") | C20: =IF(ISBLANK(A20),"", HYPERLINK("https://seekingalpha.com/symbol/" & A20,"View")) | F20: =IFERROR(__xludf.DUMMYFUNCTION("IF(ISBLANK(A20),"""", googlefinance(A20, ""price""))"),"") | H20: =IF(ISBLANK(A20),"",IFERROR(VLOOKUP(A20, 'Intrinsic Values List'!$A$2:$G$45, 7, FALSE), "Not found" )) | I20: =IFERROR(__xludf.DUMMYFUNCTION("IFERROR(googlefinance(A20,""change""),"""")"),"") | J20: =IFERROR(__xludf.DUMMYFUNCTION("iferror(GOOGLEFINANCE(A20,""changepct"")/100,"""")"),"") | K20: =if(isblank(A20),"",(D20*I20)) | L20: =IFERROR(__xludf.DUMMYFUNCTION("IF(ISBLANK(A20),"""", googlefinance(A20, ""low52""))"),"") | M20: =IFERROR(__xludf.DUMMYFUNCTION("IF(ISBLANK(A20),"""",IFERROR(SPARKLINE((F20-L20)/(N20-L20),{""charttype"",""bar"";""max"",1;""min"",0;""color1"",""2c79b5""}),""n/a""))"),"") | N20: =IFERROR(__xludf.DUMMYFUNCTION("IF(ISBLANK(A20),"""", googlefinance(A20, ""high52""))"),"") | O20: =if(isblank(A20),"",(F20-E20)*D20) | P20: =if(isblank(A20),"",O20+AE20) | Q20: =iferror(if(D20<0,0,O20/(E20*D20)),"") | R20: =if(isblank(A20),"",P20/(E20*D20)) | S20: (Select Security) | T20: (Select) | U20: (Select) | V20: =if(isblank(A20),"",AB20/$AB$32) | W20: =IFERROR(__xludf.DUMMYFUNCTION("IfError(IF(isblank(A20),"""",split(AK20, ""()"")))"),"") | Y20: =IFERROR(W20/E20,"") | AA20: =iferror(if(isblank(A20),"",D20*E20),0) | AB20: =IF(ISBLANK(A20),"",D20*F20) | AC20: =IFERROR(IF(ISBLANK(A20),"",D20*W20),"") | AD20: =if(isblank(A20),"",AC20/$AC$32) | AE20: =if(isblank(A20),"",SUM('Dividend Log'!T17,'Dividend Log'!T31,'Dividend Log'!T45,'Dividend Log'!T59,'Dividend Log'!T73)) | AF20: =IFERROR(AC20/F20,"") | AG20: =IF(ISBLANK(G20),"",(F20-G20)/G20) | AH20: =IF(G20="", "", IF(AG20<=-15%, "Strong Buy", IF(AG20<0%, "Buy", IF(AG20<=15%, "Expensive", "Overrated")))) | AI20: =IF(ISBLANK(A20),"",(F20-E20)/E20) | AJ20: =IF(A20="", "", IF(AI20<-15%, "Strong Buy", IF(AI20<-5%, "Buy", IF(AI20<5%, "Avg. Cost", IF(AI20<=15%, "Overcost", "Hold"))))) | AK20: =IFERROR(__xludf.DUMMYFUNCTION("IF(S20=""Stocks"", IfError(IF(isblank(A20),"""", substitute(index(IMPORTHTML(""http://finviz.com/quote.ashx?t=""&A20,""table"", 10),8,2),""*"","""")), 0), IfError(IF(isblank(A20),"""", substitute(index(IMPORTHTML(""http://finviz.com/quote.ashx?t"&"=""&A20,""table"", 10),7,2),""*"","""")), 0) )"),"")
B21: =IFERROR(__xludf.DUMMYFUNCTION("IF(ISBLANK(A21),"""", googlefinance(A21, ""name""))"),"") | C21: =IF(ISBLANK(A21),"", HYPERLINK("https://seekingalpha.com/symbol/" & A21,"View")) | F21: =IFERROR(__xludf.DUMMYFUNCTION("IF(ISBLANK(A21),"""", googlefinance(A21, ""price""))"),"") | H21: =IF(ISBLANK(A21),"",IFERROR(VLOOKUP(A21, 'Intrinsic Values List'!$A$2:$G$45, 7, FALSE), "Not found" )) | I21: =IFERROR(__xludf.DUMMYFUNCTION("IFERROR(googlefinance(A21,""change""),"""")"),"") | J21: =IFERROR(__xludf.DUMMYFUNCTION("iferror(GOOGLEFINANCE(A21,""changepct"")/100,"""")"),"") | K21: =if(isblank(A21),"",(D21*I21)) | L21: =IFERROR(__xludf.DUMMYFUNCTION("IF(ISBLANK(A21),"""", googlefinance(A21, ""low52""))"),"") | M21: =IFERROR(__xludf.DUMMYFUNCTION("IF(ISBLANK(A21),"""",IFERROR(SPARKLINE((F21-L21)/(N21-L21),{""charttype"",""bar"";""max"",1;""min"",0;""color1"",""2c79b5""}),""n/a""))"),"") | N21: =IFERROR(__xludf.DUMMYFUNCTION("IF(ISBLANK(A21),"""", googlefinance(A21, ""high52""))"),"") | O21: =if(isblank(A21),"",(F21-E21)*D21) | P21: =if(isblank(A21),"",O21+AE21) | Q21: =iferror(if(D21<0,0,O21/(E21*D21)),"") | R21: =if(isblank(A21),"",P21/(E21*D21)) | S21: (Select Security) | T21: (Select) | U21: (Select) | V21: =if(isblank(A21),"",AB21/$AB$32) | W21: =IFERROR(__xludf.DUMMYFUNCTION("IfError(IF(isblank(A21),"""",split(AK21, ""()"")))"),"") | Y21: =IFERROR(W21/E21,"") | AA21: =iferror(if(isblank(A21),"",D21*E21),0) | AB21: =IF(ISBLANK(A21),"",D21*F21) | AC21: =IFERROR(IF(ISBLANK(A21),"",D21*W21),"") | AD21: =if(isblank(A21),"",AC21/$AC$32) | AE21: =if(isblank(A21),"",SUM('Dividend Log'!U17,'Dividend Log'!U31,'Dividend Log'!U45,'Dividend Log'!U59,'Dividend Log'!U73)) | AF21: =IFERROR(AC21/F21,"") | AG21: =IF(ISBLANK(G21),"",(F21-G21)/G21) | AH21: =IF(G21="", "", IF(AG21<=-15%, "Strong Buy", IF(AG21<0%, "Buy", IF(AG21<=15%, "Expensive", "Overrated")))) | AI21: =IF(ISBLANK(A21),"",(F21-E21)/E21) | AJ21: =IF(A21="", "", IF(AI21<-15%, "Strong Buy", IF(AI21<-5%, "Buy", IF(AI21<5%, "Avg. Cost", IF(AI21<=15%, "Overcost", "Hold"))))) | AK21: =IFERROR(__xludf.DUMMYFUNCTION("IF(S21=""Stocks"", IfError(IF(isblank(A21),"""", substitute(index(IMPORTHTML(""http://finviz.com/quote.ashx?t=""&A21,""table"", 10),8,2),""*"","""")), 0), IfError(IF(isblank(A21),"""", substitute(index(IMPORTHTML(""http://finviz.com/quote.ashx?t"&"=""&A21,""table"", 10),7,2),""*"","""")), 0) )"),"")
B22: =IFERROR(__xludf.DUMMYFUNCTION("IF(ISBLANK(A22),"""", googlefinance(A22, ""name""))"),"") | C22: =IF(ISBLANK(A22),"", HYPERLINK("https://seekingalpha.com/symbol/" & A22,"View")) | F22: =IFERROR(__xludf.DUMMYFUNCTION("IF(ISBLANK(A22),"""", googlefinance(A22, ""price""))"),"") | H22: =IF(ISBLANK(A22),"",IFERROR(VLOOKUP(A22, 'Intrinsic Values List'!$A$2:$G$45, 7, FALSE), "Not found" )) | I22: =IFERROR(__xludf.DUMMYFUNCTION("IFERROR(googlefinance(A22,""change""),"""")"),"") | J22: =IFERROR(__xludf.DUMMYFUNCTION("iferror(GOOGLEFINANCE(A22,""changepct"")/100,"""")"),"") | K22: =if(isblank(A22),"",(D22*I22)) | L22: =IFERROR(__xludf.DUMMYFUNCTION("IF(ISBLANK(A22),"""", googlefinance(A22, ""low52""))"),"") | M22: =IFERROR(__xludf.DUMMYFUNCTION("IF(ISBLANK(A22),"""",IFERROR(SPARKLINE((F22-L22)/(N22-L22),{""charttype"",""bar"";""max"",1;""min"",0;""color1"",""2c79b5""}),""n/a""))"),"") | N22: =IFERROR(__xludf.DUMMYFUNCTION("IF(ISBLANK(A22),"""", googlefinance(A22, ""high52""))"),"") | O22: =if(isblank(A22),"",(F22-E22)*D22) | P22: =if(isblank(A22),"",O22+AE22) | Q22: =iferror(if(D22<0,0,O22/(E22*D22)),"") | R22: =if(isblank(A22),"",P22/(E22*D22)) | S22: (Select Security) | T22: (Select) | U22: (Select) | V22: =if(isblank(A22),"",AB22/$AB$32) | W22: =IFERROR(__xludf.DUMMYFUNCTION("IfError(IF(isblank(A22),"""",split(AK22, ""()"")))"),"") | Y22: =IFERROR(W22/E22,"") | AA22: =iferror(if(isblank(A22),"",D22*E22),0) | AB22: =IF(ISBLANK(A22),"",D22*F22) | AC22: =IFERROR(IF(ISBLANK(A22),"",D22*W22),"") | AD22: =if(isblank(A22),"",AC22/$AC$32) | AE22: =if(isblank(A22),"",SUM('Dividend Log'!V17,'Dividend Log'!V31,'Dividend Log'!V45,'Dividend Log'!V59,'Dividend Log'!V73)) | AF22: =IFERROR(AC22/F22,"") | AG22: =IF(ISBLANK(G22),"",(F22-G22)/G22) | AH22: =IF(G22="", "", IF(AG22<=-15%, "Strong Buy", IF(AG22<0%, "Buy", IF(AG22<=15%, "Expensive", "Overrated")))) | AI22: =IF(ISBLANK(A22),"",(F22-E22)/E22) | AJ22: =IF(A22="", "", IF(AI22<-15%, "Strong Buy", IF(AI22<-5%, "Buy", IF(AI22<5%, "Avg. Cost", IF(AI22<=15%, "Overcost", "Hold"))))) | AK22: =IFERROR(__xludf.DUMMYFUNCTION("IF(S22=""Stocks"", IfError(IF(isblank(A22),"""", substitute(index(IMPORTHTML(""http://finviz.com/quote.ashx?t=""&A22,""table"", 10),8,2),""*"","""")), 0), IfError(IF(isblank(A22),"""", substitute(index(IMPORTHTML(""http://finviz.com/quote.ashx?t"&"=""&A22,""table"", 10),7,2),""*"","""")), 0) )"),"")
B23: =IFERROR(__xludf.DUMMYFUNCTION("IF(ISBLANK(A23),"""", googlefinance(A23, ""name""))"),"") | C23: =IF(ISBLANK(A23),"", HYPERLINK("https://seekingalpha.com/symbol/" & A23,"View")) | F23: =IFERROR(__xludf.DUMMYFUNCTION("IF(ISBLANK(A23),"""", googlefinance(A23, ""price""))"),"") | H23: =IF(ISBLANK(A23),"",IFERROR(VLOOKUP(A23, 'Intrinsic Values List'!$A$2:$G$45, 7, FALSE), "Not found" )) | I23: =IFERROR(__xludf.DUMMYFUNCTION("IFERROR(googlefinance(A23,""change""),"""")"),"") | J23: =IFERROR(__xludf.DUMMYFUNCTION("iferror(GOOGLEFINANCE(A23,""changepct"")/100,"""")"),"") | K23: =if(isblank(A23),"",(D23*I23)) | L23: =IFERROR(__xludf.DUMMYFUNCTION("IF(ISBLANK(A23),"""", googlefinance(A23, ""low52""))"),"") | M23: =IFERROR(__xludf.DUMMYFUNCTION("IF(ISBLANK(A23),"""",IFERROR(SPARKLINE((F23-L23)/(N23-L23),{""charttype"",""bar"";""max"",1;""min"",0;""color1"",""2c79b5""}),""n/a""))"),"") | N23: =IFERROR(__xludf.DUMMYFUNCTION("IF(ISBLANK(A23),"""", googlefinance(A23, ""high52""))"),"") | O23: =if(isblank(A23),"",(F23-E23)*D23) | P23: =if(isblank(A23),"",O23+AE23) | Q23: =iferror(if(D23<0,0,O23/(E23*D23)),"") | R23: =if(isblank(A23),"",P23/(E23*D23)) | S23: (Select Security) | T23: (Select) | U23: (Select) | V23: =if(isblank(A23),"",AB23/$AB$32) | W23: =IFERROR(__xludf.DUMMYFUNCTION("IfError(IF(isblank(A23),"""",split(AK23, ""()"")))"),"") | Y23: =IFERROR(W23/E23,"") | AA23: =iferror(if(isblank(A23),"",D23*E23),0) | AB23: =IF(ISBLANK(A23),"",D23*F23) | AC23: =IFERROR(IF(ISBLANK(A23),"",D23*W23),"") | AD23: =if(isblank(A23),"",AC23/$AC$32) | AE23: =if(isblank(A23),"",SUM('Dividend Log'!W17,'Dividend Log'!W31,'Dividend Log'!W45,'Dividend Log'!W59,'Dividend Log'!W73)) | AF23: =IFERROR(AC23/F23,"") | AG23: =IF(ISBLANK(G23),"",(F23-G23)/G23) | AH23: =IF(G23="", "", IF(AG23<=-15%, "Strong Buy", IF(AG23<0%, "Buy", IF(AG23<=15%, "Expensive", "Overrated")))) | AI23: =IF(ISBLANK(A23),"",(F23-E23)/E23) | AJ23: =IF(A23="", "", IF(AI23<-15%, "Strong Buy", IF(AI23<-5%, "Buy", IF(AI23<5%, "Avg. Cost", IF(AI23<=15%, "Overcost", "Hold"))))) | AK23: =IFERROR(__xludf.DUMMYFUNCTION("IF(S23=""Stocks"", IfError(IF(isblank(A23),"""", substitute(index(IMPORTHTML(""http://finviz.com/quote.ashx?t=""&A23,""table"", 10),8,2),""*"","""")), 0), IfError(IF(isblank(A23),"""", substitute(index(IMPORTHTML(""http://finviz.com/quote.ashx?t"&"=""&A23,""table"", 10),7,2),""*"","""")), 0) )"),"")
B24: =IFERROR(__xludf.DUMMYFUNCTION("IF(ISBLANK(A24),"""", googlefinance(A24, ""name""))"),"") | C24: =IF(ISBLANK(A24),"", HYPERLINK("https://seekingalpha.com/symbol/" & A24,"View")) | F24: =IFERROR(__xludf.DUMMYFUNCTION("IF(ISBLANK(A24),"""", googlefinance(A24, ""price""))"),"") | H24: =IF(ISBLANK(A24),"",IFERROR(VLOOKUP(A24, 'Intrinsic Values List'!$A$2:$G$45, 7, FALSE), "Not found" )) | I24: =IFERROR(__xludf.DUMMYFUNCTION("IFERROR(googlefinance(A24,""change""),"""")"),"") | J24: =IFERROR(__xludf.DUMMYFUNCTION("iferror(GOOGLEFINANCE(A24,""changepct"")/100,"""")"),"") | K24: =if(isblank(A24),"",(D24*I24)) | L24: =IFERROR(__xludf.DUMMYFUNCTION("IF(ISBLANK(A24),"""", googlefinance(A24, ""low52""))"),"") | M24: =IFERROR(__xludf.DUMMYFUNCTION("IF(ISBLANK(A24),"""",IFERROR(SPARKLINE((F24-L24)/(N24-L24),{""charttype"",""bar"";""max"",1;""min"",0;""color1"",""2c79b5""}),""n/a""))"),"") | N24: =IFERROR(__xludf.DUMMYFUNCTION("IF(ISBLANK(A24),"""", googlefinance(A24, ""high52""))"),"") | O24: =if(isblank(A24),"",(F24-E24)*D24) | P24: =if(isblank(A24),"",O24+AE24) | Q24: =iferror(if(D24<0,0,O24/(E24*D24)),"") | R24: =if(isblank(A24),"",P24/(E24*D24)) | S24: (Select Security) | T24: (Select) | U24: (Select) | V24: =if(isblank(A24),"",AB24/$AB$32) | W24: =IFERROR(__xludf.DUMMYFUNCTION("IfError(IF(isblank(A24),"""",split(AK24, ""()"")))"),"") | Y24: =IFERROR(W24/E24,"") | AA24: =iferror(if(isblank(A24),"",D24*E24),0) | AB24: =IF(ISBLANK(A24),"",D24*F24) | AC24: =IFERROR(IF(ISBLANK(A24),"",D24*W24),"") | AD24: =if(isblank(A24),"",AC24/$AC$32) | AE24: =if(isblank(A24),"",SUM('Dividend Log'!X17,'Dividend Log'!X31,'Dividend Log'!X45,'Dividend Log'!X59,'Dividend Log'!X73)) | AF24: =IFERROR(AC24/F24,"") | AG24: =IF(ISBLANK(G24),"",(F24-G24)/G24) | AH24: =IF(G24="", "", IF(AG24<=-15%, "Strong Buy", IF(AG24<0%, "Buy", IF(AG24<=15%, "Expensive", "Overrated")))) | AI24: =IF(ISBLANK(A24),"",(F24-E24)/E24) | AJ24: =IF(A24="", "", IF(AI24<-15%, "Strong Buy", IF(AI24<-5%, "Buy", IF(AI24<5%, "Avg. Cost", IF(AI24<=15%, "Overcost", "Hold"))))) | AK24: =IFERROR(__xludf.DUMMYFUNCTION("IF(S24=""Stocks"", IfError(IF(isblank(A24),"""", substitute(index(IMPORTHTML(""http://finviz.com/quote.ashx?t=""&A24,""table"", 10),8,2),""*"","""")), 0), IfError(IF(isblank(A24),"""", substitute(index(IMPORTHTML(""http://finviz.com/quote.ashx?t"&"=""&A24,""table"", 10),7,2),""*"","""")), 0) )"),"")
B25: =IFERROR(__xludf.DUMMYFUNCTION("IF(ISBLANK(A25),"""", googlefinance(A25, ""name""))"),"") | C25: =IF(ISBLANK(A25),"", HYPERLINK("https://seekingalpha.com/symbol/" & A25,"View")) | F25: =IFERROR(__xludf.DUMMYFUNCTION("IF(ISBLANK(A25),"""", googlefinance(A25, ""price""))"),"") | H25: =IF(ISBLANK(A25),"",IFERROR(VLOOKUP(A25, 'Intrinsic Values List'!$A$2:$G$45, 7, FALSE), "Not found" )) | I25: =IFERROR(__xludf.DUMMYFUNCTION("IFERROR(googlefinance(A25,""change""),"""")"),"") | J25: =IFERROR(__xludf.DUMMYFUNCTION("iferror(GOOGLEFINANCE(A25,""changepct"")/100,"""")"),"") | K25: =if(isblank(A25),"",(D25*I25)) | L25: =IFERROR(__xludf.DUMMYFUNCTION("IF(ISBLANK(A25),"""", googlefinance(A25, ""low52""))"),"") | M25: =IFERROR(__xludf.DUMMYFUNCTION("IF(ISBLANK(A25),"""",IFERROR(SPARKLINE((F25-L25)/(N25-L25),{""charttype"",""bar"";""max"",1;""min"",0;""color1"",""2c79b5""}),""n/a""))"),"") | N25: =IFERROR(__xludf.DUMMYFUNCTION("IF(ISBLANK(A25),"""", googlefinance(A25, ""high52""))"),"") | O25: =if(isblank(A25),"",(F25-E25)*D25) | P25: =if(isblank(A25),"",O25+AE25) | Q25: =iferror(if(D25<0,0,O25/(E25*D25)),"") | R25: =if(isblank(A25),"",P25/(E25*D25)) | S25: (Select Security) | T25: (Select) | U25: (Select) | V25: =if(isblank(A25),"",AB25/$AB$32) | W25: =IFERROR(__xludf.DUMMYFUNCTION("IfError(IF(isblank(A25),"""",split(AK25, ""()"")))"),"") | Y25: =IFERROR(W25/E25,"") | AA25: =iferror(if(isblank(A25),"",D25*E25),0) | AB25: =IF(ISBLANK(A25),"",D25*F25) | AC25: =IFERROR(IF(ISBLANK(A25),"",D25*W25),"") | AD25: =if(isblank(A25),"",AC25/$AC$32) | AE25: =if(isblank(A25),"",SUM('Dividend Log'!Y17,'Dividend Log'!Y31,'Dividend Log'!Y45,'Dividend Log'!Y59,'Dividend Log'!Y73)) | AF25: =IFERROR(AC25/F25,"") | AG25: =IF(ISBLANK(G25),"",(F25-G25)/G25) | AH25: =IF(G25="", "", IF(AG25<=-15%, "Strong Buy", IF(AG25<0%, "Buy", IF(AG25<=15%, "Expensive", "Overrated")))) | AI25: =IF(ISBLANK(A25),"",(F25-E25)/E25) | AJ25: =IF(A25="", "", IF(AI25<-15%, "Strong Buy", IF(AI25<-5%, "Buy", IF(AI25<5%, "Avg. Cost", IF(AI25<=15%, "Overcost", "Hold"))))) | AK25: =IFERROR(__xludf.DUMMYFUNCTION("IF(S25=""Stocks"", IfError(IF(isblank(A25),"""", substitute(index(IMPORTHTML(""http://finviz.com/quote.ashx?t=""&A25,""table"", 10),8,2),""*"","""")), 0), IfError(IF(isblank(A25),"""", substitute(index(IMPORTHTML(""http://finviz.com/quote.ashx?t"&"=""&A25,""table"", 10),7,2),""*"","""")), 0) )"),"")
B26: =IFERROR(__xludf.DUMMYFUNCTION("IF(ISBLANK(A26),"""", googlefinance(A26, ""name""))"),"") | C26: =IF(ISBLANK(A26),"", HYPERLINK("https://seekingalpha.com/symbol/" & A26,"View")) | F26: =IFERROR(__xludf.DUMMYFUNCTION("IF(ISBLANK(A26),"""", googlefinance(A26, ""price""))"),"") | H26: =IF(ISBLANK(A26),"",IFERROR(VLOOKUP(A26, 'Intrinsic Values List'!$A$2:$G$45, 7, FALSE), "Not found" )) | I26: =IFERROR(__xludf.DUMMYFUNCTION("IFERROR(googlefinance(A26,""change""),"""")"),"") | J26: =IFERROR(__xludf.DUMMYFUNCTION("iferror(GOOGLEFINANCE(A26,""changepct"")/100,"""")"),"") | K26: =if(isblank(A26),"",(D26*I26)) | L26: =IFERROR(__xludf.DUMMYFUNCTION("IF(ISBLANK(A26),"""", googlefinance(A26, ""low52""))"),"") | M26: =IFERROR(__xludf.DUMMYFUNCTION("IF(ISBLANK(A26),"""",IFERROR(SPARKLINE((F26-L26)/(N26-L26),{""charttype"",""bar"";""max"",1;""min"",0;""color1"",""2c79b5""}),""n/a""))"),"") | N26: =IFERROR(__xludf.DUMMYFUNCTION("IF(ISBLANK(A26),"""", googlefinance(A26, ""high52""))"),"") | O26: =if(isblank(A26),"",(F26-E26)*D26) | P26: =if(isblank(A26),"",O26+AE26) | Q26: =iferror(if(D26<0,0,O26/(E26*D26)),"") | R26: =if(isblank(A26),"",P26/(E26*D26)) | S26: (Select Security) | T26: (Select) | U26: (Select) | V26: =if(isblank(A26),"",AB26/$AB$32) | W26: =IFERROR(__xludf.DUMMYFUNCTION("IfError(IF(isblank(A26),"""",split(AK26, ""()"")))"),"") | Y26: =IFERROR(W26/E26,"") | AA26: =iferror(if(isblank(A26),"",D26*E26),0) | AB26: =IF(ISBLANK(A26),"",D26*F26) | AC26: =IFERROR(IF(ISBLANK(A26),"",D26*W26),"") | AD26: =if(isblank(A26),"",AC26/$AC$32) | AE26: =if(isblank(A26),"",SUM('Dividend Log'!Z17,'Dividend Log'!Z31,'Dividend Log'!Z45,'Dividend Log'!Z59,'Dividend Log'!Z73)) | AF26: =IFERROR(AC26/F26,"") | AG26: =IF(ISBLANK(G26),"",(F26-G26)/G26) | AH26: =IF(G26="", "", IF(AG26<=-15%, "Strong Buy", IF(AG26<0%, "Buy", IF(AG26<=15%, "Expensive", "Overrated")))) | AI26: =IF(ISBLANK(A26),"",(F26-E26)/E26) | AJ26: =IF(A26="", "", IF(AI26<-15%, "Strong Buy", IF(AI26<-5%, "Buy", IF(AI26<5%, "Avg. Cost", IF(AI26<=15%, "Overcost", "Hold"))))) | AK26: =IFERROR(__xludf.DUMMYFUNCTION("IF(S26=""Stocks"", IfError(IF(isblank(A26),"""", substitute(index(IMPORTHTML(""http://finviz.com/quote.ashx?t=""&A26,""table"", 10),8,2),""*"","""")), 0), IfError(IF(isblank(A26),"""", substitute(index(IMPORTHTML(""http://finviz.com/quote.ashx?t"&"=""&A26,""table"", 10),7,2),""*"","""")), 0) )"),"")
B27: =IFERROR(__xludf.DUMMYFUNCTION("IF(ISBLANK(A27),"""", googlefinance(A27, ""name""))"),"") | C27: =IF(ISBLANK(A27),"", HYPERLINK("https://seekingalpha.com/symbol/" & A27,"View")) | F27: =IFERROR(__xludf.DUMMYFUNCTION("IF(ISBLANK(A27),"""", googlefinance(A27, ""price""))"),"") | H27: =IF(ISBLANK(A27),"",IFERROR(VLOOKUP(A27, 'Intrinsic Values List'!$A$2:$G$45, 7, FALSE), "Not found" )) | I27: =IFERROR(__xludf.DUMMYFUNCTION("IFERROR(googlefinance(A27,""change""),"""")"),"") | J27: =IFERROR(__xludf.DUMMYFUNCTION("iferror(GOOGLEFINANCE(A27,""changepct"")/100,"""")"),"") | K27: =if(isblank(A27),"",(D27*I27)) | L27: =IFERROR(__xludf.DUMMYFUNCTION("IF(ISBLANK(A27),"""", googlefinance(A27, ""low52""))"),"") | M27: =IFERROR(__xludf.DUMMYFUNCTION("IF(ISBLANK(A27),"""",IFERROR(SPARKLINE((F27-L27)/(N27-L27),{""charttype"",""bar"";""max"",1;""min"",0;""color1"",""2c79b5""}),""n/a""))"),"") | N27: =IFERROR(__xludf.DUMMYFUNCTION("IF(ISBLANK(A27),"""", googlefinance(A27, ""high52""))"),"") | O27: =if(isblank(A27),"",(F27-E27)*D27) | P27: =if(isblank(A27),"",O27+AE27) | Q27: =iferror(if(D27<0,0,O27/(E27*D27)),"") | R27: =if(isblank(A27),"",P27/(E27*D27)) | S27: (Select Security) | T27: (Select) | U27: (Select) | V27: =if(isblank(A27),"",AB27/$AB$32) | W27: =IFERROR(__xludf.DUMMYFUNCTION("IfError(IF(isblank(A27),"""",split(AK27, ""()"")))"),"") | Y27: =IFERROR(W27/E27,"") | AA27: =iferror(if(isblank(A27),"",D27*E27),0) | AB27: =IF(ISBLANK(A27),"",D27*F27) | AC27: =IFERROR(IF(ISBLANK(A27),"",D27*W27),"") | AD27: =if(isblank(A27),"",AC27/$AC$32) | AE27: =if(isblank(A27),"",SUM('Dividend Log'!AA17,'Dividend Log'!AA31,'Dividend Log'!AA45,'Dividend Log'!AA59,'Dividend Log'!AA73)) | AF27: =IFERROR(AC27/F27,"") | AG27: =IF(ISBLANK(G27),"",(F27-G27)/G27) | AH27: =IF(G27="", "", IF(AG27<=-15%, "Strong Buy", IF(AG27<0%, "Buy", IF(AG27<=15%, "Expensive", "Overrated")))) | AI27: =IF(ISBLANK(A27),"",(F27-E27)/E27) | AJ27: =IF(A27="", "", IF(AI27<-15%, "Strong Buy", IF(AI27<-5%, "Buy", IF(AI27<5%, "Avg. Cost", IF(AI27<=15%, "Overcost", "Hold"))))) | AK27: =IFERROR(__xludf.DUMMYFUNCTION("IF(S27=""Stocks"", IfError(IF(isblank(A27),"""", substitute(index(IMPORTHTML(""http://finviz.com/quote.ashx?t=""&A27,""table"", 10),8,2),""*"","""")), 0), IfError(IF(isblank(A27),"""", substitute(index(IMPORTHTML(""http://finviz.com/quote.ashx?t"&"=""&A27,""table"", 10),7,2),""*"","""")), 0) )"),"")
B28: =IFERROR(__xludf.DUMMYFUNCTION("IF(ISBLANK(A28),"""", googlefinance(A28, ""name""))"),"") | C28: =IF(ISBLANK(A28),"", HYPERLINK("https://seekingalpha.com/symbol/" & A28,"View")) | F28: =IFERROR(__xludf.DUMMYFUNCTION("IF(ISBLANK(A28),"""", googlefinance(A28, ""price""))"),"") | H28: =IF(ISBLANK(A28),"",IFERROR(VLOOKUP(A28, 'Intrinsic Values List'!$A$2:$G$45, 7, FALSE), "Not found" )) | I28: =IFERROR(__xludf.DUMMYFUNCTION("IFERROR(googlefinance(A28,""change""),"""")"),"") | J28: =IFERROR(__xludf.DUMMYFUNCTION("iferror(GOOGLEFINANCE(A28,""changepct"")/100,"""")"),"") | K28: =if(isblank(A28),"",(D28*I28)) | L28: =IFERROR(__xludf.DUMMYFUNCTION("IF(ISBLANK(A28),"""", googlefinance(A28, ""low52""))"),"") | M28: =IFERROR(__xludf.DUMMYFUNCTION("IF(ISBLANK(A28),"""",IFERROR(SPARKLINE((F28-L28)/(N28-L28),{""charttype"",""bar"";""max"",1;""min"",0;""color1"",""2c79b5""}),""n/a""))"),"") | N28: =IFERROR(__xludf.DUMMYFUNCTION("IF(ISBLANK(A28),"""", googlefinance(A28, ""high52""))"),"") | O28: =if(isblank(A28),"",(F28-E28)*D28) | P28: =if(isblank(A28),"",O28+AE28) | Q28: =iferror(if(D28<0,0,O28/(E28*D28)),"") | R28: =if(isblank(A28),"",P28/(E28*D28)) | S28: (Select Security) | T28: (Select) | U28: (Select) | V28: =if(isblank(A28),"",AB28/$AB$32) | W28: =IFERROR(__xludf.DUMMYFUNCTION("IfError(IF(isblank(A28),"""",split(AK28, ""()"")))"),"") | Y28: =IFERROR(W28/E28,"") | AA28: =iferror(if(isblank(A28),"",D28*E28),0) | AB28: =IF(ISBLANK(A28),"",D28*F28) | AC28: =IFERROR(IF(ISBLANK(A28),"",D28*W28),"") | AD28: =if(isblank(A28),"",AC28/$AC$32) | AE28: =if(isblank(A28),"",SUM('Dividend Log'!AB17,'Dividend Log'!AB31,'Dividend Log'!AB45,'Dividend Log'!AB59,'Dividend Log'!AB73)) | AF28: =IFERROR(AC28/F28,"") | AG28: =IF(ISBLANK(G28),"",(F28-G28)/G28) | AH28: =IF(G28="", "", IF(AG28<=-15%, "Strong Buy", IF(AG28<0%, "Buy", IF(AG28<=15%, "Expensive", "Overrated")))) | AI28: =IF(ISBLANK(A28),"",(F28-E28)/E28) | AJ28: =IF(A28="", "", IF(AI28<-15%, "Strong Buy", IF(AI28<-5%, "Buy", IF(AI28<5%, "Avg. Cost", IF(AI28<=15%, "Overcost", "Hold"))))) | AK28: =IFERROR(__xludf.DUMMYFUNCTION("IF(S28=""Stocks"", IfError(IF(isblank(A28),"""", substitute(index(IMPORTHTML(""http://finviz.com/quote.ashx?t=""&A28,""table"", 10),8,2),""*"","""")), 0), IfError(IF(isblank(A28),"""", substitute(index(IMPORTHTML(""http://finviz.com/quote.ashx?t"&"=""&A28,""table"", 10),7,2),""*"","""")), 0) )"),"")
B29: =IFERROR(__xludf.DUMMYFUNCTION("IF(ISBLANK(A29),"""", googlefinance(A29, ""name""))"),"") | C29: =IF(ISBLANK(A29),"", HYPERLINK("https://seekingalpha.com/symbol/" & A29,"View")) | F29: =IFERROR(__xludf.DUMMYFUNCTION("IF(ISBLANK(A29),"""", googlefinance(A29, ""price""))"),"") | H29: =IF(ISBLANK(A29),"",IFERROR(VLOOKUP(A29, 'Intrinsic Values List'!$A$2:$G$45, 7, FALSE), "Not found" )) | I29: =IFERROR(__xludf.DUMMYFUNCTION("IFERROR(googlefinance(A29,""change""),"""")"),"") | J29: =IFERROR(__xludf.DUMMYFUNCTION("iferror(GOOGLEFINANCE(A29,""changepct"")/100,"""")"),"") | K29: =if(isblank(A29),"",(D29*I29)) | L29: =IFERROR(__xludf.DUMMYFUNCTION("IF(ISBLANK(A29),"""", googlefinance(A29, ""low52""))"),"") | M29: =IFERROR(__xludf.DUMMYFUNCTION("IF(ISBLANK(A29),"""",IFERROR(SPARKLINE((F29-L29)/(N29-L29),{""charttype"",""bar"";""max"",1;""min"",0;""color1"",""2c79b5""}),""n/a""))"),"") | N29: =IFERROR(__xludf.DUMMYFUNCTION("IF(ISBLANK(A29),"""", googlefinance(A29, ""high52""))"),"") | O29: =if(isblank(A29),"",(F29-E29)*D29) | P29: =if(isblank(A29),"",O29+AE29) | Q29: =iferror(if(D29<0,0,O29/(E29*D29)),"") | R29: =if(isblank(A29),"",P29/(E29*D29)) | S29: (Select Security) | T29: (Select) | U29: (Select) | V29: =if(isblank(A29),"",AB29/$AB$32) | W29: =IFERROR(__xludf.DUMMYFUNCTION("IfError(IF(isblank(A29),"""",split(AK29, ""()"")))"),"") | Y29: =IFERROR(W29/E29,"") | AA29: =iferror(if(isblank(A29),"",D29*E29),0) | AB29: =IF(ISBLANK(A29),"",D29*F29) | AC29: =IFERROR(IF(ISBLANK(A29),"",D29*W29),"") | AD29: =if(isblank(A29),"",AC29/$AC$32) | AE29: =if(isblank(A29),"",SUM('Dividend Log'!AC17,'Dividend Log'!AC31,'Dividend Log'!AC45,'Dividend Log'!AC59,'Dividend Log'!AC73)) | AF29: =IFERROR(AC29/F29,"") | AG29: =IF(ISBLANK(G29),"",(F29-G29)/G29) | AH29: =IF(G29="", "", IF(AG29<=-15%, "Strong Buy", IF(AG29<0%, "Buy", IF(AG29<=15%, "Expensive", "Overrated")))) | AI29: =IF(ISBLANK(A29),"",(F29-E29)/E29) | AJ29: =IF(A29="", "", IF(AI29<-15%, "Strong Buy", IF(AI29<-5%, "Buy", IF(AI29<5%, "Avg. Cost", IF(AI29<=15%, "Overcost", "Hold"))))) | AK29: =IFERROR(__xludf.DUMMYFUNCTION("IF(S29=""Stocks"", IfError(IF(isblank(A29),"""", substitute(index(IMPORTHTML(""http://finviz.com/quote.ashx?t=""&A29,""table"", 10),8,2),""*"","""")), 0), IfError(IF(isblank(A29),"""", substitute(index(IMPORTHTML(""http://finviz.com/quote.ashx?t"&"=""&A29,""table"", 10),7,2),""*"","""")), 0) )"),"")
B30: =IFERROR(__xludf.DUMMYFUNCTION("IF(ISBLANK(A30),"""", googlefinance(A30, ""name""))"),"") | C30: =IF(ISBLANK(A30),"", HYPERLINK("https://seekingalpha.com/symbol/" & A30,"View")) | F30: =IFERROR(__xludf.DUMMYFUNCTION("IF(ISBLANK(A30),"""", googlefinance(A30, ""price""))"),"") | H30: =IF(ISBLANK(A30),"",IFERROR(VLOOKUP(A30, 'Intrinsic Values List'!$A$2:$G$45, 7, FALSE), "Not found" )) | I30: =IFERROR(__xludf.DUMMYFUNCTION("IFERROR(googlefinance(A30,""change""),"""")"),"") | J30: =IFERROR(__xludf.DUMMYFUNCTION("iferror(GOOGLEFINANCE(A30,""changepct"")/100,"""")"),"") | K30: =if(isblank(A30),"",(D30*I30)) | L30: =IFERROR(__xludf.DUMMYFUNCTION("IF(ISBLANK(A30),"""", googlefinance(A30, ""low52""))"),"") | M30: =IFERROR(__xludf.DUMMYFUNCTION("IF(ISBLANK(A30),"""",IFERROR(SPARKLINE((F30-L30)/(N30-L30),{""charttype"",""bar"";""max"",1;""min"",0;""color1"",""2c79b5""}),""n/a""))"),"") | N30: =IFERROR(__xludf.DUMMYFUNCTION("IF(ISBLANK(A30),"""", googlefinance(A30, ""high52""))"),"") | O30: =if(isblank(A30),"",(F30-E30)*D30) | P30: =if(isblank(A30),"",O30+AE30) | Q30: =iferror(if(D30<0,0,O30/(E30*D30)),"") | R30: =if(isblank(A30),"",P30/(E30*D30)) | S30: (Select Security) | T30: (Select) | U30: (Select) | V30: =if(isblank(A30),"",AB30/$AB$32) | W30: =IFERROR(__xludf.DUMMYFUNCTION("IfError(IF(isblank(A30),"""",split(AK30, ""()"")))"),"") | Y30: =IFERROR(W30/E30,"") | AA30: =iferror(if(isblank(A30),"",D30*E30),0) | AB30: =IF(ISBLANK(A30),"",D30*F30) | AC30: =IFERROR(IF(ISBLANK(A30),"",D30*W30),"") | AD30: =if(isblank(A30),"",AC30/$AC$32) | AE30: =if(isblank(A30),"",SUM('Dividend Log'!AD17,'Dividend Log'!AD31,'Dividend Log'!AD45,'Dividend Log'!AD59,'Dividend Log'!AD73)) | AF30: =IFERROR(AC30/F30,"") | AG30: =IF(ISBLANK(G30),"",(F30-G30)/G30) | AH30: =IF(G30="", "", IF(AG30<=-15%, "Strong Buy", IF(AG30<0%, "Buy", IF(AG30<=15%, "Expensive", "Overrated")))) | AI30: =IF(ISBLANK(A30),"",(F30-E30)/E30) | AJ30: =IF(A30="", "", IF(AI30<-15%, "Strong Buy", IF(AI30<-5%, "Buy", IF(AI30<5%, "Avg. Cost", IF(AI30<=15%, "Overcost", "Hold"))))) | AK30: =IFERROR(__xludf.DUMMYFUNCTION("IF(S30=""Stocks"", IfError(IF(isblank(A30),"""", substitute(index(IMPORTHTML(""http://finviz.com/quote.ashx?t=""&A30,""table"", 10),8,2),""*"","""")), 0), IfError(IF(isblank(A30),"""", substitute(index(IMPORTHTML(""http://finviz.com/quote.ashx?t"&"=""&A30,""table"", 10),7,2),""*"","""")), 0) )"),"")
B31: =IFERROR(__xludf.DUMMYFUNCTION("IF(ISBLANK(A31),"""", googlefinance(A31, ""name""))"),"") | C31: =IF(ISBLANK(A31),"", HYPERLINK("https://seekingalpha.com/symbol/" & A31,"View")) | F31: =IFERROR(__xludf.DUMMYFUNCTION("IF(ISBLANK(A31),"""", googlefinance(A31, ""price""))"),"") | H31: =IF(ISBLANK(A31),"",IFERROR(VLOOKUP(A31, 'Intrinsic Values List'!$A$2:$G$45, 7, FALSE), "Not found" )) | I31: =IFERROR(__xludf.DUMMYFUNCTION("IFERROR(googlefinance(A31,""change""),"""")"),"") | J31: =IFERROR(__xludf.DUMMYFUNCTION("iferror(GOOGLEFINANCE(A31,""changepct"")/100,"""")"),"") | K31: =if(isblank(A31),"",(D31*I31)) | L31: =IFERROR(__xludf.DUMMYFUNCTION("IF(ISBLANK(A31),"""", googlefinance(A31, ""low52""))"),"") | M31: =IFERROR(__xludf.DUMMYFUNCTION("IF(ISBLANK(A31),"""",IFERROR(SPARKLINE((F31-L31)/(N31-L31),{""charttype"",""bar"";""max"",1;""min"",0;""color1"",""2c79b5""}),""n/a""))"),"") | N31: =IFERROR(__xludf.DUMMYFUNCTION("IF(ISBLANK(A31),"""", googlefinance(A31, ""high52""))"),"") | O31: =if(isblank(A31),"",(F31-E31)*D31) | P31: =if(isblank(A31),"",O31+AE31) | Q31: =iferror(if(D31<0,0,O31/(E31*D31)),"") | R31: =if(isblank(A31),"",P31/(E31*D31)) | S31: (Select Security) | T31: (Select) | U31: (Select) | V31: =if(isblank(A31),"",AB31/$AB$32) | W31: =IFERROR(__xludf.DUMMYFUNCTION("IfError(IF(isblank(A31),"""",split(AK31, ""()"")))"),"") | Y31: =IFERROR(W31/E31,"") | AA31: =iferror(if(isblank(A31),"",D31*E31),0) | AB31: =IF(ISBLANK(A31),"",D31*F31) | AC31: =IFERROR(IF(ISBLANK(A31),"",D31*W31),"") | AD31: =if(isblank(A31),"",AC31/$AC$32) | AE31: =if(isblank(A31),"",SUM('Dividend Log'!AE17,'Dividend Log'!AE31,'Dividend Log'!AE45,'Dividend Log'!AE59,'Dividend Log'!AE73)) | AF31: =IFERROR(AC31/F31,"") | AG31: =IF(ISBLANK(G31),"",(F31-G31)/G31) | AH31: =IF(G31="", "", IF(AG31<=-15%, "Strong Buy", IF(AG31<0%, "Buy", IF(AG31<=15%, "Expensive", "Overrated")))) | AI31: =IF(ISBLANK(A31),"",(F31-E31)/E31) | AJ31: =IF(A31="", "", IF(AI31<-15%, "Strong Buy", IF(AI31<-5%, "Buy", IF(AI31<5%, "Avg. Cost", IF(AI31<=15%, "Overcost", "Hold"))))) | AK31: =IFERROR(__xludf.DUMMYFUNCTION("IF(S31=""Stocks"", IfError(IF(isblank(A31),"""", substitute(index(IMPORTHTML(""http://finviz.com/quote.ashx?t=""&A31,""table"", 10),8,2),""*"","""")), 0), IfError(IF(isblank(A31),"""", substitute(index(IMPORTHTML(""http://finviz.com/quote.ashx?t"&"=""&A31,""table"", 10),7,2),""*"","""")), 0) )"),"")
A32: =COUNTA(A2:A31) -> 17 | B32: <-- Total Holdings | J32: =K32/(AB32+K32) -> -0.0037180869 | K32: =SUM(K2:K31) -> -149.30738 | O32: =SUM(O2:O31) -> 5464.6604 | P32: =SUM(O32,AE32) -> 6471.6504 | Q32: =O32/(AA32-C34) -> 0.20328763 | R32: =P32/(AA32-C34) -> 0.24074808 | V32: =SUM(V2:V31)+C35 -> 1 | X32: =AC32/AB32 -> 0.021898336 | Y32: =AC32/AA32 -> 0.025332927 | Z32: =((Z2*V2)+(Z3*V3)+(Z4*V4)+(Z5*V5)+(Z6*V6)+(Z7*V7)+(Z8*V8)+(Z9*V9)+(Z10*V10)+(Z11*V11)+(Z12*V12)+(Z13*V13)+(Z14*V14)+(Z15*V15)+(Z16*V16)+(Z17*V17)+(Z18*V18)+(Z19*V19)+(Z20*V20)+(Z21*V21)+(Z22*V22)+(Z23*V23)+(Z24*V24)+(Z25*V25)+(Z26*V26)+(Z27*V27)+(Z28*V28)+(Z29*V29)+(Z30*V30)+(Z31*V31))/V32 -> 0.045599895 | AA32: =sum(AA2:AA31)+C34 -> 34841.691 | AB32: =SUM(AB2:AB31)+C34 -> 40306.351 | AC32: =SUM(AC2:AC31)+SUM('Dividend Log'!AF17,'Dividend Log'!AF31,'Dividend Log'!AF45,'Dividend Log'!AF59,'Dividend Log'!AF73) -> 882.64201 | AD32: =SUM(AD2:AD31)+(SUM('Dividend Log'!AF17,'Dividend Log'!AF31,'Dividend Log'!AF45,'Dividend Log'!AF59,'Dividend Log'!AF73))/AC32 -> 1 | AE32: =SUM(AE2:AE31)+SUM('Dividend Log'!AG17,'Dividend Log'!AG31,'Dividend Log'!AG45,'Dividend Log'!AG59,'Dividend Log'!AG73)+SUM('Dividend Log'!AF17,'Dividend Log'!AF31,'Dividend Log'!AF45,'Dividend Log'!AF59,'Dividend Log'!AF73) -> 1006.99
B34: Cash | C34: =Rebalancing!C34 -> 7960.27
B35: Weighting | C35: =C34/AB32 -> 0.19749419
B37: Category | C37: Moderate / Growth portfolio | D37: Dividend / Income portfolio
B38: US Bonds | C38: 0.5 | D38: 1
B39: International Market | C39: 9.5 | D39: 4
B40: Value Stocks (Dividend) | C40: 20 | D40: 40
B41: Foundational (Total Market) | C41: 40 | D41: 15
B42: Growth | C42: 30 | D42: 40

Sheet Rebalancing
A1: Ticker | B1: Company Name | C1: # of Shares | D1: Avg. Cost Per Share | E1: Share Price | F1: Intrinsic Value | G1: InvT Score | H1: Security Type | I1: Sector | J1: Category | K1: Portfolio Allocation | L1: Market Value | M1: Dividend Yield | N1: Distance From Intrinsic Value | O1: Intrinsic Value Signal | P1: Distance From Avg. Cost | Q1: Avg. Cost Signal | R1: Shares Buying Power | S1: # Shares to buy | T1: Shares Cost | U1: New Market Value | V1: New Allocation | W1: New Avg. Cost Per Share
A2: =Positions!A2 -> GOOGL | B2: =IFERROR(__xludf.DUMMYFUNCTION("IF(ISBLANK(A2),"""", googlefinance(A2, ""name""))"),"Alphabet Inc Class A") -> Alphabet Inc Class A | C2: =Positions!D2 -> 9.025 | D2: =Positions!E2 -> 154.48 | E2: =IFERROR(__xludf.DUMMYFUNCTION("IF(ISBLANK(A2),"""", googlefinance(A2, ""price""))"),300.88) -> 300.88 | F2: =Positions!G2 -> 187.26 | G2: =Positions!H2 -> 8.58 | H2: Stocks | I2: Information Technology | J2: Growth | K2: =if(isblank(A2),"",L2/$L$32) -> 0.083949644 | L2: =IF(ISBLANK(A2),"",C2*E2) -> 2715.442 | M2: =Positions!X2 -> 0.0028 | N2: =iferror(IF(ISBLANK(F2),"",(E2-F2)/F2),"") -> 0.60674997 | O2: =IF(N2="", "", IF(N2<=-15%, "Strong Buy", IF(N2<0%, "Buy", IF(N2<=15%, "Expensive", "Overrated")))) -> Overrated | P2: =IF(ISBLANK(A2),"",(E2-D2)/D2) -> 0.94769549 | Q2: =IF(A2="", "", IF(P2<-15%, "Strong Buy", IF(P2<-5%, "Buy", IF(P2<5%, "Avg. Cost", IF(P2<=15%, "Overcost", "Hold"))))) -> Hold | R2: =iferror($C$35/E2,"") -> 26.456627 | S2: 0 | T2: =E2*S2 -> 0 | U2: =(C2+S2)*E2 -> 2715.442 | V2: =U2/$U$32 -> 0.083949644 | W2: =iferror(((C2*D2)+(S2*E2))/(C2+S2),"") -> 154.48
A3: =Positions!A3 -> MSFT | B3: =IFERROR(__xludf.DUMMYFUNCTION("IF(ISBLANK(A3),"""", googlefinance(A3, ""name""))"),"Microsoft Corp") -> Microsoft Corp | C3: =Positions!D3 -> 9.552 | D3: =Positions!E3 -> 393.4 | E3: =IFERROR(__xludf.DUMMYFUNCTION("IF(ISBLANK(A3),"""", googlefinance(A3, ""price""))"),410.68) -> 410.68 | F3: =Positions!G3 -> 334 | G3: =Positions!H3 -> 8.74 | H3: Stocks | I3: Information Technology | J3: Growth | K3: =if(isblank(A3),"",L3/$L$32) -> 0.12127637 | L3: =IF(ISBLANK(A3),"",C3*E3) -> 3922.8154 | M3: =Positions!X3 | N3: =iferror(IF(ISBLANK(F3),"",(E3-F3)/F3),"") -> 0.22958084 | O3: =IF(N3="", "", IF(N3<=-15%, "Strong Buy", IF(N3<0%, "Buy", IF(N3<=15%, "Expensive", "Overrated")))) -> Overrated | P3: =IF(ISBLANK(A3),"",(E3-D3)/D3) -> 0.043924759 | Q3: =IF(A3="", "", IF(P3<-15%, "Strong Buy", IF(P3<-5%, "Buy", IF(P3<5%, "Avg. Cost", IF(P3<=15%, "Overcost", "Hold"))))) -> Avg. Cost | R3: =iferror($C$35/E3,"") -> 19.383145 | S3: 0 | T3: =E3*S3 -> 0 | U3: =(C3+S3)*E3 -> 3922.8154 | V3: =U3/$U$32 -> 0.12127637 | W3: =iferror(((C3*D3)+(S3*E3))/(C3+S3),"") -> 393.4
A4: =Positions!A4 -> DIS | B4: =IFERROR(__xludf.DUMMYFUNCTION("IF(ISBLANK(A4),"""", googlefinance(A4, ""name""))"),"Walt Disney Co") -> Walt Disney Co | C4: =Positions!D4 -> 17.264 | D4: =Positions!E4 -> 93.48 | E4: =IFERROR(__xludf.DUMMYFUNCTION("IF(ISBLANK(A4),"""", googlefinance(A4, ""price""))"),102.41) -> 102.41 | F4: =Positions!G4 -> 89.15 | G4: =Positions!H4 -> 3.29 | H4: Stocks | I4: Communication Services | J4: Growth | K4: =if(isblank(A4),"",L4/$L$32) -> 0.054659055 | L4: =IF(ISBLANK(A4),"",C4*E4) -> 1768.0062 | M4: =Positions!X4 -> 0.0122 | N4: =iferror(IF(ISBLANK(F4),"",(E4-F4)/F4),"") -> 0.14873808 | O4: =IF(N4="", "", IF(N4<=-15%, "Strong Buy", IF(N4<0%, "Buy", IF(N4<=15%, "Expensive", "Overrated")))) -> Expensive | P4: =IF(ISBLANK(A4),"",(E4-D4)/D4) -> 0.095528455 | Q4: =IF(A4="", "", IF(P4<-15%, "Strong Buy", IF(P4<-5%, "Buy", IF(P4<5%, "Avg. Cost", IF(P4<=15%, "Overcost", "Hold"))))) -> Overcost | R4: =iferror($C$35/E4,"") -> 77.729421 | S4: 0 | T4: =E4*S4 -> 0 | U4: =(C4+S4)*E4 -> 1768.0062 | V4: =U4/$U$32 -> 0.054659055 | W4: =iferror(((C4*D4)+(S4*E4))/(C4+S4),"") -> 93.48
A5: =Positions!A5 -> TGT | B5: =IFERROR(__xludf.DUMMYFUNCTION("IF(ISBLANK(A5),"""", googlefinance(A5, ""name""))"),"Target Corp") -> Target Corp | C5: =Positions!D5 -> 31.358 | D5: =Positions!E5 -> 117.78 | E5: =IFERROR(__xludf.DUMMYFUNCTION("IF(ISBLANK(A5),"""", googlefinance(A5, ""price""))"),120.36) -> 120.36 | F5: =Positions!G5 -> 226.6 | G5: =Positions!H5 -> 6.59 | H5: Stocks | I5: Consumer Staples | J5: Growth | K5: =if(isblank(A5),"",L5/$L$32) -> 0.11668334 | L5: =IF(ISBLANK(A5),"",C5*E5) -> 3774.2489 | M5: =Positions!X5 -> 0.0377 | N5: =iferror(IF(ISBLANK(F5),"",(E5-F5)/F5),"") -> -0.46884378 | O5: =IF(N5="", "", IF(N5<=-15%, "Strong Buy", IF(N5<0%, "Buy", IF(N5<=15%, "Expensive", "Overrated")))) -> Strong Buy | P5: =IF(ISBLANK(A5),"",(E5-D5)/D5) -> 0.021905247 | Q5: =IF(A5="", "", IF(P5<-15%, "Strong Buy", IF(P5<-5%, "Buy", IF(P5<5%, "Avg. Cost", IF(P5<=15%, "Overcost", "Hold"))))) -> Avg. Cost | R5: =iferror($C$35/E5,"") -> 66.137172 | S5: 0 | T5: =E5*S5 -> 0 | U5: =(C5+S5)*E5 -> 3774.2489 | V5: =U5/$U$32 -> 0.11668334 | W5: =iferror(((C5*D5)+(S5*E5))/(C5+S5),"") -> 117.78
A6: =Positions!A6 -> SBUX | B6: =IFERROR(__xludf.DUMMYFUNCTION("IF(ISBLANK(A6),"""", googlefinance(A6, ""name""))"),"Starbucks Corp") -> Starbucks Corp | C6: =Positions!D6 -> 5.071 | D6: =Positions!E6 -> 81.62 | E6: =IFERROR(__xludf.DUMMYFUNCTION("IF(ISBLANK(A6),"""", googlefinance(A6, ""price""))"),98.69) -> 98.69 | F6: =Positions!G6 -> 89.57 | G6: =Positions!H6 -> 5.17 | H6: Stocks | I6: Consumer Discretionary | J6: Growth | K6: =if(isblank(A6),"",L6/$L$32) -> 0.015471951 | L6: =IF(ISBLANK(A6),"",C6*E6) -> 500.45699 | M6: =Positions!X6 -> 0.0249 | N6: =iferror(IF(ISBLANK(F6),"",(E6-F6)/F6),"") -> 0.10181981 | O6: =IF(N6="", "", IF(N6<=-15%, "Strong Buy", IF(N6<0%, "Buy", IF(N6<=15%, "Expensive", "Overrated")))) -> Expensive | P6: =IF(ISBLANK(A6),"",(E6-D6)/D6) -> 0.20913992 | Q6: =IF(A6="", "", IF(P6<-15%, "Strong Buy", IF(P6<-5%, "Buy", IF(P6<5%, "Avg. Cost", IF(P6<=15%, "Overcost", "Hold"))))) -> Hold | R6: =iferror($C$35/E6,"") -> 80.659337 | S6: 0 | T6: =E6*S6 -> 0 | U6: =(C6+S6)*E6 -> 500.45699 | V6: =U6/$U$32 -> 0.015471951 | W6: =iferror(((C6*D6)+(S6*E6))/(C6+S6),"") -> 81.62
A7: =Positions!A7 -> JPM | B7: =IFERROR(__xludf.DUMMYFUNCTION("IF(ISBLANK(A7),"""", googlefinance(A7, ""name""))"),"JPMorgan Chase & Co") -> JPMorgan Chase & Co | C7: =Positions!D7 -> 2.057 | D7: =Positions!E7 -> 199.07 | E7: =IFERROR(__xludf.DUMMYFUNCTION("IF(ISBLANK(A7),"""", googlefinance(A7, ""price""))"),293.55) -> 293.55 | F7: =Positions!G7 -> 287.74 | G7: =Positions!H7 -> 6.82 | H7: Stocks | I7: Financials | J7: Value Stocks | K7: =if(isblank(A7),"",L7/$L$32) -> 0.018667867 | L7: =IF(ISBLANK(A7),"",C7*E7) -> 603.83235 | M7: =Positions!X7 -> 0.0198 | N7: =iferror(IF(ISBLANK(F7),"",(E7-F7)/F7),"") -> 0.02019184 | O7: =IF(N7="", "", IF(N7<=-15%, "Strong Buy", IF(N7<0%, "Buy", IF(N7<=15%, "Expensive", "Overrated")))) -> Expensive | P7: =IF(ISBLANK(A7),"",(E7-D7)/D7) -> 0.47460692 | Q7: =IF(A7="", "", IF(P7<-15%, "Strong Buy", IF(P7<-5%, "Buy", IF(P7<5%, "Avg. Cost", IF(P7<=15%, "Overcost", "Hold"))))) -> Hold | R7: =iferror($C$35/E7,"") -> 27.117254 | S7: 0 | T7: =E7*S7 -> 0 | U7: =(C7+S7)*E7 -> 603.83235 | V7: =U7/$U$32 -> 0.018667867 | W7: =iferror(((C7*D7)+(S7*E7))/(C7+S7),"") -> 199.07
A8: =Positions!A8 -> KO | B8: =IFERROR(__xludf.DUMMYFUNCTION("IF(ISBLANK(A8),"""", googlefinance(A8, ""name""))"),"Coca-Cola Co") -> Coca-Cola Co | C8: =Positions!D8 -> 11.418 | D8: =Positions!E8 -> 63.85 | E8: =IFERROR(__xludf.DUMMYFUNCTION("IF(ISBLANK(A8),"""", googlefinance(A8, ""price""))"),77.03) -> 77.03 | F8: =Positions!G8 -> 40.7 | G8: =Positions!H8 -> 6 | H8: Stocks | I8: Consumer Staples | J8: Value Stocks | K8: =if(isblank(A8),"",L8/$L$32) -> 0.027191193 | L8: =IF(ISBLANK(A8),"",C8*E8) -> 879.52854 | M8: =Positions!X8 -> 0.0265 | N8: =iferror(IF(ISBLANK(F8),"",(E8-F8)/F8),"") -> 0.89262899 | O8: =IF(N8="", "", IF(N8<=-15%, "Strong Buy", IF(N8<0%, "Buy", IF(N8<=15%, "Expensive", "Overrated")))) -> Overrated | P8: =IF(ISBLANK(A8),"",(E8-D8)/D8) -> 0.2064213 | Q8: =IF(A8="", "", IF(P8<-15%, "Strong Buy", IF(P8<-5%, "Buy", IF(P8<5%, "Avg. Cost", IF(P8<=15%, "Overcost", "Hold"))))) -> Hold | R8: =iferror($C$35/E8,"") -> 103.33987 | S8: 0 | T8: =E8*S8 -> 0 | U8: =(C8+S8)*E8 -> 879.52854 | V8: =U8/$U$32 -> 0.027191193 | W8: =iferror(((C8*D8)+(S8*E8))/(C8+S8),"") -> 63.85
A9: =Positions!A9 -> O | B9: =IFERROR(__xludf.DUMMYFUNCTION("IF(ISBLANK(A9),"""", googlefinance(A9, ""name""))"),"Realty Income Corp") -> Realty Income Corp | C9: =Positions!D9 -> 31.001 | D9: =Positions!E9 -> 54.62 | E9: =IFERROR(__xludf.DUMMYFUNCTION("IF(ISBLANK(A9),"""", googlefinance(A9, ""price""))"),64.8) -> 64.8 | F9: =Positions!G9 -> 33.62 | G9: =Positions!H9 -> 3.92 | H9: Stocks | I9: Real Estate | J9: Value Stocks | K9: =if(isblank(A9),"",L9/$L$32) -> 0.062105353 | L9: =IF(ISBLANK(A9),"",C9*E9) -> 2008.8648 | M9: =Positions!X9 -> 0.054 | N9: =iferror(IF(ISBLANK(F9),"",(E9-F9)/F9),"") -> 0.92742415 | O9: =IF(N9="", "", IF(N9<=-15%, "Strong Buy", IF(N9<0%, "Buy", IF(N9<=15%, "Expensive", "Overrated")))) -> Overrated | P9: =IF(ISBLANK(A9),"",(E9-D9)/D9) -> 0.18637862 | Q9: =IF(A9="", "", IF(P9<-15%, "Strong Buy", IF(P9<-5%, "Buy", IF(P9<5%, "Avg. Cost", IF(P9<=15%, "Overcost", "Hold"))))) -> Hold | R9: =iferror($C$35/E9,"") -> 122.84367 | S9: 0 | T9: =E9*S9 -> 0 | U9: =(C9+S9)*E9 -> 2008.8648 | V9: =U9/$U$32 -> 0.062105353 | W9: =iferror(((C9*D9)+(S9*E9))/(C9+S9),"") -> 54.62
A10: =Positions!A10 -> VICI | B10: =IFERROR(__xludf.DUMMYFUNCTION("IF(ISBLANK(A10),"""", googlefinance(A10, ""name""))"),"VICI Properties Inc") -> VICI Properties Inc | C10: =Positions!D10 -> 15.874 | D10: =Positions!E10 -> 29.95 | E10: =IFERROR(__xludf.DUMMYFUNCTION("IF(ISBLANK(A10),"""", googlefinance(A10, ""price""))"),29.69) -> 29.69 | F10: =Positions!G10 -> 86.13 | G10: =Positions!H10 -> 5.78 | H10: Stocks | I10: Real Estate | J10: Value Stocks | K10: =if(isblank(A10),"",L10/$L$32) -> 0.014570515 | L10: =IF(ISBLANK(A10),"",C10*E10) -> 471.29906 | M10: =Positions!X10 -> 0.0594 | N10: =iferror(IF(ISBLANK(F10),"",(E10-F10)/F10),"") -> -0.65528852 | O10: =IF(N10="", "", IF(N10<=-15%, "Strong Buy", IF(N10<0%, "Buy", IF(N10<=15%, "Expensive", "Overrated")))) -> Strong Buy | P10: =IF(ISBLANK(A10),"",(E10-D10)/D10) -> -0.0086811352 | Q10: =IF(A10="", "", IF(P10<-15%, "Strong Buy", IF(P10<-5%, "Buy", IF(P10<5%, "Avg. Cost", IF(P10<=15%, "Overcost", "Hold"))))) -> Avg. Cost | R10: =iferror($C$35/E10,"") -> 268.11283 | S10: 0 | T10: =E10*S10 -> 0 | U10: =(C10+S10)*E10 -> 471.29906 | V10: =U10/$U$32 -> 0.014570515 | W10: =iferror(((C10*D10)+(S10*E10))/(C10+S10),"") -> 29.95
A11: =Positions!A11 -> UNH | B11: =IFERROR(__xludf.DUMMYFUNCTION("IF(ISBLANK(A11),"""", googlefinance(A11, ""name""))"),"UnitedHealth Group Inc") -> UnitedHealth Group Inc | C11: =Positions!D11 -> 5.066 | D11: =Positions!E11 -> 261.98 | E11: =IFERROR(__xludf.DUMMYFUNCTION("IF(ISBLANK(A11),"""", googlefinance(A11, ""price""))"),288.77) -> 288.77 | F11: =Positions!G11 -> 362.68 | G11: =Positions!H11 -> 5 | H11: Stocks | I11: Health Care | J11: Value Stocks | K11: =if(isblank(A11),"",L11/$L$32) -> 0.045226771 | L11: =IF(ISBLANK(A11),"",C11*E11) -> 1462.9088 | M11: =Positions!X11 -> 0.0302 | N11: =iferror(IF(ISBLANK(F11),"",(E11-F11)/F11),"") -> -0.20378846 | O11: =IF(N11="", "", IF(N11<=-15%, "Strong Buy", IF(N11<0%, "Buy", IF(N11<=15%, "Expensive", "Overrated")))) -> Strong Buy | P11: =IF(ISBLANK(A11),"",(E11-D11)/D11) -> 0.10225971 | Q11: =IF(A11="", "", IF(P11<-15%, "Strong Buy", IF(P11<-5%, "Buy", IF(P11<5%, "Avg. Cost", IF(P11<=15%, "Overcost", "Hold"))))) -> Overcost | R11: =iferror($C$35/E11,"") -> 27.566125 | S11: 0 | T11: =E11*S11 -> 0 | U11: =(C11+S11)*E11 -> 1462.9088 | V11: =U11/$U$32 -> 0.045226771 | W11: =iferror(((C11*D11)+(S11*E11))/(C11+S11),"") -> 261.98
A12: =Positions!A12 -> VGT | B12: =IFERROR(__xludf.DUMMYFUNCTION("IF(ISBLANK(A12),"""", googlefinance(A12, ""name""))"),"Vanguard Information Technology Index Fund ETF") -> Vanguard Information Technology Index Fund ETF | C12: =Positions!D12 -> 3.015 | D12: =Positions!E12 -> 507.59 | E12: =IFERROR(__xludf.DUMMYFUNCTION("IF(ISBLANK(A12),"""", googlefinance(A12, ""price""))"),733.27) -> 733.27 | F12: =Positions!G12 -> Not Found | G12: =Positions!H12 -> Not Found | H12: ETFs | I12: ETF | J12: Growth | K12: =if(isblank(A12),"",L12/$L$32) -> 0.06834859 | L12: =IF(ISBLANK(A12),"",C12*E12) -> 2210.809 | M12: =Positions!X12 -> 0.0042 | N12: =iferror(IF(ISBLANK(F12),"",(E12-F12)/F12),"") | O12: =IF(N12="", "", IF(N12<=-15%, "Strong Buy", IF(N12<0%, "Buy", IF(N12<=15%, "Expensive", "Overrated")))) | P12: =IF(ISBLANK(A12),"",(E12-D12)/D12) -> 0.44461081 | Q12: =IF(A12="", "", IF(P12<-15%, "Strong Buy", IF(P12<-5%, "Buy", IF(P12<5%, "Avg. Cost", IF(P12<=15%, "Overcost", "Hold"))))) -> Hold | R12: =iferror($C$35/E12,"") -> 10.855851 | S12: 0 | T12: =E12*S12 -> 0 | U12: =(C12+S12)*E12 -> 2210.809 | V12: =U12/$U$32 -> 0.06834859 | W12: =iferror(((C12*D12)+(S12*E12))/(C12+S12),"") -> 507.59
A13: =Positions!A13 -> VOO | B13: =IFERROR(__xludf.DUMMYFUNCTION("IF(ISBLANK(A13),"""", googlefinance(A13, ""name""))"),"Vanguard S&P 500 ETF") -> Vanguard S&P 500 ETF | C13: =Positions!D13 -> 3.064 | D13: =Positions!E13 -> 480.16 | E13: =IFERROR(__xludf.DUMMYFUNCTION("IF(ISBLANK(A13),"""", googlefinance(A13, ""price""))"),626.81) -> 626.81 | F13: =Positions!G13 -> Not Found | G13: =Positions!H13 -> Not Found | H13: ETFs | I13: ETF | J13: Foundational | K13: =if(isblank(A13),"",L13/$L$32) -> 0.059374915 | L13: =IF(ISBLANK(A13),"",C13*E13) -> 1920.5458 | M13: =Positions!X13 -> 0.0113 | N13: =iferror(IF(ISBLANK(F13),"",(E13-F13)/F13),"") | O13: =IF(N13="", "", IF(N13<=-15%, "Strong Buy", IF(N13<0%, "Buy", IF(N13<=15%, "Expensive", "Overrated")))) | P13: =IF(ISBLANK(A13),"",(E13-D13)/D13) -> 0.30541903 | Q13: =IF(A13="", "", IF(P13<-15%, "Strong Buy", IF(P13<-5%, "Buy", IF(P13<5%, "Avg. Cost", IF(P13<=15%, "Overcost", "Hold"))))) -> Hold | R13: =iferror($C$35/E13,"") -> 12.699654 | S13: 0 | T13: =E13*S13 -> 0 | U13: =(C13+S13)*E13 -> 1920.5458 | V13: =U13/$U$32 -> 0.059374915 | W13: =iferror(((C13*D13)+(S13*E13))/(C13+S13),"") -> 480.16
A14: =Positions!A14 -> VTI | B14: =IFERROR(__xludf.DUMMYFUNCTION("IF(ISBLANK(A14),"""", googlefinance(A14, ""name""))"),"Vanguard Total Stock Market Index Fund ETF") -> Vanguard Total Stock Market Index Fund ETF | C14: =Positions!D14 -> 8.147 | D14: =Positions!E14 -> 260.86 | E14: =IFERROR(__xludf.DUMMYFUNCTION("IF(ISBLANK(A14),"""", googlefinance(A14, ""price""))"),336.0) -> 336 | F14: =Positions!G14 -> Not Found | G14: =Positions!H14 -> Not Found | H14: ETFs | I14: ETF | J14: Foundational | K14: =if(isblank(A14),"",L14/$L$32) -> 0.084628242 | L14: =IF(ISBLANK(A14),"",C14*E14) -> 2737.392 | M14: =Positions!X14 -> 0.0112 | N14: =iferror(IF(ISBLANK(F14),"",(E14-F14)/F14),"") | O14: =IF(N14="", "", IF(N14<=-15%, "Strong Buy", IF(N14<0%, "Buy", IF(N14<=15%, "Expensive", "Overrated")))) | P14: =IF(ISBLANK(A14),"",(E14-D14)/D14) -> 0.28804723 | Q14: =IF(A14="", "", IF(P14<-15%, "Strong Buy", IF(P14<-5%, "Buy", IF(P14<5%, "Avg. Cost", IF(P14<=15%, "Overcost", "Hold"))))) -> Hold | R14: =iferror($C$35/E14,"") -> 23.69128 | S14: 0 | T14: =E14*S14 -> 0 | U14: =(C14+S14)*E14 -> 2737.392 | V14: =U14/$U$32 -> 0.084628242 | W14: =iferror(((C14*D14)+(S14*E14))/(C14+S14),"") -> 260.86
A15: =Positions!A15 -> SCHD | B15: =IFERROR(__xludf.DUMMYFUNCTION("IF(ISBLANK(A15),"""", googlefinance(A15, ""name""))"),"Schwab US Dividend Equity ETF") -> Schwab US Dividend Equity ETF | C15: =Positions!D15 -> 186.205 | D15: =Positions!E15 -> 26.98 | E15: =IFERROR(__xludf.DUMMYFUNCTION("IF(ISBLANK(A15),"""", googlefinance(A15, ""price""))"),31.26) -> 31.26 | F15: =Positions!G15 -> Not Found | G15: =Positions!H15 -> Not Found | H15: ETFs | I15: ETF | J15: Value Stocks | K15: =if(isblank(A15),"",L15/$L$32) -> 0.17995281 | L15: =IF(ISBLANK(A15),"",C15*E15) -> 5820.7683 | M15: =Positions!X15 -> 0.0335 | N15: =iferror(IF(ISBLANK(F15),"",(E15-F15)/F15),"") | O15: =IF(N15="", "", IF(N15<=-15%, "Strong Buy", IF(N15<0%, "Buy", IF(N15<=15%, "Expensive", "Overrated")))) | P15: =IF(ISBLANK(A15),"",(E15-D15)/D15) -> 0.15863603 | Q15: =IF(A15="", "", IF(P15<-15%, "Strong Buy", IF(P15<-5%, "Buy", IF(P15<5%, "Avg. Cost", IF(P15<=15%, "Overcost", "Hold"))))) -> Hold | R15: =iferror($C$35/E15,"") -> 254.64715 | S15: 0 | T15: =E15*S15 -> 0 | U15: =(C15+S15)*E15 -> 5820.7683 | V15: =U15/$U$32 -> 0.17995281 | W15: =iferror(((C15*D15)+(S15*E15))/(C15+S15),"") -> 26.98
A16: =Positions!A16 -> VIG | B16: =IFERROR(__xludf.DUMMYFUNCTION("IF(ISBLANK(A16),"""", googlefinance(A16, ""name""))"),"Vanguard Dividend Appreciation Index Fund ETF") -> Vanguard Dividend Appreciation Index Fund ETF | C16: =Positions!D16 -> 1.03 | D16: =Positions!E16 -> 179.84 | E16: =IFERROR(__xludf.DUMMYFUNCTION("IF(ISBLANK(A16),"""", googlefinance(A16, ""price""))"),223.45) -> 223.45 | F16: =Positions!G16 -> Not Found | G16: =Positions!H16 -> Not Found | H16: ETFs | I16: ETF | J16: Value Stocks | K16: =if(isblank(A16),"",L16/$L$32) -> 0.0071153442 | L16: =IF(ISBLANK(A16),"",C16*E16) -> 230.1535 | M16: =Positions!X16 -> 0.0159 | N16: =iferror(IF(ISBLANK(F16),"",(E16-F16)/F16),"") | O16: =IF(N16="", "", IF(N16<=-15%, "Strong Buy", IF(N16<0%, "Buy", IF(N16<=15%, "Expensive", "Overrated")))) | P16: =IF(ISBLANK(A16),"",(E16-D16)/D16) -> 0.24249333 | Q16: =IF(A16="", "", IF(P16<-15%, "Strong Buy", IF(P16<-5%, "Buy", IF(P16<5%, "Avg. Cost", IF(P16<=15%, "Overcost", "Hold"))))) -> Hold | R16: =iferror($C$35/E16,"") -> 35.62439 | S16: 0 | T16: =E16*S16 -> 0 | U16: =(C16+S16)*E16 -> 230.1535 | V16: =U16/$U$32 -> 0.0071153442 | W16: =iferror(((C16*D16)+(S16*E16))/(C16+S16),"") -> 179.84
A17: =Positions!A17 -> VXUS | B17: =IFERROR(__xludf.DUMMYFUNCTION("IF(ISBLANK(A17),"""", googlefinance(A17, ""name""))"),"Vanguard Total International Stock Index Fund ETF") -> Vanguard Total International Stock Index Fund ETF | C17: =Positions!D17 -> 14.765 | D17: =Positions!E17 -> 59.99 | E17: =IFERROR(__xludf.DUMMYFUNCTION("IF(ISBLANK(A17),"""", googlefinance(A17, ""price""))"),78.72) -> 78.72 | F17: =Positions!G17 -> Not Found | G17: =Positions!H17 -> Not Found | H17: ETFs | I17: ETF | J17: International Market | K17: =if(isblank(A17),"",L17/$L$32) -> 0.03593328 | L17: =IF(ISBLANK(A17),"",C17*E17) -> 1162.3008 | M17: =Positions!X17 -> 0.0305 | N17: =iferror(IF(ISBLANK(F17),"",(E17-F17)/F17),"") | O17: =IF(N17="", "", IF(N17<=-15%, "Strong Buy", IF(N17<0%, "Buy", IF(N17<=15%, "Expensive", "Overrated")))) | P17: =IF(ISBLANK(A17),"",(E17-D17)/D17) -> 0.3122187 | Q17: =IF(A17="", "", IF(P17<-15%, "Strong Buy", IF(P17<-5%, "Buy", IF(P17<5%, "Avg. Cost", IF(P17<=15%, "Overcost", "Hold"))))) -> Hold | R17: =iferror($C$35/E17,"") -> 101.12132 | S17: 0 | T17: =E17*S17 -> 0 | U17: =(C17+S17)*E17 -> 1162.3008 | V17: =U17/$U$32 -> 0.03593328 | W17: =iferror(((C17*D17)+(S17*E17))/(C17+S17),"") -> 59.99
A18: =Positions!A18 -> BND | B18: =IFERROR(__xludf.DUMMYFUNCTION("IF(ISBLANK(A18),"""", googlefinance(A18, ""name""))"),"Vanguard Total Bond Market Index Fund ETF") -> Vanguard Total Bond Market Index Fund ETF | C18: =Positions!D18 -> 2.108 | D18: =Positions!E18 -> 72.28 | E18: =IFERROR(__xludf.DUMMYFUNCTION("IF(ISBLANK(A18),"""", googlefinance(A18, ""price""))"),74.34) -> 74.34 | F18: =Positions!G18 -> Not Found | G18: =Positions!H18 -> Not Found | H18: ETFs | I18: Bonds | J18: US Bonds | K18: =if(isblank(A18),"",L18/$L$32) -> 0.0048447513 | L18: =IF(ISBLANK(A18),"",C18*E18) -> 156.70872 | M18: =Positions!X18 -> 0.0387 | N18: =iferror(IF(ISBLANK(F18),"",(E18-F18)/F18),"") | O18: =IF(N18="", "", IF(N18<=-15%, "Strong Buy", IF(N18<0%, "Buy", IF(N18<=15%, "Expensive", "Overrated")))) | P18: =IF(ISBLANK(A18),"",(E18-D18)/D18) -> 0.028500277 | Q18: =IF(A18="", "", IF(P18<-15%, "Strong Buy", IF(P18<-5%, "Buy", IF(P18<5%, "Avg. Cost", IF(P18<=15%, "Overcost", "Hold"))))) -> Avg. Cost | R18: =iferror($C$35/E18,"") -> 107.07923 | S18: 0 | T18: =E18*S18 -> 0 | U18: =(C18+S18)*E18 -> 156.70872 | V18: =U18/$U$32 -> 0.0048447513 | W18: =iferror(((C18*D18)+(S18*E18))/(C18+S18),"") -> 72.28
A19: =Positions!A19 | B19: =IFERROR(__xludf.DUMMYFUNCTION("IF(ISBLANK(A19),"""", googlefinance(A19, ""name""))"),"") | C19: =Positions!D19 | D19: =Positions!E19 | E19: =IFERROR(__xludf.DUMMYFUNCTION("IF(ISBLANK(A19),"""", googlefinance(A19, ""price""))"),"") | F19: =Positions!G19 | G19: =Positions!H19 | H19: (Select Security) | I19: (Select) | J19: (Select) | K19: =if(isblank(A19),"",L19/$L$32) | L19: =IF(ISBLANK(A19),"",C19*E19) | M19: =Positions!X19 | N19: =iferror(IF(ISBLANK(F19),"",(E19-F19)/F19),"") | O19: =IF(N19="", "", IF(N19<=-15%, "Strong Buy", IF(N19<0%, "Buy", IF(N19<=15%, "Expensive", "Overrated")))) | P19: =IF(ISBLANK(A19),"",(E19-D19)/D19) | Q19: =IF(A19="", "", IF(P19<-15%, "Strong Buy", IF(P19<-5%, "Buy", IF(P19<5%, "Avg. Cost", IF(P19<=15%, "Overcost", "Hold"))))) | R19: =iferror($C$35/E19,"") | S19: 0 | T19: =E19*S19 -> 0 | U19: =(C19+S19)*E19 -> 0 | V19: =U19/$U$32 -> 0 | W19: =iferror(((C19*D19)+(S19*E19))/(C19+S19),"")
A20: =Positions!A20 | B20: =IFERROR(__xludf.DUMMYFUNCTION("IF(ISBLANK(A20),"""", googlefinance(A20, ""name""))"),"") | C20: =Positions!D20 | D20: =Positions!E20 | E20: =IFERROR(__xludf.DUMMYFUNCTION("IF(ISBLANK(A20),"""", googlefinance(A20, ""price""))"),"") | F20: =Positions!G20 | G20: =Positions!H20 | H20: (Select Security) | I20: (Select) | J20: (Select) | K20: =if(isblank(A20),"",L20/$L$32) | L20: =IF(ISBLANK(A20),"",C20*E20) | M20: =Positions!X20 | N20: =iferror(IF(ISBLANK(F20),"",(E20-F20)/F20),"") | O20: =IF(N20="", "", IF(N20<=-15%, "Strong Buy", IF(N20<0%, "Buy", IF(N20<=15%, "Expensive", "Overrated")))) | P20: =IF(ISBLANK(A20),"",(E20-D20)/D20) | Q20: =IF(A20="", "", IF(P20<-15%, "Strong Buy", IF(P20<-5%, "Buy", IF(P20<5%, "Avg. Cost", IF(P20<=15%, "Overcost", "Hold"))))) | R20: =iferror($C$35/E20,"") | S20: 0 | T20: =E20*S20 -> 0 | U20: =(C20+S20)*E20 -> 0 | V20: =U20/$U$32 -> 0 | W20: =iferror(((C20*D20)+(S20*E20))/(C20+S20),"")
A21: =Positions!A21 | B21: =IFERROR(__xludf.DUMMYFUNCTION("IF(ISBLANK(A21),"""", googlefinance(A21, ""name""))"),"") | C21: =Positions!D21 | D21: =Positions!E21 | E21: =IFERROR(__xludf.DUMMYFUNCTION("IF(ISBLANK(A21),"""", googlefinance(A21, ""price""))"),"") | F21: =Positions!G21 | G21: =Positions!H21 | H21: (Select Security) | I21: (Select) | J21: (Select) | K21: =if(isblank(A21),"",L21/$L$32) | L21: =IF(ISBLANK(A21),"",C21*E21) | M21: =Positions!X21 | N21: =iferror(IF(ISBLANK(F21),"",(E21-F21)/F21),"") | O21: =IF(N21="", "", IF(N21<=-15%, "Strong Buy", IF(N21<0%, "Buy", IF(N21<=15%, "Expensive", "Overrated")))) | P21: =IF(ISBLANK(A21),"",(E21-D21)/D21) | Q21: =IF(A21="", "", IF(P21<-15%, "Strong Buy", IF(P21<-5%, "Buy", IF(P21<5%, "Avg. Cost", IF(P21<=15%, "Overcost", "Hold"))))) | R21: =iferror($C$35/E21,"") | S21: 0 | T21: =E21*S21 -> 0 | U21: =(C21+S21)*E21 -> 0 | V21: =U21/$U$32 -> 0 | W21: =iferror(((C21*D21)+(S21*E21))/(C21+S21),"")
A22: =Positions!A22 | B22: =IFERROR(__xludf.DUMMYFUNCTION("IF(ISBLANK(A22),"""", googlefinance(A22, ""name""))"),"") | C22: =Positions!D22 | D22: =Positions!E22 | E22: =IFERROR(__xludf.DUMMYFUNCTION("IF(ISBLANK(A22),"""", googlefinance(A22, ""price""))"),"") | F22: =Positions!G22 | G22: =Positions!H22 | H22: (Select Security) | I22: (Select) | J22: (Select) | K22: =if(isblank(A22),"",L22/$L$32) | L22: =IF(ISBLANK(A22),"",C22*E22) | M22: =Positions!X22 | N22: =iferror(IF(ISBLANK(F22),"",(E22-F22)/F22),"") | O22: =IF(N22="", "", IF(N22<=-15%, "Strong Buy", IF(N22<0%, "Buy", IF(N22<=15%, "Expensive", "Overrated")))) | P22: =IF(ISBLANK(A22),"",(E22-D22)/D22) | Q22: =IF(A22="", "", IF(P22<-15%, "Strong Buy", IF(P22<-5%, "Buy", IF(P22<5%, "Avg. Cost", IF(P22<=15%, "Overcost", "Hold"))))) | R22: =iferror($C$35/E22,"") | S22: 0 | T22: =E22*S22 -> 0 | U22: =(C22+S22)*E22 -> 0 | V22: =U22/$U$32 -> 0 | W22: =iferror(((C22*D22)+(S22*E22))/(C22+S22),"")
A23: =Positions!A23 | B23: =IFERROR(__xludf.DUMMYFUNCTION("IF(ISBLANK(A23),"""", googlefinance(A23, ""name""))"),"") | C23: =Positions!D23 | D23: =Positions!E23 | E23: =IFERROR(__xludf.DUMMYFUNCTION("IF(ISBLANK(A23),"""", googlefinance(A23, ""price""))"),"") | F23: =Positions!G23 | G23: =Positions!H23 | H23: (Select Security) | I23: (Select) | J23: (Select) | K23: =if(isblank(A23),"",L23/$L$32) | L23: =IF(ISBLANK(A23),"",C23*E23) | M23: =Positions!X23 | N23: =iferror(IF(ISBLANK(F23),"",(E23-F23)/F23),"") | O23: =IF(N23="", "", IF(N23<=-15%, "Strong Buy", IF(N23<0%, "Buy", IF(N23<=15%, "Expensive", "Overrated")))) | P23: =IF(ISBLANK(A23),"",(E23-D23)/D23) | Q23: =IF(A23="", "", IF(P23<-15%, "Strong Buy", IF(P23<-5%, "Buy", IF(P23<5%, "Avg. Cost", IF(P23<=15%, "Overcost", "Hold"))))) | R23: =iferror($C$35/E23,"") | S23: 0 | T23: =E23*S23 -> 0 | U23: =(C23+S23)*E23 -> 0 | V23: =U23/$U$32 -> 0 | W23: =iferror(((C23*D23)+(S23*E23))/(C23+S23),"")
A24: =Positions!A24 | B24: =IFERROR(__xludf.DUMMYFUNCTION("IF(ISBLANK(A24),"""", googlefinance(A24, ""name""))"),"") | C24: =Positions!D24 | D24: =Positions!E24 | E24: =IFERROR(__xludf.DUMMYFUNCTION("IF(ISBLANK(A24),"""", googlefinance(A24, ""price""))"),"") | F24: =Positions!G24 | G24: =Positions!H24 | H24: (Select Security) | I24: (Select) | J24: (Select) | K24: =if(isblank(A24),"",L24/$L$32) | L24: =IF(ISBLANK(A24),"",C24*E24) | M24: =Positions!X24 | N24: =iferror(IF(ISBLANK(F24),"",(E24-F24)/F24),"") | O24: =IF(N24="", "", IF(N24<=-15%, "Strong Buy", IF(N24<0%, "Buy", IF(N24<=15%, "Expensive", "Overrated")))) | P24: =IF(ISBLANK(A24),"",(E24-D24)/D24) | Q24: =IF(A24="", "", IF(P24<-15%, "Strong Buy", IF(P24<-5%, "Buy", IF(P24<5%, "Avg. Cost", IF(P24<=15%, "Overcost", "Hold"))))) | R24: =iferror($C$35/E24,"") | S24: 0 | T24: =E24*S24 -> 0 | U24: =(C24+S24)*E24 -> 0 | V24: =U24/$U$32 -> 0 | W24: =iferror(((C24*D24)+(S24*E24))/(C24+S24),"")
A25: =Positions!A25 | B25: =IFERROR(__xludf.DUMMYFUNCTION("IF(ISBLANK(A25),"""", googlefinance(A25, ""name""))"),"") | C25: =Positions!D25 | D25: =Positions!E25 | E25: =IFERROR(__xludf.DUMMYFUNCTION("IF(ISBLANK(A25),"""", googlefinance(A25, ""price""))"),"") | F25: =Positions!G25 | G25: =Positions!H25 | H25: (Select Security) | I25: (Select) | J25: (Select) | K25: =if(isblank(A25),"",L25/$L$32) | L25: =IF(ISBLANK(A25),"",C25*E25) | M25: =Positions!X25 | N25: =iferror(IF(ISBLANK(F25),"",(E25-F25)/F25),"") | O25: =IF(N25="", "", IF(N25<=-15%, "Strong Buy", IF(N25<0%, "Buy", IF(N25<=15%, "Expensive", "Overrated")))) | P25: =IF(ISBLANK(A25),"",(E25-D25)/D25) | Q25: =IF(A25="", "", IF(P25<-15%, "Strong Buy", IF(P25<-5%, "Buy", IF(P25<5%, "Avg. Cost", IF(P25<=15%, "Overcost", "Hold"))))) | R25: =iferror($C$35/E25,"") | S25: 0 | T25: =E25*S25 -> 0 | U25: =(C25+S25)*E25 -> 0 | V25: =U25/$U$32 -> 0 | W25: =iferror(((C25*D25)+(S25*E25))/(C25+S25),"")
A26: =Positions!A26 | B26: =IFERROR(__xludf.DUMMYFUNCTION("IF(ISBLANK(A26),"""", googlefinance(A26, ""name""))"),"") | C26: =Positions!D26 | D26: =Positions!E26 | E26: =IFERROR(__xludf.DUMMYFUNCTION("IF(ISBLANK(A26),"""", googlefinance(A26, ""price""))"),"") | F26: =Positions!G26 | G26: =Positions!H26 | H26: (Select Security) | I26: (Select) | J26: (Select) | K26: =if(isblank(A26),"",L26/$L$32) | L26: =IF(ISBLANK(A26),"",C26*E26) | M26: =Positions!X26 | N26: =iferror(IF(ISBLANK(F26),"",(E26-F26)/F26),"") | O26: =IF(N26="", "", IF(N26<=-15%, "Strong Buy", IF(N26<0%, "Buy", IF(N26<=15%, "Expensive", "Overrated")))) | P26: =IF(ISBLANK(A26),"",(E26-D26)/D26) | Q26: =IF(A26="", "", IF(P26<-15%, "Strong Buy", IF(P26<-5%, "Buy", IF(P26<5%, "Avg. Cost", IF(P26<=15%, "Overcost", "Hold"))))) | R26: =iferror($C$35/E26,"") | S26: 0 | T26: =E26*S26 -> 0 | U26: =(C26+S26)*E26 -> 0 | V26: =U26/$U$32 -> 0 | W26: =iferror(((C26*D26)+(S26*E26))/(C26+S26),"")
A27: =Positions!A27 | B27: =IFERROR(__xludf.DUMMYFUNCTION("IF(ISBLANK(A27),"""", googlefinance(A27, ""name""))"),"") | C27: =Positions!D27 | D27: =Positions!E27 | E27: =IFERROR(__xludf.DUMMYFUNCTION("IF(ISBLANK(A27),"""", googlefinance(A27, ""price""))"),"") | F27: =Positions!G27 | G27: =Positions!H27 | H27: (Select Security) | I27: (Select) | J27: (Select) | K27: =if(isblank(A27),"",L27/$L$32) | L27: =IF(ISBLANK(A27),"",C27*E27) | M27: =Positions!X27 | N27: =iferror(IF(ISBLANK(F27),"",(E27-F27)/F27),"") | O27: =IF(N27="", "", IF(N27<=-15%, "Strong Buy", IF(N27<0%, "Buy", IF(N27<=15%, "Expensive", "Overrated")))) | P27: =IF(ISBLANK(A27),"",(E27-D27)/D27) | Q27: =IF(A27="", "", IF(P27<-15%, "Strong Buy", IF(P27<-5%, "Buy", IF(P27<5%, "Avg. Cost", IF(P27<=15%, "Overcost", "Hold"))))) | R27: =iferror($C$35/E27,"") | S27: 0 | T27: =E27*S27 -> 0 | U27: =(C27+S27)*E27 -> 0 | V27: =U27/$U$32 -> 0 | W27: =iferror(((C27*D27)+(S27*E27))/(C27+S27),"")
A28: =Positions!A28 | B28: =IFERROR(__xludf.DUMMYFUNCTION("IF(ISBLANK(A28),"""", googlefinance(A28, ""name""))"),"") | C28: =Positions!D28 | D28: =Positions!E28 | E28: =IFERROR(__xludf.DUMMYFUNCTION("IF(ISBLANK(A28),"""", googlefinance(A28, ""price""))"),"") | F28: =Positions!G28 | G28: =Positions!H28 | H28: (Select Security) | I28: (Select) | J28: (Select) | K28: =if(isblank(A28),"",L28/$L$32) | L28: =IF(ISBLANK(A28),"",C28*E28) | M28: =Positions!X28 | N28: =iferror(IF(ISBLANK(F28),"",(E28-F28)/F28),"") | O28: =IF(N28="", "", IF(N28<=-15%, "Strong Buy", IF(N28<0%, "Buy", IF(N28<=15%, "Expensive", "Overrated")))) | P28: =IF(ISBLANK(A28),"",(E28-D28)/D28) | Q28: =IF(A28="", "", IF(P28<-15%, "Strong Buy", IF(P28<-5%, "Buy", IF(P28<5%, "Avg. Cost", IF(P28<=15%, "Overcost", "Hold"))))) | R28: =iferror($C$35/E28,"") | S28: 0 | T28: =E28*S28 -> 0 | U28: =(C28+S28)*E28 -> 0 | V28: =U28/$U$32 -> 0 | W28: =iferror(((C28*D28)+(S28*E28))/(C28+S28),"")
A29: =Positions!A29 | B29: =IFERROR(__xludf.DUMMYFUNCTION("IF(ISBLANK(A29),"""", googlefinance(A29, ""name""))"),"") | C29: =Positions!D29 | D29: =Positions!E29 | E29: =IFERROR(__xludf.DUMMYFUNCTION("IF(ISBLANK(A29),"""", googlefinance(A29, ""price""))"),"") | F29: =Positions!G29 | G29: =Positions!H29 | H29: (Select Security) | I29: (Select) | J29: (Select) | K29: =if(isblank(A29),"",L29/$L$32) | L29: =IF(ISBLANK(A29),"",C29*E29) | M29: =Positions!X29 | N29: =iferror(IF(ISBLANK(F29),"",(E29-F29)/F29),"") | O29: =IF(N29="", "", IF(N29<=-15%, "Strong Buy", IF(N29<0%, "Buy", IF(N29<=15%, "Expensive", "Overrated")))) | P29: =IF(ISBLANK(A29),"",(E29-D29)/D29) | Q29: =IF(A29="", "", IF(P29<-15%, "Strong Buy", IF(P29<-5%, "Buy", IF(P29<5%, "Avg. Cost", IF(P29<=15%, "Overcost", "Hold"))))) | R29: =iferror($C$35/E29,"") | S29: 0 | T29: =E29*S29 -> 0 | U29: =(C29+S29)*E29 -> 0 | V29: =U29/$U$32 -> 0 | W29: =iferror(((C29*D29)+(S29*E29))/(C29+S29),"")
A30: =Positions!A30 | B30: =IFERROR(__xludf.DUMMYFUNCTION("IF(ISBLANK(A30),"""", googlefinance(A30, ""name""))"),"") | C30: =Positions!D30 | D30: =Positions!E30 | E30: =IFERROR(__xludf.DUMMYFUNCTION("IF(ISBLANK(A30),"""", googlefinance(A30, ""price""))"),"") | F30: =Positions!G30 | G30: =Positions!H30 | H30: (Select Security) | I30: (Select) | J30: (Select) | K30: =if(isblank(A30),"",L30/$L$32) | L30: =IF(ISBLANK(A30),"",C30*E30) | M30: =Positions!X30 | N30: =iferror(IF(ISBLANK(F30),"",(E30-F30)/F30),"") | O30: =IF(N30="", "", IF(N30<=-15%, "Strong Buy", IF(N30<0%, "Buy", IF(N30<=15%, "Expensive", "Overrated")))) | P30: =IF(ISBLANK(A30),"",(E30-D30)/D30) | Q30: =IF(A30="", "", IF(P30<-15%, "Strong Buy", IF(P30<-5%, "Buy", IF(P30<5%, "Avg. Cost", IF(P30<=15%, "Overcost", "Hold"))))) | R30: =iferror($C$35/E30,"") | S30: 0 | T30: =E30*S30 -> 0 | U30: =(C30+S30)*E30 -> 0 | V30: =U30/$U$32 -> 0 | W30: =iferror(((C30*D30)+(S30*E30))/(C30+S30),"")
A31: =Positions!A31 | B31: =IFERROR(__xludf.DUMMYFUNCTION("IF(ISBLANK(A31),"""", googlefinance(A31, ""name""))"),"") | C31: =Positions!D31 | D31: =Positions!E31 | E31: =IFERROR(__xludf.DUMMYFUNCTION("IF(ISBLANK(A31),"""", googlefinance(A31, ""price""))"),"") | F31: =Positions!G31 | G31: =Positions!H31 | H31: (Select Security) | I31: (Select) | J31: (Select) | K31: =if(isblank(A31),"",L31/$L$32) | L31: =IF(ISBLANK(A31),"",C31*E31) | M31: =Positions!X31 | N31: =iferror(IF(ISBLANK(F31),"",(E31-F31)/F31),"") | O31: =IF(N31="", "", IF(N31<=-15%, "Strong Buy", IF(N31<0%, "Buy", IF(N31<=15%, "Expensive", "Overrated")))) | P31: =IF(ISBLANK(A31),"",(E31-D31)/D31) | Q31: =IF(A31="", "", IF(P31<-15%, "Strong Buy", IF(P31<-5%, "Buy", IF(P31<5%, "Avg. Cost", IF(P31<=15%, "Overcost", "Hold"))))) | R31: =iferror($C$35/E31,"") | S31: 0 | T31: =E31*S31 -> 0 | U31: =(C31+S31)*E31 -> 0 | V31: =U31/$U$32 -> 0 | W31: =iferror(((C31*D31)+(S31*E31))/(C31+S31),"")
A32: =COUNTA(A2:A31) -> 17 | B32: <-- Total Holdings | K32: =SUM(K2:K31) -> 1 | L32: =SUM(L2:L31) -> 32346.081 | M32: =Positions!X32 -> 0.021898336 | S32: =SUM(S2:S31) -> 0 | T32: =SUM(T2:T31) -> 0 | U32: =SUM(U2:U31) -> 32346.081 | V32: =SUM(V2:V31) -> 1
B34: Buying Power | C34: 7960.27 | D34: =C34/L32 -> 0.24609689
B35: Remaining | C35: =C34-T32 -> 7960.27 | D35: =C35/U32 -> 0.24609689
B37: Category | C37: Moderate / Growth portfolio | D37: Dividend / Income portfolio
B38: US Bonds | C38: 0.5 | D38: 1
B39: International Market | C39: 9.5 | D39: 4
B40: Value Stocks (Dividend) | C40: 20 | D40: 40
B41: Foundational (Total Market) | C41: 40 | D41: 15
B42: Growth | C42: 30 | D42: 40

Sheet Sold Positions
A1: Ticker | B1: Company Name | C1: Date Sold | D1: # of Shares | E1: Avg. Cost Per Share | F1: Sale Price | G1: Current Price | H1: Total Dividends Received | I1: Market Return ($) | J1: Total Return ($) | K1: Market Return (%) | L1: Total Return (%) | M1: Expected Tax
A2: TGT | B2: =IFERROR(__xludf.DUMMYFUNCTION("IF(ISBLANK(A2),"""", googlefinance(A2, ""name""))"),"Target Corp") -> Target Corp | C2: 45617 | D2: 2 | E2: =306.11/D2 -> 153.055 | F2: 122.256 | G2: =IFERROR(__xludf.DUMMYFUNCTION("IF(ISBLANK(A2),"""", googlefinance(A2, ""price""))"),120.36) -> 120.36 | H2: 6.7 | I2: =if(isblank(A2),"",(F2-E2)*D2) -> -61.598 | J2: =if(isblank(A2),"",I2+H2) -> -54.898 | K2: =iferror(if(D2<0,0,I2/(E2*D2)),"") -> -0.20122832 | L2: =iferror(if(D2<0,0,J2/(E2*D2)),"") -> -0.17934076 | M2: =if(I2>0,I2*0.12,0) -> 0
A3: TGT | B3: =IFERROR(__xludf.DUMMYFUNCTION("IF(ISBLANK(A3),"""", googlefinance(A3, ""name""))"),"Target Corp") -> Target Corp | C3: 45617 | D3: 0.5 | E3: =94.6/D3 -> 189.2 | F3: 122.24 | G3: =IFERROR(__xludf.DUMMYFUNCTION("IF(ISBLANK(A3),"""", googlefinance(A3, ""price""))"),120.36) -> 120.36 | H3: 0 | I3: =if(isblank(A3),"",(F3-E3)*D3) -> -33.48 | J3: =if(isblank(A3),"",I3+H3) -> -33.48 | K3: =iferror(if(D3<0,0,I3/(E3*D3)),"") -> -0.35391121 | L3: =iferror(if(D3<0,0,J3/(E3*D3)),"") -> -0.35391121 | M3: =if(I3>0,I3*0.12,0) -> 0
B4: =IFERROR(__xludf.DUMMYFUNCTION("IF(ISBLANK(A4),"""", googlefinance(A4, ""name""))"),"") | G4: =IFERROR(__xludf.DUMMYFUNCTION("IF(ISBLANK(A4),"""", googlefinance(A4, ""price""))"),"") | I4: =if(isblank(A4),"",(F4-E4)*D4) | J4: =if(isblank(A4),"",I4+H4) | K4: =iferror(if(D4<0,0,I4/(E4*D4)),"") | L4: =iferror(if(D4<0,0,J4/(E4*D4)),"") | M4: =if(I4>0,I4*0.12,0) -> 0
B5: =IFERROR(__xludf.DUMMYFUNCTION("IF(ISBLANK(A5),"""", googlefinance(A5, ""name""))"),"") | G5: =IFERROR(__xludf.DUMMYFUNCTION("IF(ISBLANK(A5),"""", googlefinance(A5, ""price""))"),"") | I5: =if(isblank(A5),"",(F5-E5)*D5) | J5: =if(isblank(A5),"",I5+H5) | K5: =iferror(if(D5<0,0,I5/(E5*D5)),"") | L5: =iferror(if(D5<0,0,J5/(E5*D5)),"") | M5: =if(I5>0,I5*0.12,0) -> 0
B6: =IFERROR(__xludf.DUMMYFUNCTION("IF(ISBLANK(A6),"""", googlefinance(A6, ""name""))"),"") | G6: =IFERROR(__xludf.DUMMYFUNCTION("IF(ISBLANK(A6),"""", googlefinance(A6, ""price""))"),"") | I6: =if(isblank(A6),"",(F6-E6)*D6) | J6: =if(isblank(A6),"",I6+H6) | K6: =iferror(if(D6<0,0,I6/(E6*D6)),"") | L6: =iferror(if(D6<0,0,J6/(E6*D6)),"") | M6: =if(I6>0,I6*0.12,0) -> 0
B7: =IFERROR(__xludf.DUMMYFUNCTION("IF(ISBLANK(A7),"""", googlefinance(A7, ""name""))"),"") | G7: =IFERROR(__xludf.DUMMYFUNCTION("IF(ISBLANK(A7),"""", googlefinance(A7, ""price""))"),"") | I7: =if(isblank(A7),"",(F7-E7)*D7) | J7: =if(isblank(A7),"",I7+H7) | K7: =iferror(if(D7<0,0,I7/(E7*D7)),"") | L7: =iferror(if(D7<0,0,J7/(E7*D7)),"") | M7: =if(I7>0,I7*0.12,0) -> 0
B8: =IFERROR(__xludf.DUMMYFUNCTION("IF(ISBLANK(A8),"""", googlefinance(A8, ""name""))"),"") | G8: =IFERROR(__xludf.DUMMYFUNCTION("IF(ISBLANK(A8),"""", googlefinance(A8, ""price""))"),"") | I8: =if(isblank(A8),"",(F8-E8)*D8) | J8: =if(isblank(A8),"",I8+H8) | K8: =iferror(if(D8<0,0,I8/(E8*D8)),"") | L8: =iferror(if(D8<0,0,J8/(E8*D8)),"") | M8: =if(I8>0,I8*0.12,0) -> 0
B9: =IFERROR(__xludf.DUMMYFUNCTION("IF(ISBLANK(A9),"""", googlefinance(A9, ""name""))"),"") | G9: =IFERROR(__xludf.DUMMYFUNCTION("IF(ISBLANK(A9),"""", googlefinance(A9, ""price""))"),"") | I9: =if(isblank(A9),"",(F9-E9)*D9) | J9: =if(isblank(A9),"",I9+H9) | K9: =iferror(if(D9<0,0,I9/(E9*D9)),"") | L9: =iferror(if(D9<0,0,J9/(E9*D9)),"") | M9: =if(I9>0,I9*0.12,0) -> 0
B10: =IFERROR(__xludf.DUMMYFUNCTION("IF(ISBLANK(A10),"""", googlefinance(A10, ""name""))"),"") | G10: =IFERROR(__xludf.DUMMYFUNCTION("IF(ISBLANK(A10),"""", googlefinance(A10, ""price""))"),"") | I10: =if(isblank(A10),"",(F10-E10)*D10) | J10: =if(isblank(A10),"",I10+H10) | K10: =iferror(if(D10<0,0,I10/(E10*D10)),"") | L10: =iferror(if(D10<0,0,J10/(E10*D10)),"") | M10: =if(I10>0,I10*0.12,0) -> 0
B11: =IFERROR(__xludf.DUMMYFUNCTION("IF(ISBLANK(A11),"""", googlefinance(A11, ""name""))"),"") | G11: =IFERROR(__xludf.DUMMYFUNCTION("IF(ISBLANK(A11),"""", googlefinance(A11, ""price""))"),"") | I11: =if(isblank(A11),"",(F11-E11)*D11) | J11: =if(isblank(A11),"",I11+H11) | K11: =iferror(if(D11<0,0,I11/(E11*D11)),"") | L11: =iferror(if(D11<0,0,J11/(E11*D11)),"") | M11: =if(I11>0,I11*0.12,0) -> 0
B12: =IFERROR(__xludf.DUMMYFUNCTION("IF(ISBLANK(A12),"""", googlefinance(A12, ""name""))"),"") | G12: =IFERROR(__xludf.DUMMYFUNCTION("IF(ISBLANK(A12),"""", googlefinance(A12, ""price""))"),"") | I12: =if(isblank(A12),"",(F12-E12)*D12) | J12: =if(isblank(A12),"",I12+H12) | K12: =iferror(if(D12<0,0,I12/(E12*D12)),"") | L12: =iferror(if(D12<0,0,J12/(E12*D12)),"") | M12: =if(I12>0,I12*0.12,0) -> 0
B13: =IFERROR(__xludf.DUMMYFUNCTION("IF(ISBLANK(A13),"""", googlefinance(A13, ""name""))"),"") | G13: =IFERROR(__xludf.DUMMYFUNCTION("IF(ISBLANK(A13),"""", googlefinance(A13, ""price""))"),"") | I13: =if(isblank(A13),"",(F13-E13)*D13) | J13: =if(isblank(A13),"",I13+H13) | K13: =iferror(if(D13<0,0,I13/(E13*D13)),"") | L13: =iferror(if(D13<0,0,J13/(E13*D13)),"") | M13: =if(I13>0,I13*0.12,0) -> 0
B14: =IFERROR(__xludf.DUMMYFUNCTION("IF(ISBLANK(A14),"""", googlefinance(A14, ""name""))"),"") | G14: =IFERROR(__xludf.DUMMYFUNCTION("IF(ISBLANK(A14),"""", googlefinance(A14, ""price""))"),"") | I14: =if(isblank(A14),"",(F14-E14)*D14) | J14: =if(isblank(A14),"",I14+H14) | K14: =iferror(if(D14<0,0,I14/(E14*D14)),"") | L14: =iferror(if(D14<0,0,J14/(E14*D14)),"") | M14: =if(I14>0,I14*0.12,0) -> 0
B15: =IFERROR(__xludf.DUMMYFUNCTION("IF(ISBLANK(A15),"""", googlefinance(A15, ""name""))"),"") | G15: =IFERROR(__xludf.DUMMYFUNCTION("IF(ISBLANK(A15),"""", googlefinance(A15, ""price""))"),"") | I15: =if(isblank(A15),"",(F15-E15)*D15) | J15: =if(isblank(A15),"",I15+H15) | K15: =iferror(if(D15<0,0,I15/(E15*D15)),"") | L15: =iferror(if(D15<0,0,J15/(E15*D15)),"") | M15: =if(I15>0,I15*0.12,0) -> 0
A16: 2024 | I16: =SUM(I2:I15) -> -95.078 | J16: =SUM(J2:J15) -> -88.378 | M16: =SUM(M2:M15) -> 0
B21: WALKTHROUGH
B23: Click the link below for the spreadsheet walkthrough video on YouTube.
B26: WATCH HERE

Sheet Dividend Log
B1: =Dashboard!B1 -> PORTFOLIO FIDELITY 2024 | K1: Income Dividend Cumulated | N1: =SUM(AH4+AH18+AH46+AH60+AH74+AH88+AH102+AH116) -> 886.2 | AF1: CASH Interest | AG1: SOLD POSITIONS | AH1: TOTAL
B2: =Positions!A2 -> GOOGL | C2: =Positions!A3 -> MSFT | D2: =Positions!A4 -> DIS | E2: =Positions!A5 -> TGT | F2: =Positions!A6 -> SBUX | G2: =Positions!A7 -> JPM | H2: =Positions!A8 -> KO | I2: =Positions!A9 -> O | J2: =Positions!A10 -> VICI | K2: =Positions!A11 -> UNH | L2: =Positions!A12 -> VGT | M2: =Positions!A13 -> VOO | N2: =Positions!A14 -> VTI | O2: =Positions!A15 -> SCHD | P2: =Positions!A16 -> VIG | Q2: =Positions!A17 -> VXUS | R2: =Positions!A18 -> BND | S2: =Positions!A19 | T2: =Positions!A20 | U2: =Positions!A21 | V2: =Positions!A22 | W2: =Positions!A23 | X2: =Positions!A24 | Y2: =Positions!A25 | Z2: =Positions!A26 | AA2: =Positions!A27 | AB2: =Positions!A28 | AC2: =Positions!A29 | AD2: =Positions!A30 | AE2: =Positions!A31 | AF2: SPAXX
A3: All Times | B3: =SUM(B17,B31,B45,B59,B73,B87,B101,B115) -> 5.67 | C3: =SUM(C17,C31,C45,C59,C73,C87,C101,C115) -> 33.03 | D3: =SUM(D17,D31,D45,D59,D73,D87,D101,D115) -> 29.71 | E3: =SUM(E17,E31,E45,E59,E73,E87,E101,E115) -> 172.39 | F3: =SUM(F17,F31,F45,F59,F73,F87,F101,F115) -> 12.43 | G3: =SUM(G17,G31,G45,G59,G73,G87,G101,G115) -> 18.03 | H3: =SUM(H17,H31,H45,H59,H73,H87,H101,H115) -> 28.74 | I3: =SUM(I17,I31,I45,I59,I73,I87,I101,I115) -> 124 | ... AF3: =SUM(AF17,AF31,AF45,AF59,AF73,AF87,AF101,AF115) -> 180.66
A4: 2024 | B4: Highest Month Income | E4: =MAX(AH5:AH16) -> 66.58 | AE4: Expected Tax | AG4: =AH4*0.06 -> 9.0456 | AH4: =SUM(AH17) -> 150.76
A5: January | AH5: =SUM(B5:AF5)+AG5 -> 0
A6: February | AH6: =SUM(B6:AF6)+AG6 -> 0
A7: March | AH7: =SUM(B7:AF7)+AG7 -> 0
A8: April | AH8: =SUM(B8:AF8)+AG8 -> 0
A9: May | AF9: 3.56 | AH9: =SUM(B9:AF9)+AG9 -> 3.56
A10: June | C10: 0.75 | E10: 1.1 | I10: 0.79 | Q10: 1.93 | R10: 0.22 | AF10: 3.38 | AH10: =SUM(B10:AF10)+AG10 -> 8.17
A11: July | D11: 1.8 | G11: 1.15 | H11: 1.46 | I11: 2.37 | L11: 0.76 | M11: 3.57 | N11: 4.76 | O11: 3.3 | P11: 0.9 | R11: 0.22 | AF11: 0.48 | AH11: =SUM(B11:AF11)+AG11 -> 20.77
A12: August | I12: 2.38 | R12: 0.22 | AF12: 1.75 | AH12: =SUM(B12:AF12)+AG12 -> 4.35
A13: September | C13: 1.13 | E13: 5.6 | I13: 2.39 | O13: 12.1 | Q13: 3.28 | R13: 0.23 | AF13: 0.72 | AH13: =SUM(B13:AF13)+AG13 -> 25.45
A14: October | G14: 2.51 | H14: 1.47 | I14: 2.4 | L14: 0.92 | M14: 4.93 | N14: 5.24 | P14: 0.84 | R14: 0.22 | AF14: 0.37 | AH14: =SUM(B14:AF14)+AG14 -> 18.9
A15: November | I15: 2.41 | R15: 0.23 | AF15: 0.34 | AH15: =SUM(B15:AF15)+AG15 -> 2.98
A16: December | C16: 2.91 | E16: 7.88 | H16: 2.93 | I16: 2.42 | L16: 0.78 | M16: 5.24 | N16: 5.68 | O16: 23.95 | P16: 0.88 | Q16: 12.14 | R16: =0.23+0.47 -> 0.7 | AF16: 1.07 | AH16: =SUM(B16:AF16)+AG16 -> 66.58
A17: Total | B17: =SUM(B5:B16) -> 0 | C17: =SUM(C5:C16) -> 4.79 | D17: =SUM(D5:D16) -> 1.8 | E17: =SUM(E5:E16) -> 14.58 | F17: =SUM(F5:F16) -> 0 | G17: =SUM(G5:G16) -> 3.66 | H17: =SUM(H5:H16) -> 5.86 | I17: =SUM(I5:I16) -> 15.16 | ... AG17: =SUM(AG5:AG16) -> 0 | AH17: =SUM(B17:AF17)+AG17 -> 150.76
A18: 2025 | B18: Highest Month Income | E18: =MAX(AH19:AH30) -> 177.54 | AE18: Expected Tax | AG18: =AH18*0.06 -> 44.1264 | AH18: =SUM(AH31) -> 735.44
A19: January | D19: 6.51 | G19: 2.52 | I19: 5.87 | AF19: 4.83 | AH19: =SUM(B19:AF19)+AG19 -> 19.73
A20: February | I20: 5.9 | R20: 0.48 | AF20: 5.72 | AH20: =SUM(B20:AF20)+AG20 -> 12.1
A21: March | C21: 3.74 | E21: 16.23 | I21: 7.63 | L21: 0.73 | M21: 5.48 | N21: 5.97 | O21: 24.98 | P21: 0.95 | Q21: 2.35 | R21: 0.45 | AF21: 23.92 | AH21: =SUM(B21:AF21)+AG21 -> 92.43
A22: April | G22: 2.84 | H22: 5.66 | I22: 7.68 | J22: 6.49 | R22: 0.49 | AF22: 12.78 | AH22: =SUM(B22:AF22)+AG22 -> 35.94
A23: May | F23: 3.05 | I23: 7.98 | R23: 0.48 | AF23: 10.25 | AH23: =SUM(B23:AF23)+AG23 -> 21.76
A24: June | B24: 1.89 | C24: 7.9 | E24: 34.3 | I24: 8.02 | L24: 2.11 | O24: 34.17 | Q24: 6.95 | R24: 0.49 | AF24: 10.12 | AH24: =SUM(B24:AF24)+AG24 -> 105.95
A25: July | D25: 8.54 | G25: 2.85 | H25: 5.7 | I25: 8.08 | J25: 6.57 | M25: 5.3 | N25: 7.38 | P25: 0.89 | R25: 0.48 | AF25: 9.59 | AH25: =SUM(B25:AF25)+AG25 -> 55.38
A26: August | F26: 3.07 | I26: 8.11 | R26: 0.5 | AF26: 6.78 | AH26: =SUM(B26:AF26)+AG26 -> 18.46
A27: September | B27: 1.89 | C27: 7.91 | E27: 35.33 | I27: 8.15 | K27: 11.05 | L27: 2.58 | O27: 47.55 | Q27: 5.19 | R27: 0.5 | AF27: 4.86 | AH27: =SUM(B27:AF27)+AG27 -> 125.01
A28: October | G28: 3.07 | H28: 5.74 | I28: 8.2 | J28: 6.93 | M28: 5.3 | N28: 7.35 | P28: 0.88 | R28: 0.49 | AF28: 8.3 | AH28: =SUM(B28:AF28)+AG28 -> 46.26
A29: November | F29: 3.14 | I29: 8.24 | R29: 0.51 | AF29: 12.99 | AH29: =SUM(B29:AF29)+AG29 -> 24.88
A30: December | B30: 1.89 | C30: 8.69 | E30: 35.75 | H30: 5.78 | I30: 8.28 | K30: 11.12 | L30: 2.28 | M30: 5.41 | N30: 7.72 | O30: 51.29 | P30: 0.91 | Q30: 19.77 | R30: =0.5+0.52 -> 1.02 | AF30: 17.63 | AH30: =SUM(B30:AF30)+AG30 -> 177.54
A31: Total | B31: =SUM(B19:B30) -> 5.67 | C31: =SUM(C19:C30) -> 28.24 | D31: =SUM(D19:D30) -> 15.05 | E31: =SUM(E19:E30) -> 121.61 | F31: =SUM(F19:F30) -> 9.26 | G31: =SUM(G19:G30) -> 11.28 | H31: =SUM(H19:H30) -> 22.88 | I31: =SUM(I19:I30) -> 92.14 | ... AG31: =SUM(AG19:AG30) -> 0 | AH31: =SUM(B31:AF31)+AG31 -> 735.44
A32: 2026 | B32: Highest Month Income | E32: =MAX(AH33:AH44) -> 52.21 | AE32: Expected Tax | AG32: =AH32*0.06 -> 7.2474 | AH32: =SUM(AH45) -> 120.79
A33: January | D33: 12.86 | G33: 3.09 | I33: 8.33 | J33: 7.03 | AF33: 20.9 | AH33: =SUM(B33:AF33)+AG33 -> 52.21
A34: February | F34: 3.17 | I34: 8.37 | R34: 0.52 | AF34: 20.32 | AH34: =SUM(B34:AF34)+AG34 -> 32.38
A35: March | E35: 36.2 | AH35: =SUM(B35:AF35)+AG35 -> 36.2
A36: April | AH36: =SUM(B36:AF36)+AG36 -> 0
A37: May | AH37: =SUM(B37:AF37)+AG37 -> 0
A38: June | AH38: =SUM(B38:AF38)+AG38 -> 0
A39: July | AH39: =SUM(B39:AF39)+AG39 -> 0
A40: August | AH40: =SUM(B40:AF40)+AG40 -> 0
A41: September | AH41: =SUM(B41:AF41)+AG41 -> 0
A42: October | AH42: =SUM(B42:AF42)+AG42 -> 0
A43: November | AH43: =SUM(B43:AF43)+AG43 -> 0
A44: December | AH44: =SUM(B44:AF44)+AG44 -> 0
A45: Total | B45: =SUM(B33:B44) -> 0 | C45: =SUM(C33:C44) -> 0 | D45: =SUM(D33:D44) -> 12.86 | E45: =SUM(E33:E44) -> 36.2 | F45: =SUM(F33:F44) -> 3.17 | G45: =SUM(G33:G44) -> 3.09 | H45: =SUM(H33:H44) -> 0 | I45: =SUM(I33:I44) -> 16.7 | ... AG45: =SUM(AG33:AG44) -> 0 | AH45: =SUM(B45:AF45)+AG45 -> 120.79
A46: 2027 | B46: Highest Month Income | E46: =MAX(AH47:AH58) -> 0 | AE46: Expected Tax | AG46: =AH46*0.06 -> 0 | AH46: =SUM(AH59) -> 0
A47: January | AH47: =SUM(B47:AF47)+AG47 -> 0
A48: February | AH48: =SUM(B48:AF48)+AG48 -> 0
A49: March | AH49: =SUM(B49:AF49)+AG49 -> 0
A50: April | AH50: =SUM(B50:AF50)+AG50 -> 0
A51: May | AH51: =SUM(B51:AF51)+AG51 -> 0
A52: June | AH52: =SUM(B52:AF52)+AG52 -> 0
A53: July | AH53: =SUM(B53:AF53)+AG53 -> 0
A54: August | AH54: =SUM(B54:AF54)+AG54 -> 0
A55: September | AH55: =SUM(B55:AF55)+AG55 -> 0
A56: October | AH56: =SUM(B56:AF56)+AG56 -> 0
A57: November | AH57: =SUM(B57:AF57)+AG57 -> 0
A58: December | AH58: =SUM(B58:AF58)+AG58 -> 0
A59: Total | B59: =SUM(B47:B58) -> 0 | C59: =SUM(C47:C58) -> 0 | D59: =SUM(D47:D58) -> 0 | E59: =SUM(E47:E58) -> 0 | F59: =SUM(F47:F58) -> 0 | G59: =SUM(G47:G58) -> 0 | H59: =SUM(H47:H58) -> 0 | I59: =SUM(I47:I58) -> 0 | ... AG59: =SUM(AG47:AG58) -> 0 | AH59: =SUM(B59:AF59)+AG59 -> 0
A60: 2028 | B60: Highest Month Income | E60: =MAX(AH61:AH72) -> 0 | AE60: Expected Tax | AG60: =AH60*0.06 -> 0 | AH60: =SUM(AH73) -> 0
A61: January | AH61: =SUM(B61:AF61)+AG61 -> 0
A62: February | AH62: =SUM(B62:AF62)+AG62 -> 0
A63: March | AH63: =SUM(B63:AF63)+AG63 -> 0
A64: April | AH64: =SUM(B64:AF64)+AG64 -> 0
A65: May | AH65: =SUM(B65:AF65)+AG65 -> 0
A66: June | AH66: =SUM(B66:AF66)+AG66 -> 0
A67: July | AH67: =SUM(B67:AF67)+AG67 -> 0
A68: August | AH68: =SUM(B68:AF68)+AG68 -> 0
A69: September | AH69: =SUM(B69:AF69)+AG69 -> 0
A70: October | AH70: =SUM(B70:AF70)+AG70 -> 0
A71: November | AH71: =SUM(B71:AF71)+AG71 -> 0
A72: December | AH72: =SUM(B72:AF72)+AG72 -> 0
A73: Total | B73: =SUM(B61:B72) -> 0 | C73: =SUM(C61:C72) -> 0 | D73: =SUM(D61:D72) -> 0 | E73: =SUM(E61:E72) -> 0 | F73: =SUM(F61:F72) -> 0 | G73: =SUM(G61:G72) -> 0 | H73: =SUM(H61:H72) -> 0 | I73: =SUM(I61:I72) -> 0 | ... AE73: =SUM(AE61:AE72) -> 0 | AG73: =SUM(AG61:AG72) -> 0 | AH73: =SUM(B73:AE73)+AG73 -> 0
A74: 2029 | B74: Highest Month Income | E74: =MAX(AH75:AH86) -> 0 | AE74: Expected Tax | AG74: =AH74*0.06 -> 0 | AH74: =SUM(AH87) -> 0
A75: January | AH75: =SUM(B75:AF75)+AG75 -> 0
A76: February | AH76: =SUM(B76:AF76)+AG76 -> 0
A77: March | AH77: =SUM(B77:AF77)+AG77 -> 0
A78: April | AH78: =SUM(B78:AF78)+AG78 -> 0
A79: May | AH79: =SUM(B79:AF79)+AG79 -> 0
A80: June | AH80: =SUM(B80:AF80)+AG80 -> 0
A81: July | AH81: =SUM(B81:AF81)+AG81 -> 0
A82: August | AH82: =SUM(B82:AF82)+AG82 -> 0
A83: September | AH83: =SUM(B83:AF83)+AG83 -> 0
A84: October | AH84: =SUM(B84:AF84)+AG84 -> 0
A85: November | AH85: =SUM(B85:AF85)+AG85 -> 0
A86: December | AH86: =SUM(B86:AF86)+AG86 -> 0
A87: Total | B87: =SUM(B75:B86) -> 0 | C87: =SUM(C75:C86) -> 0 | D87: =SUM(D75:D86) -> 0 | E87: =SUM(E75:E86) -> 0 | F87: =SUM(F75:F86) -> 0 | G87: =SUM(G75:G86) -> 0 | H87: =SUM(H75:H86) -> 0 | I87: =SUM(I75:I86) -> 0 | ... AG87: =SUM(AG75:AG86) -> 0 | AH87: =SUM(B87:AF87)+AG87 -> 0
A88: 2030 | B88: Highest Month Income | E88: =MAX(AH89:AH100) -> 0 | AE88: Expected Tax | AG88: =AH88*0.06 -> 0 | AH88: =SUM(AH101) -> 0
A89: January | AH89: =SUM(B89:AF89)+AG89 -> 0
A90: February | AH90: =SUM(B90:AF90)+AG90 -> 0
A91: March | AH91: =SUM(B91:AF91)+AG91 -> 0
A92: April | AH92: =SUM(B92:AF92)+AG92 -> 0
A93: May | AH93: =SUM(B93:AF93)+AG93 -> 0
A94: June | AH94: =SUM(B94:AF94)+AG94 -> 0
A95: July | AH95: =SUM(B95:AF95)+AG95 -> 0
A96: August | AH96: =SUM(B96:AF96)+AG96 -> 0
A97: September | AH97: =SUM(B97:AF97)+AG97 -> 0
A98: October | AH98: =SUM(B98:AF98)+AG98 -> 0
A99: November | AH99: =SUM(B99:AF99)+AG99 -> 0
A100: December | AH100: =SUM(B100:AF100)+AG100 -> 0
...

Sheet Monthly Data 
A1: Starting Investment | C1: =Dashboard!B1 -> PORTFOLIO FIDELITY 2024 | K1: Monthly Income Distribution
A2: =4260 -> 4260 | C2: Portfolio Value (considering DRIP) | D2: Monthly Contributions | E2: Dividend Income | F2: Accumulated Investment | G2: Total Return | H2: Total Return (%) | I2: Portfolio Yield (%) | K2: Month | L2: 2024 | M2: 2025 | N2: 2026 | O2: 2027 | P2: 2028 | Q2: 2029 | R2: 2030 | S2: 2031 | T2: YOY Growth (%)
A3: 2024 | B3: January 24 | C3: 0 | D3: 0 | E3: ='Dividend Log'!AH5 -> 0 | F3: =Sum(D3:E3) -> 0 | G3: =C3-F3 -> 0 | H3: =IFERROR((G3)/F3,0) -> 0 | K3: January | L3: =E3 -> 0 | M3: =E15 -> 19.73 | N3: =E27 -> 52.21 | O3: =E39 -> 0 | P3: =E51 -> 0 | Q3: =E63 -> 0 | R3: =E75 -> 0 | S3: =E87 -> 0 | T3: =iferror((N3-M3)/N3,"") -> 0.62210305
B4: February 24 | C4: 0 | D4: 0 | E4: ='Dividend Log'!AH6 -> 0 | F4: =Sum(D4:E4) -> 0 | G4: =C4-F4 -> 0 | H4: =IFERROR((G4)/F4,0) -> 0 | K4: February | L4: =E4 -> 0 | M4: =E16 -> 12.1 | N4: =E28 -> 32.38 | O4: =E40 -> 0 | P4: =E52 -> 0 | Q4: =E64 -> 0 | R4: =E76 -> 0 | S4: =E88 -> 0 | T4: =iferror((N4-M4)/N4,"") -> 0.62631254
B5: March 24 | C5: 0 | D5: 0 | E5: ='Dividend Log'!AH7 -> 0 | F5: =Sum(D5:E5) -> 0 | G5: =C5-F5 -> 0 | H5: =IFERROR((G5)/F5,0) -> 0 | K5: March | L5: =E5 -> 0 | M5: =E17 -> 92.43 | N5: =E29 -> 36.2 | O5: =E41 -> 0 | P5: =E53 -> 0 | Q5: =E65 -> 0 | R5: =E77 -> 0 | S5: =E89 -> 0 | T5: =iferror((N5-M5)/N5,"") -> -1.5533149
B6: April 24 | C6: 0 | D6: 0 | E6: ='Dividend Log'!AH8 -> 0 | F6: =Sum(D6:E6) -> 0 | G6: =C6-F6 -> 0 | H6: =IFERROR((G6)/F6,0) -> 0 | K6: April | L6: =E6 -> 0 | M6: =E18 -> 35.94 | N6: =E30 -> 0 | O6: =E42 -> 0 | P6: =E54 -> 0 | Q6: =E66 -> 0 | R6: =E78 -> 0 | S6: =E90 -> 0 | T6: =iferror((N6-M6)/N6,"")
B7: May 24 | C7: 4318.02 | D7: 0 | E7: ='Dividend Log'!AH9 -> 3.56 | F7: =$A$2+sum($D$3:D7) -> 4260 | G7: =C7-F7 -> 58.02 | H7: =IFERROR((G7)/F7,0) -> 0.013619718 | K7: May | L7: =E7 -> 3.56 | M7: =E19 -> 21.76 | N7: =E31 -> 0 | O7: =E43 -> 0 | P7: =E55 -> 0 | Q7: =E67 -> 0 | R7: =E79 -> 0 | S7: =E91 -> 0 | T7: =iferror((N7-M7)/N7,"")
B8: June 24 | C8: 6230.35 | D8: 1800 | E8: ='Dividend Log'!AH10 -> 8.17 | F8: =$A$2+sum($D$3:D8) -> 6060 | G8: =C8-F8 -> 170.35 | H8: =IFERROR((G8)/F8,0) -> 0.028110561 | K8: June | L8: =E8 -> 8.17 | M8: =E20 -> 105.95 | N8: =E32 -> 0 | O8: =E44 -> 0 | P8: =E56 -> 0 | Q8: =E68 -> 0 | R8: =E80 -> 0 | S8: =E92 -> 0 | T8: =iferror((N8-M8)/N8,"")
B9: July 24 | C9: 7339.37 | D9: 1000 | E9: ='Dividend Log'!AH11 -> 20.77 | F9: =$A$2+sum($D$3:D9) -> 7060 | G9: =C9-F9 -> 279.37 | H9: =IFERROR((G9)/F9,0) -> 0.039570822 | K9: July | L9: =E9 -> 20.77 | M9: =E21 -> 55.38 | N9: =E33 -> 0 | O9: =E45 -> 0 | P9: =E57 -> 0 | Q9: =E69 -> 0 | R9: =E81 -> 0 | S9: =E93 -> 0 | T9: =iferror((N9-M9)/N9,"")
B10: August 24 | C10: 8638.08 | D10: 1000 | E10: ='Dividend Log'!AH12 -> 4.35 | F10: =$A$2+sum($D$3:D10) -> 8060 | G10: =C10-F10 -> 578.08 | H10: =IFERROR((G10)/F10,0) -> 0.071722084 | K10: August | L10: =E10 -> 4.35 | M10: =E22 -> 18.46 | N10: =E34 -> 0 | O10: =E46 -> 0 | P10: =E58 -> 0 | Q10: =E70 -> 0 | R10: =E82 -> 0 | S10: =E94 -> 0 | T10: =iferror((N10-M10)/N10,"")
B11: September 24 | C11: =9922.32 -> 9922.32 | D11: 1070 | E11: ='Dividend Log'!AH13 -> 25.45 | F11: =$A$2+sum($D$3:D11) -> 9130 | G11: =C11-F11 -> 792.32 | H11: =IFERROR((G11)/F11,0) -> 0.086782037 | K11: September | L11: =E11 -> 25.45 | M11: =E23 -> 125.01 | N11: =E35 -> 0 | O11: =E47 -> 0 | P11: =E59 -> 0 | Q11: =E71 -> 0 | R11: =E83 -> 0 | S11: =E95 -> 0 | T11: =iferror((N11-M11)/N11,"")
B12: October 24 | C12: 10975.41 | D12: 1200 | E12: ='Dividend Log'!AH14 -> 18.9 | F12: =$A$2+sum($D$3:D12) -> 10330 | G12: =C12-F12 -> 645.41 | H12: =IFERROR((G12)/F12,0) -> 0.062479187 | K12: October | L12: =E12 -> 18.9 | M12: =E24 -> 46.26 | N12: =E36 -> 0 | O12: =E48 -> 0 | P12: =E60 -> 0 | Q12: =E72 -> 0 | R12: =E84 -> 0 | S12: =E96 -> 0 | T12: =iferror((N12-M12)/N12,"")
B13: November 24 | C13: 13901.98 | D13: 2250 | E13: ='Dividend Log'!AH15 -> 2.98 | F13: =$A$2+sum($D$3:D13) -> 12580 | G13: =C13-F13 -> 1321.98 | H13: =IFERROR((G13)/F13,0) -> 0.10508585 | K13: November | L13: =E13 -> 2.98 | M13: =E25 -> 24.88 | N13: =E37 -> 0 | O13: =E49 -> 0 | P13: =E61 -> 0 | Q13: =E73 -> 0 | R13: =E85 -> 0 | S13: =E97 -> 0 | T13: =iferror((N13-M13)/N13,"")
B14: December 24 | C14: 14947.02 | D14: 1500 | E14: ='Dividend Log'!AH16 -> 66.58 | F14: =$A$2+sum($D$3:D14) -> 14080 | G14: =C14-F14 -> 867.02 | H14: =IFERROR((G14)/F14,0) -> 0.061578125 | K14: December | L14: =E14 -> 66.58 | M14: =E26 -> 177.54 | N14: =E38 -> 0 | O14: =E50 -> 0 | P14: =E62 -> 0 | Q14: =E74 -> 0 | R14: =E86 -> 0 | S14: =E98 -> 0 | T14: =iferror((N14-M14)/N14,"")
A15: 2025 | B15: January 25 | C15: 16775.1 | D15: 1500 | E15: ='Dividend Log'!AH19 -> 19.73 | F15: =$A$2+sum($D$3:D15) -> 15580 | G15: =C15-F15 -> 1195.1 | H15: =IFERROR((G15)/F15,0) -> 0.076707317 | K15: Best Month Income | L15: =MAX(L3:L14) -> 66.58 | M15: =MAX(M3:M14) -> 177.54 | N15: =MAX(N3:N14) -> 52.21 | O15: =MAX(O3:O14) -> 0 | P15: =MAX(P3:P14) -> 0 | Q15: =MAX(Q3:Q14) -> 0 | R15: =MAX(R3:R14) -> 0 | S15: =MAX(S3:S14) -> 0 | T15: =iferror((M15-L15)/M15,"") -> 0.62498592
B16: February 25 | C16: 23233.26 | D16: 6500 | E16: ='Dividend Log'!AH20 -> 12.1 | F16: =$A$2+sum($D$3:D16) -> 22080 | G16: =C16-F16 -> 1153.26 | H16: =IFERROR((G16)/F16,0) -> 0.052230978
B17: March 25 | C17: 23838.27 | D17: 1500 | E17: ='Dividend Log'!AH21 -> 92.43 | F17: =$A$2+sum($D$3:D17) -> 23580 | G17: =C17-F17 -> 258.27 | H17: =IFERROR((G17)/F17,0) -> 0.010952926 | K17: Total Income | L17: =SUM(L3:L14) -> 150.76 | M17: =SUM(M3:M14) -> 735.44 | N17: =SUM(N3:N14) -> 120.79 | O17: =SUM(O3:O14) -> 0 | P17: =SUM(P3:P14) -> 0 | Q17: =SUM(Q3:Q14) -> 0 | R17: =SUM(R3:R14) -> 0 | S17: =SUM(S3:S14) -> 0 | T17: =iferror((M17-L17)/M17,"") -> 0.79500707
B18: April 25 | C18: 25271.25 | D18: 1500 | E18: ='Dividend Log'!AH22 -> 35.94 | F18: =$A$2+sum($D$3:D18) -> 25080 | G18: =C18-F18 -> 191.25 | H18: =IFERROR((G18)/F18,0) -> 0.0076255981
B19: May 25 | C19: 28355.93 | D19: 1500 | E19: ='Dividend Log'!AH23 -> 21.76 | F19: =$A$2+sum($D$3:D19) -> 26580 | G19: =C19-F19 -> 1775.93 | H19: =IFERROR((G19)/F19,0) -> 0.066814522
B20: June 25 | C20: 30753.41 | D20: 1000 | E20: ='Dividend Log'!AH24 -> 105.95 | F20: =$A$2+sum($D$3:D20) -> 27580 | G20: =C20-F20 -> 3173.41 | H20: =IFERROR((G20)/F20,0) -> 0.115062
B21: July 25 | C21: 31357.29 | D21: 0 | E21: ='Dividend Log'!AH25 -> 55.38 | F21: =$A$2+sum($D$3:D21) -> 27580 | G21: =C21-F21 -> 3777.29 | H21: =IFERROR((G21)/F21,0) -> 0.13695758
B22: August 25 | C22: 31939.91 | D22: 0 | E22: ='Dividend Log'!AH26 -> 18.46 | F22: =$A$2+sum($D$3:D22) -> 27580 | G22: =C22-F22 -> 4359.91 | H22: =IFERROR((G22)/F22,0) -> 0.15808231
B23: September 25 | C23: 32595.16 | D23: 0 | E23: ='Dividend Log'!AH27 -> 125.01 | F23: =$A$2+sum($D$3:D23) -> 27580 | G23: =C23-F23 -> 5015.16 | H23: =IFERROR((G23)/F23,0) -> 0.18184046
B24: October 25 | C24: 34563.82 | D24: 3000 | E24: ='Dividend Log'!AH28 -> 46.26 | F24: =$A$2+sum($D$3:D24) -> 30580 | G24: =C24-F24 -> 3983.82 | H24: =IFERROR((G24)/F24,0) -> 0.13027534
B25: November 25 | C25: 36036.33 | D25: 1500 | E25: ='Dividend Log'!AH29 -> 24.88 | F25: =$A$2+sum($D$3:D25) -> 32080 | G25: =C25-F25 -> 3956.33 | H25: =IFERROR((G25)/F25,0) -> 0.12332699
B26: December 25 | C26: 39944.91 | D26: 1500 | E26: ='Dividend Log'!AH30 -> 177.54 | F26: =$A$2+sum($D$3:D26) -> 33580 | G26: =C26-F26 -> 6364.91 | H26: =IFERROR((G26)/F26,0) -> 0.18954467
A27: 2026 | B27: January 26 | C27: 40289.09 | D27: 400 | E27: ='Dividend Log'!AH33 -> 52.21 | F27: =$A$2+sum($D$3:D27) -> 33980 | G27: =C27-F27 -> 6309.09 | H27: =IFERROR((G27)/F27,0) -> 0.18567069
B28: February 26 | C28: 40554.79 | D28: 0 | E28: ='Dividend Log'!AH34 -> 32.38 | F28: =$A$2+sum($D$3:D28) -> 33980 | G28: =C28-F28 -> 6574.79 | H28: =IFERROR((G28)/F28,0) -> 0.19348999
B29: March 26 | C29: =Dashboard!D4 -> 40306.351 | E29: ='Dividend Log'!AH35 -> 36.2 | G29: =C29-F29 -> 40306.351 | H29: =IFERROR((G29)/F29,0) -> 0
B30: April 26 | E30: ='Dividend Log'!AH36 -> 0 | G30: =C30-F30 -> 0 | H30: =IFERROR((G30)/F30,0) -> 0
B31: May 26 | E31: ='Dividend Log'!AH37 -> 0 | G31: =C31-F31 -> 0 | H31: =IFERROR((G31)/F31,0) -> 0
B32: June 26 | E32: ='Dividend Log'!AH38 -> 0 | G32: =C32-F32 -> 0 | H32: =IFERROR((G32)/F32,0) -> 0
B33: July 26 | E33: ='Dividend Log'!AH39 -> 0 | G33: =C33-F33 -> 0 | H33: =IFERROR((G33)/F33,0) -> 0
B34: August 26 | E34: ='Dividend Log'!AH40 -> 0 | G34: =C34-F34 -> 0 | H34: =IFERROR((G34)/F34,0) -> 0
B35: September 26 | E35: ='Dividend Log'!AH41 -> 0 | G35: =C35-F35 -> 0 | H35: =IFERROR((G35)/F35,0) -> 0
B36: October 26 | E36: ='Dividend Log'!AH42 -> 0 | G36: =C36-F36 -> 0 | H36: =IFERROR((G36)/F36,0) -> 0
B37: November 26 | E37: ='Dividend Log'!AH43 -> 0 | G37: =C37-F37 -> 0 | H37: =IFERROR((G37)/F37,0) -> 0
B38: December 26 | E38: ='Dividend Log'!AH44 -> 0 | G38: =C38-F38 -> 0 | H38: =IFERROR((G38)/F38,0) -> 0
A39: 2027 | B39: January 27 | E39: ='Dividend Log'!AH47 -> 0 | G39: =C39-F39 -> 0 | H39: =IFERROR((G39)/F39,0) -> 0
B40: February 27 | E40: ='Dividend Log'!AH48 -> 0 | G40: =C40-F40 -> 0 | H40: =IFERROR((G40)/F40,0) -> 0
B41: March 27 | E41: ='Dividend Log'!AH49 -> 0 | G41: =C41-F41 -> 0 | H41: =IFERROR((G41)/F41,0) -> 0
B42: April 27 | E42: ='Dividend Log'!AH50 -> 0 | G42: =C42-F42 -> 0 | H42: =IFERROR((G42)/F42,0) -> 0
B43: May 27 | E43: ='Dividend Log'!AH51 -> 0 | G43: =C43-F43 -> 0 | H43: =IFERROR((G43)/F43,0) -> 0
B44: June 27 | E44: ='Dividend Log'!AH52 -> 0 | G44: =C44-F44 -> 0 | H44: =IFERROR((G44)/F44,0) -> 0
B45: July 27 | E45: ='Dividend Log'!AH53 -> 0 | G45: =C45-F45 -> 0 | H45: =IFERROR((G45)/F45,0) -> 0
B46: August 27 | E46: ='Dividend Log'!AH54 -> 0 | G46: =C46-F46 -> 0 | H46: =IFERROR((G46)/F46,0) -> 0
B47: September 27 | E47: ='Dividend Log'!AH55 -> 0 | G47: =C47-F47 -> 0 | H47: =IFERROR((G47)/F47,0) -> 0
B48: October 27 | E48: ='Dividend Log'!AH56 -> 0 | G48: =C48-F48 -> 0 | H48: =IFERROR((G48)/F48,0) -> 0
B49: November 27 | E49: ='Dividend Log'!AH57 -> 0 | G49: =C49-F49 -> 0 | H49: =IFERROR((G49)/F49,0) -> 0
B50: December 27 | E50: ='Dividend Log'!AH58 -> 0 | G50: =C50-F50 -> 0 | H50: =IFERROR((G50)/F50,0) -> 0
A51: 2028 | B51: January 28 | E51: ='Dividend Log'!AH61 -> 0 | G51: =C51-F51 -> 0 | H51: =IFERROR((G51)/F51,0) -> 0
B52: February 28 | E52: ='Dividend Log'!AH62 -> 0 | G52: =C52-F52 -> 0 | H52: =IFERROR((G52)/F52,0) -> 0
B53: March 28 | E53: ='Dividend Log'!AH63 -> 0 | G53: =C53-F53 -> 0 | H53: =IFERROR((G53)/F53,0) -> 0
B54: April 28 | E54: ='Dividend Log'!AH64 -> 0 | G54: =C54-F54 -> 0 | H54: =IFERROR((G54)/F54,0) -> 0
B55: May 28 | E55: ='Dividend Log'!AH65 -> 0 | G55: =C55-F55 -> 0 | H55: =IFERROR((G55)/F55,0) -> 0
B56: June 28 | E56: ='Dividend Log'!AH66 -> 0 | G56: =C56-F56 -> 0 | H56: =IFERROR((G56)/F56,0) -> 0
B57: July 28 | E57: ='Dividend Log'!AH67 -> 0 | G57: =C57-F57 -> 0 | H57: =IFERROR((G57)/F57,0) -> 0
B58: August 28 | E58: ='Dividend Log'!AH68 -> 0 | G58: =C58-F58 -> 0 | H58: =IFERROR((G58)/F58,0) -> 0
B59: September 28 | E59: ='Dividend Log'!AH69 -> 0 | G59: =C59-F59 -> 0 | H59: =IFERROR((G59)/F59,0) -> 0
B60: October 28 | E60: ='Dividend Log'!AH70 -> 0 | G60: =C60-F60 -> 0 | H60: =IFERROR((G60)/F60,0) -> 0
B61: November 28 | E61: ='Dividend Log'!AH71 -> 0 | G61: =C61-F61 -> 0 | H61: =IFERROR((G61)/F61,0) -> 0
B62: December 28 | E62: ='Dividend Log'!AH72 -> 0 | G62: =C62-F62 -> 0 | H62: =IFERROR((G62)/F62,0) -> 0
A63: 2029 | B63: January 29 | E63: ='Dividend Log'!AH75 -> 0 | G63: =C63-F63 -> 0 | H63: =IFERROR((G63)/F63,0) -> 0
B64: February 29 | E64: ='Dividend Log'!AH76 -> 0 | G64: =C64-F64 -> 0 | H64: =IFERROR((G64)/F64,0) -> 0
B65: March 29 | E65: ='Dividend Log'!AH77 -> 0 | G65: =C65-F65 -> 0 | H65: =IFERROR((G65)/F65,0) -> 0
B66: April 29 | E66: ='Dividend Log'!AH78 -> 0 | G66: =C66-F66 -> 0 | H66: =IFERROR((G66)/F66,0) -> 0
B67: May 29 | E67: ='Dividend Log'!AH79 -> 0 | G67: =C67-F67 -> 0 | H67: =IFERROR((G67)/F67,0) -> 0
B68: June 29 | E68: ='Dividend Log'!AH80 -> 0 | G68: =C68-F68 -> 0 | H68: =IFERROR((G68)/F68,0) -> 0
B69: July 29 | E69: ='Dividend Log'!AH81 -> 0 | G69: =C69-F69 -> 0 | H69: =IFERROR((G69)/F69,0) -> 0
B70: August 29 | E70: ='Dividend Log'!AH82 -> 0 | G70: =C70-F70 -> 0 | H70: =IFERROR((G70)/F70,0) -> 0
B71: September 29 | E71: ='Dividend Log'!AH83 -> 0 | G71: =C71-F71 -> 0 | H71: =IFERROR((G71)/F71,0) -> 0
B72: October 29 | E72: ='Dividend Log'!AH84 -> 0 | G72: =C72-F72 -> 0 | H72: =IFERROR((G72)/F72,0) -> 0
B73: November 29 | E73: ='Dividend Log'!AH85 -> 0 | G73: =C73-F73 -> 0 | H73: =IFERROR((G73)/F73,0) -> 0
B74: December 29 | E74: ='Dividend Log'!AH86 -> 0 | G74: =C74-F74 -> 0 | H74: =IFERROR((G74)/F74,0) -> 0
A75: 2030 | B75: January 30 | E75: ='Dividend Log'!AH89 -> 0 | G75: =C75-F75 -> 0 | H75: =IFERROR((G75)/F75,0) -> 0
B76: February 30 | E76: ='Dividend Log'!AH90 -> 0 | G76: =C76-F76 -> 0 | H76: =IFERROR((G76)/F76,0) -> 0
B77: March 30 | E77: ='Dividend Log'!AH91 -> 0 | G77: =C77-F77 -> 0 | H77: =IFERROR((G77)/F77,0) -> 0
B78: April 30 | E78: ='Dividend Log'!AH92 -> 0 | G78: =C78-F78 -> 0 | H78: =IFERROR((G78)/F78,0) -> 0
B79: May 30 | E79: ='Dividend Log'!AH93 -> 0 | G79: =C79-F79 -> 0 | H79: =IFERROR((G79)/F79,0) -> 0
B80: June 30 | E80: ='Dividend Log'!AH94 -> 0 | G80: =C80-F80 -> 0 | H80: =IFERROR((G80)/F80,0) -> 0
B81: July 30 | E81: ='Dividend Log'!AH95 -> 0 | G81: =C81-F81 -> 0 | H81: =IFERROR((G81)/F81,0) -> 0
B82: August 30 | E82: ='Dividend Log'!AH96 -> 0 | G82: =C82-F82 -> 0 | H82: =IFERROR((G82)/F82,0) -> 0
B83: September 30 | E83: ='Dividend Log'!AH97 -> 0 | G83: =C83-F83 -> 0 | H83: =IFERROR((G83)/F83,0) -> 0
B84: October 30 | E84: ='Dividend Log'!AH98 -> 0 | G84: =C84-F84 -> 0 | H84: =IFERROR((G84)/F84,0) -> 0
B85: November 30 | E85: ='Dividend Log'!AH99 -> 0 | G85: =C85-F85 -> 0 | H85: =IFERROR((G85)/F85,0) -> 0
B86: December 30 | E86: ='Dividend Log'!AH100 -> 0 | G86: =C86-F86 -> 0 | H86: =IFERROR((G86)/F86,0) -> 0
A87: 2031 | B87: January 31 | E87: ='Dividend Log'!AH103 -> 0 | G87: =C87-F87 -> 0 | H87: =IFERROR((G87)/F87,0) -> 0
B88: February 31 | E88: ='Dividend Log'!AH104 -> 0 | G88: =C88-F88 -> 0 | H88: =IFERROR((G88)/F88,0) -> 0
B89: March 31 | E89: ='Dividend Log'!AH105 -> 0 | G89: =C89-F89 -> 0 | H89: =IFERROR((G89)/F89,0) -> 0
B90: April 31 | E90: ='Dividend Log'!AH106 -> 0 | G90: =C90-F90 -> 0 | H90: =IFERROR((G90)/F90,0) -> 0
B91: May 31 | E91: ='Dividend Log'!AH107 -> 0 | G91: =C91-F91 -> 0 | H91: =IFERROR((G91)/F91,0) -> 0
B92: June 31 | E92: ='Dividend Log'!AH108 -> 0 | G92: =C92-F92 -> 0 | H92: =IFERROR((G92)/F92,0) -> 0
B93: July 31 | E93: ='Dividend Log'!AH109 -> 0 | G93: =C93-F93 -> 0 | H93: =IFERROR((G93)/F93,0) -> 0
B94: August 31 | E94: ='Dividend Log'!AH110 -> 0 | G94: =C94-F94 -> 0 | H94: =IFERROR((G94)/F94,0) -> 0
B95: September 31 | E95: ='Dividend Log'!AH111 -> 0 | G95: =C95-F95 -> 0 | H95: =IFERROR((G95)/F95,0) -> 0
B96: October 31 | E96: ='Dividend Log'!AH112 -> 0 | G96: =C96-F96 -> 0 | H96: =IFERROR((G96)/F96,0) -> 0
B97: November 31 | E97: ='Dividend Log'!AH113 -> 0 | G97: =C97-F97 -> 0 | H97: =IFERROR((G97)/F97,0) -> 0
B98: December 31 | E98: ='Dividend Log'!AH114 -> 0 | G98: =C98-F98 -> 0 | H98: =IFERROR((G98)/F98,0) -> 0

Sheet Annual Data
B1: =Dashboard!B1 -> PORTFOLIO FIDELITY 2024 | G1: S&P500
B2: Portfolio Value | C2: Annual Contributions | D2: Dividend Income | E2: Dividend Yield | F2: Portfolio Yield (%) | G2: S&P500 Yield (%)
A3: Current | B3: =LOOKUP(1.E+308, B2:B9) -> 40306.351 | C3: =SUM(C4:C11) -> 33980 | D3: =SUM(D4:D11) -> 1006.99 | E3: =iferror(D3/C3,0) -> 0.029634785 | F3: =LOOKUP(1E+308, F4:F11) -> 0 | G3: =LOOKUP(1E+308, G4:G11) -> 0.1788
A4: 2024 | B4: =IFERROR(__xludf.DUMMYFUNCTION("IFerror(INDEX('Monthly Data '!C3:C14, MAX(FILTER(ROW('Monthly Data '!C3:C14) - ROW('Monthly Data '!C3) + 1, 'Monthly Data '!C3:C14 <> """"))),"""") "),14947.02) -> 14947.02 | C4: ='Monthly Data '!A2+sum('Monthly Data '!D3:D14) -> 14080 | D4: =SUM('Monthly Data '!E3:E14) -> 150.76 | E4: =iferror(D4/B4,0) -> 0.010086291 | F4: =IFERROR(__xludf.DUMMYFUNCTION("IFERROR( IF( COUNTIFS('Monthly Data '!B:B,""December ""&RIGHT(A4,2),'Monthly Data '!C:C,"""")>0, INDEX( FILTER('Monthly Data '!H:H, 'Monthly Data '!C:C<>"""", RIGHT('Monthly Data '!B:B,2)=RIGHT(A4,2) ), COUNTA( FILTER('Monthly "&"Data '!H:H, 'Monthly Data '!C:C<>"""", RIGHT('Monthly Data '!B:B,2)=RIGHT(A4,2) ) ) ), IF( COUNTIF('Monthly Data '!B:B,""December ""&RIGHT(A4-1,2))=0, INDEX(FILTER('Monthly Data '!H:H,'Monthly Data '!B:B=""December ""&RIGHT(A4,"&"2)),1), ((1+INDEX(FILTER('Monthly Data '!H:H,'Monthly Data '!B:B=""December ""&RIGHT(A4,2)),1)) / (1+INDEX(FILTER('Monthly Data '!H:H,'Monthly Data '!B:B=""December ""&RIGHT(A4-1,2)),1))) - 1 ) ) , """") "),0.06157812500000003) -> 0.061578125 | G4: 0.1085
A5: 2025 | B5: =IFERROR(__xludf.DUMMYFUNCTION("IFerror(INDEX('Monthly Data '!C15:C25, MAX(FILTER(ROW('Monthly Data '!C15:C25) - ROW('Monthly Data '!C15) + 1, 'Monthly Data '!C15:C25 <> """"))),"""") "),36036.33) -> 36036.33 | C5: =sum('Monthly Data '!D15:D26) -> 19500 | D5: =SUM('Monthly Data '!E15:E26) -> 735.44 | E5: =iferror(D5/B5,0) -> 0.020408294 | F5: =IFERROR(__xludf.DUMMYFUNCTION("IFERROR( IF( COUNTIFS('Monthly Data '!B:B,""December ""&RIGHT(A5,2),'Monthly Data '!C:C,"""")>0, INDEX( FILTER('Monthly Data '!H:H, 'Monthly Data '!C:C<>"""", RIGHT('Monthly Data '!B:B,2)=RIGHT(A5,2) ), COUNTA( FILTER('Monthly "&"Data '!H:H, 'Monthly Data '!C:C<>"""", RIGHT('Monthly Data '!B:B,2)=RIGHT(A5,2) ) ) ), IF( COUNTIF('Monthly Data '!B:B,""December ""&RIGHT(A5-1,2))=0, INDEX(FILTER('Monthly Data '!H:H,'Monthly Data '!B:B=""December ""&RIGHT(A5,"&"2)),1), ((1+INDEX(FILTER('Monthly Data '!H:H,'Monthly Data '!B:B=""December ""&RIGHT(A5,2)),1)) / (1+INDEX(FILTER('Monthly Data '!H:H,'Monthly Data '!B:B=""December ""&RIGHT(A5-1,2)),1))) - 1 ) ) , """") "),0.12054369003326904) -> 0.12054369 | G5: 0.1788
A6: 2026 | B6: =IFERROR(__xludf.DUMMYFUNCTION("IFERROR(INDEX('Monthly Data '!C27:C38, MAX(FILTER(ROW('Monthly Data '!C27:C38) - ROW('Monthly Data '!C27) + 1, 'Monthly Data '!C27:C38 <> """"))),"""") "),40306.35125) -> 40306.351 | C6: =Sum('Monthly Data '!D27:D38) -> 400 | D6: =SUM('Monthly Data '!E27:E38) -> 120.79 | E6: =iferror(D6/C6,0) -> 0.301975 | F6: =IFERROR(__xludf.DUMMYFUNCTION("IFERROR( IF( COUNTIFS('Monthly Data '!B:B,""December ""&RIGHT(A6,2),'Monthly Data '!C:C,"""")>0, INDEX( FILTER('Monthly Data '!H:H, 'Monthly Data '!C:C<>"""", RIGHT('Monthly Data '!B:B,2)=RIGHT(A6,2) ), COUNTA( FILTER('Monthly "&"Data '!H:H, 'Monthly Data '!C:C<>"""", RIGHT('Monthly Data '!B:B,2)=RIGHT(A6,2) ) ) ), IF( COUNTIF('Monthly Data '!B:B,""December ""&RIGHT(A6-1,2))=0, INDEX(FILTER('Monthly Data '!H:H,'Monthly Data '!B:B=""December ""&RIGHT(A6,"&"2)),1), ((1+INDEX(FILTER('Monthly Data '!H:H,'Monthly Data '!B:B=""December ""&RIGHT(A6,2)),1)) / (1+INDEX(FILTER('Monthly Data '!H:H,'Monthly Data '!B:B=""December ""&RIGHT(A6-1,2)),1))) - 1 ) ) , """") "),0.0) -> 0
A7: 2027 | B7: =IFERROR(__xludf.DUMMYFUNCTION("IFERROR(INDEX('Monthly Data '!C39:C50, MAX(FILTER(ROW('Monthly Data '!C39:C50) - ROW('Monthly Data '!C39) + 1, 'Monthly Data '!C39:C50 <> """"))),"""") "),"") | C7: =Sum('Monthly Data '!D39:D50) -> 0 | D7: =SUM('Monthly Data '!E39:E50) -> 0 | E7: =iferror(D7/C7,0) -> 0 | F7: =IFERROR(__xludf.DUMMYFUNCTION("IFERROR( IF( COUNTIFS('Monthly Data '!B:B,""December ""&RIGHT(A7,2),'Monthly Data '!C:C,"""")>0, INDEX( FILTER('Monthly Data '!H:H, 'Monthly Data '!C:C<>"""", RIGHT('Monthly Data '!B:B,2)=RIGHT(A7,2) ), COUNTA( FILTER('Monthly "&"Data '!H:H, 'Monthly Data '!C:C<>"""", RIGHT('Monthly Data '!B:B,2)=RIGHT(A7,2) ) ) ), IF( COUNTIF('Monthly Data '!B:B,""December ""&RIGHT(A7-1,2))=0, INDEX(FILTER('Monthly Data '!H:H,'Monthly Data '!B:B=""December ""&RIGHT(A7,"&"2)),1), ((1+INDEX(FILTER('Monthly Data '!H:H,'Monthly Data '!B:B=""December ""&RIGHT(A7,2)),1)) / (1+INDEX(FILTER('Monthly Data '!H:H,'Monthly Data '!B:B=""December ""&RIGHT(A7-1,2)),1))) - 1 ) ) , """") "),"")
A8: 2028 | B8: =IFERROR(__xludf.DUMMYFUNCTION("IFERROR(INDEX('Monthly Data '!C51:C62, MAX(FILTER(ROW('Monthly Data '!C51:C62) - ROW('Monthly Data '!C51) + 1, 'Monthly Data '!C51:C62 <> """"))),"""") "),"") | C8: =sum('Monthly Data '!D51:D62) -> 0 | D8: =SUM('Monthly Data '!E51:E62) -> 0 | E8: =iferror(D8/C8,0) -> 0 | F8: =IFERROR(__xludf.DUMMYFUNCTION("IFERROR( IF( COUNTIFS('Monthly Data '!B:B,""December ""&RIGHT(A8,2),'Monthly Data '!C:C,"""")>0, INDEX( FILTER('Monthly Data '!H:H, 'Monthly Data '!C:C<>"""", RIGHT('Monthly Data '!B:B,2)=RIGHT(A8,2) ), COUNTA( FILTER('Monthly "&"Data '!H:H, 'Monthly Data '!C:C<>"""", RIGHT('Monthly Data '!B:B,2)=RIGHT(A8,2) ) ) ), IF( COUNTIF('Monthly Data '!B:B,""December ""&RIGHT(A8-1,2))=0, INDEX(FILTER('Monthly Data '!H:H,'Monthly Data '!B:B=""December ""&RIGHT(A8,"&"2)),1), ((1+INDEX(FILTER('Monthly Data '!H:H,'Monthly Data '!B:B=""December ""&RIGHT(A8,2)),1)) / (1+INDEX(FILTER('Monthly Data '!H:H,'Monthly Data '!B:B=""December ""&RIGHT(A8-1,2)),1))) - 1 ) ) , """") "),"")
A9: 2029 | B9: =IFERROR(__xludf.DUMMYFUNCTION("IFERROR(INDEX('Monthly Data '!C63:C74, MAX(FILTER(ROW('Monthly Data '!C63:C74) - ROW('Monthly Data '!C63) + 1, 'Monthly Data '!C63:C74 <> """"))),"""") "),"") | C9: =SUM('Monthly Data '!D63:D74) -> 0 | D9: =SUM('Monthly Data '!E63:E74) -> 0 | E9: =iferror(D9/C9,0) -> 0 | F9: =IFERROR(__xludf.DUMMYFUNCTION("IFERROR( IF( COUNTIFS('Monthly Data '!B:B,""December ""&RIGHT(A9,2),'Monthly Data '!C:C,"""")>0, INDEX( FILTER('Monthly Data '!H:H, 'Monthly Data '!C:C<>"""", RIGHT('Monthly Data '!B:B,2)=RIGHT(A9,2) ), COUNTA( FILTER('Monthly "&"Data '!H:H, 'Monthly Data '!C:C<>"""", RIGHT('Monthly Data '!B:B,2)=RIGHT(A9,2) ) ) ), IF( COUNTIF('Monthly Data '!B:B,""December ""&RIGHT(A9-1,2))=0, INDEX(FILTER('Monthly Data '!H:H,'Monthly Data '!B:B=""December ""&RIGHT(A9,"&"2)),1), ((1+INDEX(FILTER('Monthly Data '!H:H,'Monthly Data '!B:B=""December ""&RIGHT(A9,2)),1)) / (1+INDEX(FILTER('Monthly Data '!H:H,'Monthly Data '!B:B=""December ""&RIGHT(A9-1,2)),1))) - 1 ) ) , """") "),"")
A10: 2030 | B10: =IFERROR(__xludf.DUMMYFUNCTION("IFERROR(INDEX('Monthly Data '!C75:C86, MAX(FILTER(ROW('Monthly Data '!C75:C86) - ROW('Monthly Data '!C75) + 1, 'Monthly Data '!C75:C86 <> """"))),"""") "),"") | C10: =SUM('Monthly Data '!D75:D86) -> 0 | D10: =SUM('Monthly Data '!E75:E86) -> 0 | E10: =iferror(D10/C10,0) -> 0 | F10: =IFERROR(__xludf.DUMMYFUNCTION("IFERROR( IF( COUNTIFS('Monthly Data '!B:B,""December ""&RIGHT(A10,2),'Monthly Data '!C:C,"""")>0, INDEX( FILTER('Monthly Data '!H:H, 'Monthly Data '!C:C<>"""", RIGHT('Monthly Data '!B:B,2)=RIGHT(A10,2) ), COUNTA( FILTER('Monthl"&"y Data '!H:H, 'Monthly Data '!C:C<>"""", RIGHT('Monthly Data '!B:B,2)=RIGHT(A10,2) ) ) ), IF( COUNTIF('Monthly Data '!B:B,""December ""&RIGHT(A10-1,2))=0, INDEX(FILTER('Monthly Data '!H:H,'Monthly Data '!B:B=""December ""&RIGHT"&"(A10,2)),1), ((1+INDEX(FILTER('Monthly Data '!H:H,'Monthly Data '!B:B=""December ""&RIGHT(A10,2)),1)) / (1+INDEX(FILTER('Monthly Data '!H:H,'Monthly Data '!B:B=""December ""&RIGHT(A10-1,2)),1))) - 1 ) ) , """") "),"")
A11: 2031 | B11: =IFERROR(__xludf.DUMMYFUNCTION("IFERROR(INDEX('Monthly Data '!C87:C98, MAX(FILTER(ROW('Monthly Data '!C87:C98) - ROW('Monthly Data '!C87) + 1, 'Monthly Data '!C87:C98 <> """"))),"""") "),"") | C11: =SUM('Monthly Data '!D87:D98) -> 0 | D11: =SUM('Monthly Data '!E87:E98) -> 0 | E11: =iferror(D11/C11,0) -> 0 | F11: =IFERROR(__xludf.DUMMYFUNCTION("IFERROR( IF( COUNTIFS('Monthly Data '!B:B,""December ""&RIGHT(A11,2),'Monthly Data '!C:C,"""")>0, INDEX( FILTER('Monthly Data '!H:H, 'Monthly Data '!C:C<>"""", RIGHT('Monthly Data '!B:B,2)=RIGHT(A11,2) ), COUNTA( FILTER('Monthl"&"y Data '!H:H, 'Monthly Data '!C:C<>"""", RIGHT('Monthly Data '!B:B,2)=RIGHT(A11,2) ) ) ), IF( COUNTIF('Monthly Data '!B:B,""December ""&RIGHT(A11-1,2))=0, INDEX(FILTER('Monthly Data '!H:H,'Monthly Data '!B:B=""December ""&RIGHT"&"(A11,2)),1), ((1+INDEX(FILTER('Monthly Data '!H:H,'Monthly Data '!B:B=""December ""&RIGHT(A11,2)),1)) / (1+INDEX(FILTER('Monthly Data '!H:H,'Monthly Data '!B:B=""December ""&RIGHT(A11-1,2)),1))) - 1 ) ) , """") "),"")
B15: https://finance.yahoo.com/quote/%5EGSPC/

Sheet Watchlist
A1: Ticker | B1: Company Name | C1: Share Price | D1: Intrinsic Value | E1: InvT SCore | F1: Priority | G1: Distance From Intrinsic | H1: Day Change / Share ($) | I1: Day Change / Share (%) | J1: 52 Week Low | K1: 52 Week Range | L1: 52 Week High | M1: Security Type | N1: Sector | O1: Category | P1: P/E Ratio | Q1: EPS | R1: Annual Dividend | S1: Dividend Yield | T1: Annual Income (100 Shares) | U1: How Much Invested For 100 Shares | V1: DO NOT DELETE | W1: Signal
A2: AAPL | B2: =IFERROR(__xludf.DUMMYFUNCTION("IF(ISBLANK(A2),"""", googlefinance(A2, ""name""))"),"Apple Inc") -> Apple Inc | C2: =IFERROR(__xludf.DUMMYFUNCTION("IF(ISBLANK(A2),"""", googlefinance(A2, ""price""))"),260.29) -> 260.29 | D2: =IF(ISBLANK(A2),"",IFERROR(VLOOKUP(A2, 'Intrinsic Values List'!$A$2:$D$70, 4, FALSE), "Not Found" )) -> 173.95 | E2: =IF(ISBLANK(A2),"",IFERROR(VLOOKUP(A2, 'Intrinsic Values List'!$A$2:$G$70, 7, FALSE), "Not Found" )) -> 8.1 | F2: High | G2: =IF(ISBLANK(D2),"", IFERROR((C2-D2)/D2,"")) -> 0.49634953 | H2: =IFERROR(__xludf.DUMMYFUNCTION("IFERROR(googlefinance(A2,""change""),"""")"),-2.23) -> -2.23 | I2: =IFERROR(__xludf.DUMMYFUNCTION("iferror(GOOGLEFINANCE(A2,""changepct"")/100,"""")"),-0.0085) -> -0.0085 | J2: =IFERROR(__xludf.DUMMYFUNCTION("IF(ISBLANK(A2),"""", googlefinance(A2, ""low52""))"),169.21) -> 169.21 | K2: =IFERROR(__xludf.DUMMYFUNCTION("IF(ISBLANK(A2),"""",IFERROR(SPARKLINE((C2-J2)/(L2-J2),{""charttype"",""bar"";""max"",1;""min"",0;""color1"",""2c79b5""}),""n/a""))"),"") | L2: =IFERROR(__xludf.DUMMYFUNCTION("IF(ISBLANK(A2),"""", googlefinance(A2, ""high52""))"),288.61) -> 288.61 | M2: Stocks | N2: Information Technology | O2: Growth | P2: =IFERROR(__xludf.DUMMYFUNCTION("IF(ISBLANK(A2),"""", googlefinance(A2, ""PE""))"),32.93) -> 32.93 | Q2: =IFERROR(__xludf.DUMMYFUNCTION("IF(ISBLANK(A2),"""", googlefinance(A2, ""eps""))"),7.9) -> 7.9 | R2: =IFERROR(__xludf.DUMMYFUNCTION("IfError(IF(isblank(A2),"""",split(V2, ""()"")))"),1.04) -> 1.04 | S2: =IFERROR(__xludf.DUMMYFUNCTION("""COMPUTED_VALUE"""),0.004) -> 0.004 | T2: =IF(ISBLANK(A2),"", (R2*100)) -> 104 | U2: =IF(ISBLANK(A2),"", C2*100) -> 26029 | V2: =IFERROR(__xludf.DUMMYFUNCTION("LET(t, A2, IF(t="""","""", IFERROR( SUBSTITUTE( INDEX( IMPORTXML( ""https://finviz.com/quote.ashx?t=""&t&""&ty=dv"", ""(//td[normalize-space()='Dividend TTM' or contains(.,'Dividend TTM')]/following-si"&"bling::td[1])[1]"" ),1,1), ""*"",""""), IFERROR( SUBSTITUTE( INDEX( IMPORTXML( ""https://finviz.com/quote.ashx?t=""&t, ""(//td[normalize-space()='Dividend']/following-sibling:"&":td[1])[1]"" ),1,1), ""*"",""""), """") ) ) ) "),"1.04 (0.40%)") -> 1.04 (0.40%) | W2: =IF(A2="", "", IF(G2<=-15%, "Strong Buy", IF(G2<0%, "Buy", IF(G2<=15%, "Expensive", "Overrated")))) -> Overrated
A3: V | B3: =IFERROR(__xludf.DUMMYFUNCTION("IF(ISBLANK(A3),"""", googlefinance(A3, ""name""))"),"Visa Inc") -> Visa Inc | C3: =IFERROR(__xludf.DUMMYFUNCTION("IF(ISBLANK(A3),"""", googlefinance(A3, ""price""))"),319.8) -> 319.8 | D3: =IF(ISBLANK(A3),"",IFERROR(VLOOKUP(A3, 'Intrinsic Values List'!$A$2:$D$70, 4, FALSE), "Not Found" )) -> 207.57 | E3: =IF(ISBLANK(A3),"",IFERROR(VLOOKUP(A3, 'Intrinsic Values List'!$A$2:$G$70, 7, FALSE), "Not Found" )) -> 8.71 | F3: Low | G3: =IF(ISBLANK(D3),"", IFERROR((C3-D3)/D3,"")) -> 0.54068507 | H3: =IFERROR(__xludf.DUMMYFUNCTION("IFERROR(googlefinance(A3,""change""),"""")"),-0.67) -> -0.67 | I3: =IFERROR(__xludf.DUMMYFUNCTION("iferror(GOOGLEFINANCE(A3,""changepct"")/100,"""")"),-0.0021) -> -0.0021 | J3: =IFERROR(__xludf.DUMMYFUNCTION("IF(ISBLANK(A3),"""", googlefinance(A3, ""low52""))"),299.0) -> 299 | K3: =IFERROR(__xludf.DUMMYFUNCTION("IF(ISBLANK(A3),"""",IFERROR(SPARKLINE((C3-J3)/(L3-J3),{""charttype"",""bar"";""max"",1;""min"",0;""color1"",""2c79b5""}),""n/a""))"),"") | L3: =IFERROR(__xludf.DUMMYFUNCTION("IF(ISBLANK(A3),"""", googlefinance(A3, ""high52""))"),375.51) -> 375.51 | M3: Stocks | N3: Financials | O3: Growth | P3: =IFERROR(__xludf.DUMMYFUNCTION("IF(ISBLANK(A3),"""", googlefinance(A3, ""PE""))"),30.01) -> 30.01 | Q3: =IFERROR(__xludf.DUMMYFUNCTION("IF(ISBLANK(A3),"""", googlefinance(A3, ""eps""))"),10.65) -> 10.65 | R3: =IFERROR(__xludf.DUMMYFUNCTION("IfError(IF(isblank(A3),"""",split(V3, ""()"")))"),2.52) -> 2.52 | S3: =IFERROR(__xludf.DUMMYFUNCTION("""COMPUTED_VALUE"""),0.0079) -> 0.0079 | T3: =IF(ISBLANK(A3),"", (R3*100)) -> 252 | U3: =IF(ISBLANK(A3),"", C3*100) -> 31980 | V3: =IFERROR(__xludf.DUMMYFUNCTION("LET(t, A3, IF(t="""","""", IFERROR( SUBSTITUTE( INDEX( IMPORTXML( ""https://finviz.com/quote.ashx?t=""&t&""&ty=dv"", ""(//td[normalize-space()='Dividend TTM' or contains(.,'Dividend TTM')]/following-si"&"bling::td[1])[1]"" ),1,1), ""*"",""""), IFERROR( SUBSTITUTE( INDEX( IMPORTXML( ""https://finviz.com/quote.ashx?t=""&t, ""(//td[normalize-space()='Dividend']/following-sibling:"&":td[1])[1]"" ),1,1), ""*"",""""), """") ) ) ) "),"2.52 (0.79%)") -> 2.52 (0.79%) | W3: =IF(A3="", "", IF(G3<=-15%, "Strong Buy", IF(G3<0%, "Buy", IF(G3<=15%, "Expensive", "Overrated")))) -> Overrated
A4: PEP | B4: =IFERROR(__xludf.DUMMYFUNCTION("IF(ISBLANK(A4),"""", googlefinance(A4, ""name""))"),"PepsiCo Inc") -> PepsiCo Inc | C4: =IFERROR(__xludf.DUMMYFUNCTION("IF(ISBLANK(A4),"""", googlefinance(A4, ""price""))"),160.7) -> 160.7 | D4: =IF(ISBLANK(A4),"",IFERROR(VLOOKUP(A4, 'Intrinsic Values List'!$A$2:$D$70, 4, FALSE), "Not Found" )) -> 120.16 | E4: =IF(ISBLANK(A4),"",IFERROR(VLOOKUP(A4, 'Intrinsic Values List'!$A$2:$G$70, 7, FALSE), "Not Found" )) -> 5.99 | F4: Low | G4: =IF(ISBLANK(D4),"", IFERROR((C4-D4)/D4,"")) -> 0.33738349 | H4: =IFERROR(__xludf.DUMMYFUNCTION("IFERROR(googlefinance(A4,""change""),"""")"),-3.22) -> -3.22 | I4: =IFERROR(__xludf.DUMMYFUNCTION("iferror(GOOGLEFINANCE(A4,""changepct"")/100,"""")"),-0.0196) -> -0.0196 | J4: =IFERROR(__xludf.DUMMYFUNCTION("IF(ISBLANK(A4),"""", googlefinance(A4, ""low52""))"),127.6) -> 127.6 | K4: =IFERROR(__xludf.DUMMYFUNCTION("IF(ISBLANK(A4),"""",IFERROR(SPARKLINE((C4-J4)/(L4-J4),{""charttype"",""bar"";""max"",1;""min"",0;""color1"",""2c79b5""}),""n/a""))"),"") | L4: =IFERROR(__xludf.DUMMYFUNCTION("IF(ISBLANK(A4),"""", googlefinance(A4, ""high52""))"),171.48) -> 171.48 | M4: Stocks | N4: Consumer Staples | O4: Value Stocks | P4: =IFERROR(__xludf.DUMMYFUNCTION("IF(ISBLANK(A4),"""", googlefinance(A4, ""PE""))"),26.78) -> 26.78 | Q4: =IFERROR(__xludf.DUMMYFUNCTION("IF(ISBLANK(A4),"""", googlefinance(A4, ""eps""))"),6.0) -> 6 | R4: =IFERROR(__xludf.DUMMYFUNCTION("IfError(IF(isblank(A4),"""",split(V4, ""()"")))"),5.62) -> 5.62 | S4: =IFERROR(__xludf.DUMMYFUNCTION("""COMPUTED_VALUE"""),0.035) -> 0.035 | T4: =IF(ISBLANK(A4),"", (R4*100)) -> 562 | U4: =IF(ISBLANK(A4),"", C4*100) -> 16070 | V4: =IFERROR(__xludf.DUMMYFUNCTION("LET(t, A4, IF(t="""","""", IFERROR( SUBSTITUTE( INDEX( IMPORTXML( ""https://finviz.com/quote.ashx?t=""&t&""&ty=dv"", ""(//td[normalize-space()='Dividend TTM' or contains(.,'Dividend TTM')]/following-si"&"bling::td[1])[1]"" ),1,1), ""*"",""""), IFERROR( SUBSTITUTE( INDEX( IMPORTXML( ""https://finviz.com/quote.ashx?t=""&t, ""(//td[normalize-space()='Dividend']/following-sibling:"&":td[1])[1]"" ),1,1), ""*"",""""), """") ) ) ) "),"5.62 (3.50%)") -> 5.62 (3.50%) | W4: =IF(A4="", "", IF(G4<=-15%, "Strong Buy", IF(G4<0%, "Buy", IF(G4<=15%, "Expensive", "Overrated")))) -> Overrated
A5: MO | B5: =IFERROR(__xludf.DUMMYFUNCTION("IF(ISBLANK(A5),"""", googlefinance(A5, ""name""))"),"Altria Group Inc") -> Altria Group Inc | C5: =IFERROR(__xludf.DUMMYFUNCTION("IF(ISBLANK(A5),"""", googlefinance(A5, ""price""))"),66.98) -> 66.98 | D5: =IF(ISBLANK(A5),"",IFERROR(VLOOKUP(A5, 'Intrinsic Values List'!$A$2:$D$70, 4, FALSE), "Not Found" )) -> 94.06 | E5: =IF(ISBLANK(A5),"",IFERROR(VLOOKUP(A5, 'Intrinsic Values List'!$A$2:$G$70, 7, FALSE), "Not Found" )) -> 6.26 | F5: Low | G5: =IF(ISBLANK(D5),"", IFERROR((C5-D5)/D5,"")) -> -0.28790134 | H5: =IFERROR(__xludf.DUMMYFUNCTION("IFERROR(googlefinance(A5,""change""),"""")"),-1.14) -> -1.14 | I5: =IFERROR(__xludf.DUMMYFUNCTION("iferror(GOOGLEFINANCE(A5,""changepct"")/100,"""")"),-0.0166) -> -0.0166 | J5: =IFERROR(__xludf.DUMMYFUNCTION("IF(ISBLANK(A5),"""", googlefinance(A5, ""low52""))"),52.82) -> 52.82 | K5: =IFERROR(__xludf.DUMMYFUNCTION("IF(ISBLANK(A5),"""",IFERROR(SPARKLINE((C5-J5)/(L5-J5),{""charttype"",""bar"";""max"",1;""min"",0;""color1"",""2c79b5""}),""n/a""))"),"") | L5: =IFERROR(__xludf.DUMMYFUNCTION("IF(ISBLANK(A5),"""", googlefinance(A5, ""high52""))"),70.51) -> 70.51 | M5: Stocks | N5: Consumer Staples | O5: Value Stocks | P5: =IFERROR(__xludf.DUMMYFUNCTION("IF(ISBLANK(A5),"""", googlefinance(A5, ""PE""))"),16.27) -> 16.27 | Q5: =IFERROR(__xludf.DUMMYFUNCTION("IF(ISBLANK(A5),"""", googlefinance(A5, ""eps""))"),4.12) -> 4.12 | R5: =IFERROR(__xludf.DUMMYFUNCTION("IfError(IF(isblank(A5),"""",split(V5, ""()"")))"),4.16) -> 4.16 | S5: =IFERROR(__xludf.DUMMYFUNCTION("""COMPUTED_VALUE"""),0.0621) -> 0.0621 | T5: =IF(ISBLANK(A5),"", (R5*100)) -> 416 | U5: =IF(ISBLANK(A5),"", C5*100) -> 6698 | V5: =IFERROR(__xludf.DUMMYFUNCTION("LET(t, A5, IF(t="""","""", IFERROR( SUBSTITUTE( INDEX( IMPORTXML( ""https://finviz.com/quote.ashx?t=""&t&""&ty=dv"", ""(//td[normalize-space()='Dividend TTM' or contains(.,'Dividend TTM')]/following-si"&"bling::td[1])[1]"" ),1,1), ""*"",""""), IFERROR( SUBSTITUTE( INDEX( IMPORTXML( ""https://finviz.com/quote.ashx?t=""&t, ""(//td[normalize-space()='Dividend']/following-sibling:"&":td[1])[1]"" ),1,1), ""*"",""""), """") ) ) ) "),"4.16 (6.21%)") -> 4.16 (6.21%) | W5: =IF(A5="", "", IF(G5<=-15%, "Strong Buy", IF(G5<0%, "Buy", IF(G5<=15%, "Expensive", "Overrated")))) -> Strong Buy
A6: ABBV | B6: =IFERROR(__xludf.DUMMYFUNCTION("IF(ISBLANK(A6),"""", googlefinance(A6, ""name""))"),"AbbVie Common Stock") -> AbbVie Common Stock | C6: =IFERROR(__xludf.DUMMYFUNCTION("IF(ISBLANK(A6),"""", googlefinance(A6, ""price""))"),232.35) -> 232.35 | D6: =IF(ISBLANK(A6),"",IFERROR(VLOOKUP(A6, 'Intrinsic Values List'!$A$2:$D$70, 4, FALSE), "Not Found" )) -> 124.34 | E6: =IF(ISBLANK(A6),"",IFERROR(VLOOKUP(A6, 'Intrinsic Values List'!$A$2:$G$70, 7, FALSE), "Not Found" )) -> 5.34 | F6: High | G6: =IF(ISBLANK(D6),"", IFERROR((C6-D6)/D6,"")) -> 0.86866656 | H6: =IFERROR(__xludf.DUMMYFUNCTION("IFERROR(googlefinance(A6,""change""),"""")"),-3.84) -> -3.84 | I6: =IFERROR(__xludf.DUMMYFUNCTION("iferror(GOOGLEFINANCE(A6,""changepct"")/100,"""")"),-0.0163) -> -0.0163 | J6: =IFERROR(__xludf.DUMMYFUNCTION("IF(ISBLANK(A6),"""", googlefinance(A6, ""low52""))"),164.39) -> 164.39 | K6: =IFERROR(__xludf.DUMMYFUNCTION("IF(ISBLANK(A6),"""",IFERROR(SPARKLINE((C6-J6)/(L6-J6),{""charttype"",""bar"";""max"",1;""min"",0;""color1"",""2c79b5""}),""n/a""))"),"") | L6: =IFERROR(__xludf.DUMMYFUNCTION("IF(ISBLANK(A6),"""", googlefinance(A6, ""high52""))"),244.81) -> 244.81 | M6: Stocks | N6: Health Care | O6: Value Stocks | P6: =IFERROR(__xludf.DUMMYFUNCTION("IF(ISBLANK(A6),"""", googlefinance(A6, ""PE""))"),98.41) -> 98.41 | Q6: =IFERROR(__xludf.DUMMYFUNCTION("IF(ISBLANK(A6),"""", googlefinance(A6, ""eps""))"),2.36) -> 2.36 | R6: =IFERROR(__xludf.DUMMYFUNCTION("IfError(IF(isblank(A6),"""",split(V6, ""()"")))"),6.65) -> 6.65 | S6: =IFERROR(__xludf.DUMMYFUNCTION("""COMPUTED_VALUE"""),0.0286) -> 0.0286 | T6: =IF(ISBLANK(A6),"", (R6*100)) -> 665 | U6: =IF(ISBLANK(A6),"", C6*100) -> 23235 | V6: =IFERROR(__xludf.DUMMYFUNCTION("LET(t, A6, IF(t="""","""", IFERROR( SUBSTITUTE( INDEX( IMPORTXML( ""https://finviz.com/quote.ashx?t=""&t&""&ty=dv"", ""(//td[normalize-space()='Dividend TTM' or contains(.,'Dividend TTM')]/following-si"&"bling::td[1])[1]"" ),1,1), ""*"",""""), IFERROR( SUBSTITUTE( INDEX( IMPORTXML( ""https://finviz.com/quote.ashx?t=""&t, ""(//td[normalize-space()='Dividend']/following-sibling:"&":td[1])[1]"" ),1,1), ""*"",""""), """") ) ) ) "),"6.65 (2.86%)") -> 6.65 (2.86%) | W6: =IF(A6="", "", IF(G6<=-15%, "Strong Buy", IF(G6<0%, "Buy", IF(G6<=15%, "Expensive", "Overrated")))) -> Overrated
A7: JNJ | B7: =IFERROR(__xludf.DUMMYFUNCTION("IF(ISBLANK(A7),"""", googlefinance(A7, ""name""))"),"Johnson & Johnson") -> Johnson & Johnson | C7: =IFERROR(__xludf.DUMMYFUNCTION("IF(ISBLANK(A7),"""", googlefinance(A7, ""price""))"),239.63) -> 239.63 | D7: =IF(ISBLANK(A7),"",IFERROR(VLOOKUP(A7, 'Intrinsic Values List'!$A$2:$D$70, 4, FALSE), "Not Found" )) -> 148.99 | E7: =IF(ISBLANK(A7),"",IFERROR(VLOOKUP(A7, 'Intrinsic Values List'!$A$2:$G$70, 7, FALSE), "Not Found" )) -> 7.25 | F7: High | G7: =IF(ISBLANK(D7),"", IFERROR((C7-D7)/D7,"")) -> 0.60836298 | H7: =IFERROR(__xludf.DUMMYFUNCTION("IFERROR(googlefinance(A7,""change""),"""")"),-5.67) -> -5.67 | I7: =IFERROR(__xludf.DUMMYFUNCTION("iferror(GOOGLEFINANCE(A7,""changepct"")/100,"""")"),-0.023) -> -0.023 | J7: =IFERROR(__xludf.DUMMYFUNCTION("IF(ISBLANK(A7),"""", googlefinance(A7, ""low52""))"),141.5) -> 141.5 | K7: =IFERROR(__xludf.DUMMYFUNCTION("IF(ISBLANK(A7),"""",IFERROR(SPARKLINE((C7-J7)/(L7-J7),{""charttype"",""bar"";""max"",1;""min"",0;""color1"",""2c79b5""}),""n/a""))"),"") | L7: =IFERROR(__xludf.DUMMYFUNCTION("IF(ISBLANK(A7),"""", googlefinance(A7, ""high52""))"),251.71) -> 251.71 | M7: Stocks | N7: Health Care | O7: Value Stocks | P7: =IFERROR(__xludf.DUMMYFUNCTION("IF(ISBLANK(A7),"""", googlefinance(A7, ""PE""))"),20.94) -> 20.94 | Q7: =IFERROR(__xludf.DUMMYFUNCTION("IF(ISBLANK(A7),"""", googlefinance(A7, ""eps""))"),11.44) -> 11.44 | R7: =IFERROR(__xludf.DUMMYFUNCTION("IfError(IF(isblank(A7),"""",split(V7, ""()"")))"),5.2) -> 5.2 | S7: =IFERROR(__xludf.DUMMYFUNCTION("""COMPUTED_VALUE"""),0.0217) -> 0.0217 | T7: =IF(ISBLANK(A7),"", (R7*100)) -> 520 | U7: =IF(ISBLANK(A7),"", C7*100) -> 23963 | V7: =IFERROR(__xludf.DUMMYFUNCTION("LET(t, A7, IF(t="""","""", IFERROR( SUBSTITUTE( INDEX( IMPORTXML( ""https://finviz.com/quote.ashx?t=""&t&""&ty=dv"", ""(//td[normalize-space()='Dividend TTM' or contains(.,'Dividend TTM')]/following-si"&"bling::td[1])[1]"" ),1,1), ""*"",""""), IFERROR( SUBSTITUTE( INDEX( IMPORTXML( ""https://finviz.com/quote.ashx?t=""&t, ""(//td[normalize-space()='Dividend']/following-sibling:"&":td[1])[1]"" ),1,1), ""*"",""""), """") ) ) ) "),"5.20 (2.17%)") -> 5.20 (2.17%) | W7: =IF(A7="", "", IF(G7<=-15%, "Strong Buy", IF(G7<0%, "Buy", IF(G7<=15%, "Expensive", "Overrated")))) -> Overrated
A8: COST | B8: =IFERROR(__xludf.DUMMYFUNCTION("IF(ISBLANK(A8),"""", googlefinance(A8, ""name""))"),"Costco Wholesale Corp") -> Costco Wholesale Corp | C8: =IFERROR(__xludf.DUMMYFUNCTION("IF(ISBLANK(A8),"""", googlefinance(A8, ""price""))"),982.57) -> 982.57 | D8: =IF(ISBLANK(A8),"",IFERROR(VLOOKUP(A8, 'Intrinsic Values List'!$A$2:$D$70, 4, FALSE), "Not Found" )) -> 426.65 | E8: =IF(ISBLANK(A8),"",IFERROR(VLOOKUP(A8, 'Intrinsic Values List'!$A$2:$G$70, 7, FALSE), "Not Found" )) -> 6.36 | F8: Low | G8: =IF(ISBLANK(D8),"", IFERROR((C8-D8)/D8,"")) -> 1.3029884 | H8: =IFERROR(__xludf.DUMMYFUNCTION("IFERROR(googlefinance(A8,""change""),"""")"),-24.17) -> -24.17 | I8: =IFERROR(__xludf.DUMMYFUNCTION("iferror(GOOGLEFINANCE(A8,""changepct"")/100,"""")"),-0.024) -> -0.024 | J8: =IFERROR(__xludf.DUMMYFUNCTION("IF(ISBLANK(A8),"""", googlefinance(A8, ""low52""))"),844.06) -> 844.06 | K8: =IFERROR(__xludf.DUMMYFUNCTION("IF(ISBLANK(A8),"""",IFERROR(SPARKLINE((C8-J8)/(L8-J8),{""charttype"",""bar"";""max"",1;""min"",0;""color1"",""2c79b5""}),""n/a""))"),"") | L8: =IFERROR(__xludf.DUMMYFUNCTION("IF(ISBLANK(A8),"""", googlefinance(A8, ""high52""))"),1067.08) -> 1067.08 | M8: Stocks | N8: Consumer Staples | O8: Growth | P8: =IFERROR(__xludf.DUMMYFUNCTION("IF(ISBLANK(A8),"""", googlefinance(A8, ""PE""))"),52.63) -> 52.63 | Q8: =IFERROR(__xludf.DUMMYFUNCTION("IF(ISBLANK(A8),"""", googlefinance(A8, ""eps""))"),18.67) -> 18.67 | R8: =IFERROR(__xludf.DUMMYFUNCTION("IfError(IF(isblank(A8),"""",split(V8, ""()"")))"),5.2) -> 5.2 | S8: =IFERROR(__xludf.DUMMYFUNCTION("""COMPUTED_VALUE"""),0.0053) -> 0.0053 | T8: =IF(ISBLANK(A8),"", (R8*100)) -> 520 | U8: =IF(ISBLANK(A8),"", C8*100) -> 98257 | V8: =IFERROR(__xludf.DUMMYFUNCTION("LET(t, A8, IF(t="""","""", IFERROR( SUBSTITUTE( INDEX( IMPORTXML( ""https://finviz.com/quote.ashx?t=""&t&""&ty=dv"", ""(//td[normalize-space()='Dividend TTM' or contains(.,'Dividend TTM')]/following-si"&"bling::td[1])[1]"" ),1,1), ""*"",""""), IFERROR( SUBSTITUTE( INDEX( IMPORTXML( ""https://finviz.com/quote.ashx?t=""&t, ""(//td[normalize-space()='Dividend']/following-sibling:"&":td[1])[1]"" ),1,1), ""*"",""""), """") ) ) ) "),"5.20 (0.53%)") -> 5.20 (0.53%) | W8: =IF(A8="", "", IF(G8<=-15%, "Strong Buy", IF(G8<0%, "Buy", IF(G8<=15%, "Expensive", "Overrated")))) -> Overrated
A9: TXRH | B9: =IFERROR(__xludf.DUMMYFUNCTION("IF(ISBLANK(A9),"""", googlefinance(A9, ""name""))"),"Texas Roadhouse Inc") -> Texas Roadhouse Inc | C9: =IFERROR(__xludf.DUMMYFUNCTION("IF(ISBLANK(A9),"""", googlefinance(A9, ""price""))"),175.04) -> 175.04 | D9: =IF(ISBLANK(A9),"",IFERROR(VLOOKUP(A9, 'Intrinsic Values List'!$A$2:$D$70, 4, FALSE), "Not Found" )) -> 142.76 | E9: =IF(ISBLANK(A9),"",IFERROR(VLOOKUP(A9, 'Intrinsic Values List'!$A$2:$G$70, 7, FALSE), "Not Found" )) -> 7.16 | F9: Low | G9: =IF(ISBLANK(D9),"", IFERROR((C9-D9)/D9,"")) -> 0.22611376 | H9: =IFERROR(__xludf.DUMMYFUNCTION("IFERROR(googlefinance(A9,""change""),"""")"),-3.66) -> -3.66 | I9: =IFERROR(__xludf.DUMMYFUNCTION("iferror(GOOGLEFINANCE(A9,""changepct"")/100,"""")"),-0.020499999999999997) -> -0.0205 | J9: =IFERROR(__xludf.DUMMYFUNCTION("IF(ISBLANK(A9),"""", googlefinance(A9, ""low52""))"),148.73) -> 148.73 | K9: =IFERROR(__xludf.DUMMYFUNCTION("IF(ISBLANK(A9),"""",IFERROR(SPARKLINE((C9-J9)/(L9-J9),{""charttype"",""bar"";""max"",1;""min"",0;""color1"",""2c79b5""}),""n/a""))"),"") | L9: =IFERROR(__xludf.DUMMYFUNCTION("IF(ISBLANK(A9),"""", googlefinance(A9, ""high52""))"),199.99) -> 199.99 | M9: Stocks | N9: Consumer Discretionary | O9: Value Stocks | P9: =IFERROR(__xludf.DUMMYFUNCTION("IF(ISBLANK(A9),"""", googlefinance(A9, ""PE""))"),28.71) -> 28.71 | Q9: =IFERROR(__xludf.DUMMYFUNCTION("IF(ISBLANK(A9),"""", googlefinance(A9, ""eps""))"),6.1) -> 6.1 | R9: =IFERROR(__xludf.DUMMYFUNCTION("IfError(IF(isblank(A9),"""",split(V9, ""()"")))"),2.72) -> 2.72 | S9: =IFERROR(__xludf.DUMMYFUNCTION("""COMPUTED_VALUE"""),0.0155) -> 0.0155 | T9: =IF(ISBLANK(A9),"", (R9*100)) -> 272 | U9: =IF(ISBLANK(A9),"", C9*100) -> 17504 | V9: =IFERROR(__xludf.DUMMYFUNCTION("LET(t, A9, IF(t="""","""", IFERROR( SUBSTITUTE( INDEX( IMPORTXML( ""https://finviz.com/quote.ashx?t=""&t&""&ty=dv"", ""(//td[normalize-space()='Dividend TTM' or contains(.,'Dividend TTM')]/following-si"&"bling::td[1])[1]"" ),1,1), ""*"",""""), IFERROR( SUBSTITUTE( INDEX( IMPORTXML( ""https://finviz.com/quote.ashx?t=""&t, ""(//td[normalize-space()='Dividend']/following-sibling:"&":td[1])[1]"" ),1,1), ""*"",""""), """") ) ) ) "),"2.72 (1.55%)") -> 2.72 (1.55%) | W9: =IF(A9="", "", IF(G9<=-15%, "Strong Buy", IF(G9<0%, "Buy", IF(G9<=15%, "Expensive", "Overrated")))) -> Overrated
A10: CMG | B10: =IFERROR(__xludf.DUMMYFUNCTION("IF(ISBLANK(A10),"""", googlefinance(A10, ""name""))"),"Chipotle Mexican Grill Inc") -> Chipotle Mexican Grill Inc | C10: =IFERROR(__xludf.DUMMYFUNCTION("IF(ISBLANK(A10),"""", googlefinance(A10, ""price""))"),37.06) -> 37.06 | D10: =IF(ISBLANK(A10),"",IFERROR(VLOOKUP(A10, 'Intrinsic Values List'!$A$2:$D$70, 4, FALSE), "Not Found" )) -> 28.31 | E10: =IF(ISBLANK(A10),"",IFERROR(VLOOKUP(A10, 'Intrinsic Values List'!$A$2:$G$70, 7, FALSE), "Not Found" )) -> 5.91 | F10: Low | G10: =IF(ISBLANK(D10),"", IFERROR((C10-D10)/D10,"")) -> 0.30907806 | H10: =IFERROR(__xludf.DUMMYFUNCTION("IFERROR(googlefinance(A10,""change""),"""")"),0.35) -> 0.35 | I10: =IFERROR(__xludf.DUMMYFUNCTION("iferror(GOOGLEFINANCE(A10,""changepct"")/100,"""")"),0.0095) -> 0.0095 | J10: =IFERROR(__xludf.DUMMYFUNCTION("IF(ISBLANK(A10),"""", googlefinance(A10, ""low52""))"),29.75) -> 29.75 | K10: =IFERROR(__xludf.DUMMYFUNCTION("IF(ISBLANK(A10),"""",IFERROR(SPARKLINE((C10-J10)/(L10-J10),{""charttype"",""bar"";""max"",1;""min"",0;""color1"",""2c79b5""}),""n/a""))"),"") | L10: =IFERROR(__xludf.DUMMYFUNCTION("IF(ISBLANK(A10),"""", googlefinance(A10, ""high52""))"),58.42) -> 58.42 | M10: Stocks | N10: Consumer Discretionary | O10: Growth | P10: =IFERROR(__xludf.DUMMYFUNCTION("IF(ISBLANK(A10),"""", googlefinance(A10, ""PE""))"),32.4) -> 32.4 | Q10: =IFERROR(__xludf.DUMMYFUNCTION("IF(ISBLANK(A10),"""", googlefinance(A10, ""eps""))"),1.14) -> 1.14 | R10: =IFERROR(__xludf.DUMMYFUNCTION("IfError(IF(isblank(A10),"""",split(V10, ""()"")))"),"-") -> - | T10: =IF(ISBLANK(A10),"", (R10*100)) -> #VALUE! | U10: =IF(ISBLANK(A10),"", C10*100) -> 3706 | V10: =IFERROR(__xludf.DUMMYFUNCTION("LET(t, A10, IF(t="""","""", IFERROR( SUBSTITUTE( INDEX( IMPORTXML( ""https://finviz.com/quote.ashx?t=""&t&""&ty=dv"", ""(//td[normalize-space()='Dividend TTM' or contains(.,'Dividend TTM')]/following-s"&"ibling::td[1])[1]"" ),1,1), ""*"",""""), IFERROR( SUBSTITUTE( INDEX( IMPORTXML( ""https://finviz.com/quote.ashx?t=""&t, ""(//td[normalize-space()='Dividend']/following-sibling"&"::td[1])[1]"" ),1,1), ""*"",""""), """") ) ) ) "),"-") -> - | W10: =IF(A10="", "", IF(G10<=-15%, "Strong Buy", IF(G10<0%, "Buy", IF(G10<=15%, "Expensive", "Overrated")))) -> Overrated
A11: STZ | B11: =IFERROR(__xludf.DUMMYFUNCTION("IF(ISBLANK(A11),"""", googlefinance(A11, ""name""))"),"Constellation Brands Inc") -> Constellation Brands Inc | C11: =IFERROR(__xludf.DUMMYFUNCTION("IF(ISBLANK(A11),"""", googlefinance(A11, ""price""))"),147.3) -> 147.3 | D11: =IF(ISBLANK(A11),"",IFERROR(VLOOKUP(A11, 'Intrinsic Values List'!$A$2:$D$70, 4, FALSE), "Not Found" )) -> 140.38782 | E11: =IF(ISBLANK(A11),"",IFERROR(VLOOKUP(A11, 'Intrinsic Values List'!$A$2:$G$70, 7, FALSE), "Not Found" )) -> 4.75 | F11: Low | G11: =IF(ISBLANK(D11),"", IFERROR((C11-D11)/D11,"")) -> 0.049236289 | H11: =IFERROR(__xludf.DUMMYFUNCTION("IFERROR(googlefinance(A11,""change""),"""")"),-3.94) -> -3.94 | I11: =IFERROR(__xludf.DUMMYFUNCTION("iferror(GOOGLEFINANCE(A11,""changepct"")/100,"""")"),-0.026099999999999998) -> -0.0261 | J11: =IFERROR(__xludf.DUMMYFUNCTION("IF(ISBLANK(A11),"""", googlefinance(A11, ""low52""))"),126.45) -> 126.45 | K11: =IFERROR(__xludf.DUMMYFUNCTION("IF(ISBLANK(A11),"""",IFERROR(SPARKLINE((C11-J11)/(L11-J11),{""charttype"",""bar"";""max"",1;""min"",0;""color1"",""2c79b5""}),""n/a""))"),"") | L11: =IFERROR(__xludf.DUMMYFUNCTION("IF(ISBLANK(A11),"""", googlefinance(A11, ""high52""))"),196.91) -> 196.91 | M11: Stocks | N11: Consumer Staples | O11: Growth | P11: =IFERROR(__xludf.DUMMYFUNCTION("IF(ISBLANK(A11),"""", googlefinance(A11, ""PE""))"),23.23) -> 23.23 | Q11: =IFERROR(__xludf.DUMMYFUNCTION("IF(ISBLANK(A11),"""", googlefinance(A11, ""eps""))"),6.34) -> 6.34 | R11: =IFERROR(__xludf.DUMMYFUNCTION("IfError(IF(isblank(A11),"""",split(V11, ""()"")))"),4.08) -> 4.08 | S11: =IFERROR(__xludf.DUMMYFUNCTION("""COMPUTED_VALUE"""),0.0277) -> 0.0277 | T11: =IF(ISBLANK(A11),"", (R11*100)) -> 408 | U11: =IF(ISBLANK(A11),"", C11*100) -> 14730 | V11: =IFERROR(__xludf.DUMMYFUNCTION("LET(t, A11, IF(t="""","""", IFERROR( SUBSTITUTE( INDEX( IMPORTXML( ""https://finviz.com/quote.ashx?t=""&t&""&ty=dv"", ""(//td[normalize-space()='Dividend TTM' or contains(.,'Dividend TTM')]/following-s"&"ibling::td[1])[1]"" ),1,1), ""*"",""""), IFERROR( SUBSTITUTE( INDEX( IMPORTXML( ""https://finviz.com/quote.ashx?t=""&t, ""(//td[normalize-space()='Dividend']/following-sibling"&"::td[1])[1]"" ),1,1), ""*"",""""), """") ) ) ) "),"4.08 (2.77%)") -> 4.08 (2.77%) | W11: =IF(A11="", "", IF(G11<=-15%, "Strong Buy", IF(G11<0%, "Buy", IF(G11<=15%, "Expensive", "Overrated")))) -> Expensive
A12: CMCSA | B12: =IFERROR(__xludf.DUMMYFUNCTION("IF(ISBLANK(A12),"""", googlefinance(A12, ""name""))"),"Comcast Corp") -> Comcast Corp | C12: =IFERROR(__xludf.DUMMYFUNCTION("IF(ISBLANK(A12),"""", googlefinance(A12, ""price""))"),31.6) -> 31.6 | D12: =IF(ISBLANK(A12),"",IFERROR(VLOOKUP(A12, 'Intrinsic Values List'!$A$2:$D$70, 4, FALSE), "Not Found" )) -> 60.23 | E12: =IF(ISBLANK(A12),"",IFERROR(VLOOKUP(A12, 'Intrinsic Values List'!$A$2:$G$70, 7, FALSE), "Not Found" )) -> 6.33 | F12: Low | G12: =IF(ISBLANK(D12),"", IFERROR((C12-D12)/D12,"")) -> -0.47534451 | H12: =IFERROR(__xludf.DUMMYFUNCTION("IFERROR(googlefinance(A12,""change""),"""")"),-0.49) -> -0.49 | I12: =IFERROR(__xludf.DUMMYFUNCTION("iferror(GOOGLEFINANCE(A12,""changepct"")/100,"""")"),-0.015300000000000001) -> -0.0153 | J12: =IFERROR(__xludf.DUMMYFUNCTION("IF(ISBLANK(A12),"""", googlefinance(A12, ""low52""))"),24.12) -> 24.12 | K12: =IFERROR(__xludf.DUMMYFUNCTION("IF(ISBLANK(A12),"""",IFERROR(SPARKLINE((C12-J12)/(L12-J12),{""charttype"",""bar"";""max"",1;""min"",0;""color1"",""2c79b5""}),""n/a""))"),"") | L12: =IFERROR(__xludf.DUMMYFUNCTION("IF(ISBLANK(A12),"""", googlefinance(A12, ""high52""))"),35.58) -> 35.58 | M12: Stocks | N12: Communication Services | O12: Value Stocks | P12: =IFERROR(__xludf.DUMMYFUNCTION("IF(ISBLANK(A12),"""", googlefinance(A12, ""PE""))"),5.86) -> 5.86 | Q12: =IFERROR(__xludf.DUMMYFUNCTION("IF(ISBLANK(A12),"""", googlefinance(A12, ""eps""))"),5.39) -> 5.39 | R12: =IFERROR(__xludf.DUMMYFUNCTION("IfError(IF(isblank(A12),"""",split(V12, ""()"")))"),"") | T12: =IF(ISBLANK(A12),"", (R12*100)) -> 0 | U12: =IF(ISBLANK(A12),"", C12*100) -> 3160 | V12: =IFERROR(__xludf.DUMMYFUNCTION("LET(t, A12, IF(t="""","""", IFERROR( SUBSTITUTE( INDEX( IMPORTXML( ""https://finviz.com/quote.ashx?t=""&t&""&ty=dv"", ""(//td[normalize-space()='Dividend TTM' or contains(.,'Dividend TTM')]/following-s"&"ibling::td[1])[1]"" ),1,1), ""*"",""""), IFERROR( SUBSTITUTE( INDEX( IMPORTXML( ""https://finviz.com/quote.ashx?t=""&t, ""(//td[normalize-space()='Dividend']/following-sibling"&"::td[1])[1]"" ),1,1), ""*"",""""), """") ) ) ) "),"") | W12: =IF(A12="", "", IF(G12<=-15%, "Strong Buy", IF(G12<0%, "Buy", IF(G12<=15%, "Expensive", "Overrated")))) -> Strong Buy
A13: CVX | B13: =IFERROR(__xludf.DUMMYFUNCTION("IF(ISBLANK(A13),"""", googlefinance(A13, ""name""))"),"Chevron Corp") -> Chevron Corp | C13: =IFERROR(__xludf.DUMMYFUNCTION("IF(ISBLANK(A13),"""", googlefinance(A13, ""price""))"),189.9) -> 189.9 | D13: =IF(ISBLANK(A13),"",IFERROR(VLOOKUP(A13, 'Intrinsic Values List'!$A$2:$D$70, 4, FALSE), "Not Found" )) -> 214.15 | E13: =IF(ISBLANK(A13),"",IFERROR(VLOOKUP(A13, 'Intrinsic Values List'!$A$2:$G$70, 7, FALSE), "Not Found" )) -> 5.26 | F13: Low | G13: =IF(ISBLANK(D13),"", IFERROR((C13-D13)/D13,"")) -> -0.11323838 | H13: =IFERROR(__xludf.DUMMYFUNCTION("IFERROR(googlefinance(A13,""change""),"""")"),3.87) -> 3.87 | I13: =IFERROR(__xludf.DUMMYFUNCTION("iferror(GOOGLEFINANCE(A13,""changepct"")/100,"""")"),0.0208) -> 0.0208 | J13: =IFERROR(__xludf.DUMMYFUNCTION("IF(ISBLANK(A13),"""", googlefinance(A13, ""low52""))"),132.04) -> 132.04 | K13: =IFERROR(__xludf.DUMMYFUNCTION("IF(ISBLANK(A13),"""",IFERROR(SPARKLINE((C13-J13)/(L13-J13),{""charttype"",""bar"";""max"",1;""min"",0;""color1"",""2c79b5""}),""n/a""))"),"") | L13: =IFERROR(__xludf.DUMMYFUNCTION("IF(ISBLANK(A13),"""", googlefinance(A13, ""high52""))"),191.56) -> 191.56 | M13: Stocks | N13: Energy | O13: Value Stocks | P13: =IFERROR(__xludf.DUMMYFUNCTION("IF(ISBLANK(A13),"""", googlefinance(A13, ""PE""))"),28.66) -> 28.66 | Q13: =IFERROR(__xludf.DUMMYFUNCTION("IF(ISBLANK(A13),"""", googlefinance(A13, ""eps""))"),6.63) -> 6.63 | R13: =IFERROR(__xludf.DUMMYFUNCTION("IfError(IF(isblank(A13),"""",split(V13, ""()"")))"),6.91) -> 6.91 | S13: =IFERROR(__xludf.DUMMYFUNCTION("""COMPUTED_VALUE"""),0.0364) -> 0.0364 | T13: =IF(ISBLANK(A13),"", (R13*100)) -> 691 | U13: =IF(ISBLANK(A13),"", C13*100) -> 18990 | V13: =IFERROR(__xludf.DUMMYFUNCTION("LET(t, A13, IF(t="""","""", IFERROR( SUBSTITUTE( INDEX( IMPORTXML( ""https://finviz.com/quote.ashx?t=""&t&""&ty=dv"", ""(//td[normalize-space()='Dividend TTM' or contains(.,'Dividend TTM')]/following-s"&"ibling::td[1])[1]"" ),1,1), ""*"",""""), IFERROR( SUBSTITUTE( INDEX( IMPORTXML( ""https://finviz.com/quote.ashx?t=""&t, ""(//td[normalize-space()='Dividend']/following-sibling"&"::td[1])[1]"" ),1,1), ""*"",""""), """") ) ) ) "),"6.91 (3.64%)") -> 6.91 (3.64%) | W13: =IF(A13="", "", IF(G13<=-15%, "Strong Buy", IF(G13<0%, "Buy", IF(G13<=15%, "Expensive", "Overrated")))) -> Buy
